Workbook

Sheet 0_GUIA_INTRO
B3: CUDI - Bienestar Animal
B4: Modelo de Flujos de Caja, Escenarios y Plan de Control
B5: Versión Académica y Profesional v6.1.7 (Optimizada en Español)
B7: ÍNDICE DEL MODELO FINANCIERO
B9: 0_GUIA_INTRO | C9: Portada, manual de colores e índice del simulador.
B10: 1_PANEL_CONTROL | C10: Panel central para la configuración manual de todo el modelo excel.
B11: 2_AJUSTES_MACRO | C11: Configuración de variables macro: WACC, Impuestos y periodos de amortización CAPEX.
B12: 3_HIPOTESIS_NEGOCIO | C12: Supuestos de negocio editables (Tarifas, Conversión, Churn, Costes AWS/Stripe/APIs).
B13: 4_PROY_DEMANDA | C13: Proyección mensual de demanda por producto para 3 escenarios en paralelo.
B14: 15_DASHBOARD_KPI | C14: Dashboard interactivo con selector de escenario y visualización de KPIs en tiempo real.
B15: 12_ANALISIS_ESCENARIOS | C15: Matriz comparativa de 3 escenarios (Negativo, Equilibrio y Positivo) a 3 años.
B16: 5_DETALLE_INGRESOS | C16: Proyección mensual de tráfico, CAC, altas, bajas de usuarios y desglose de monetización.
B17: 6_COSTES_COGS | C17: Desglose de costes directos asociados a la venta del servicio y del hardware (Smart Collar).
B18: 7_EQUIPO_RRHH | C18: Planificación mensual de nóminas bajo el modelo legal español/catalán (cotizaciones y topes).
B19: 8_COSTES_OPEX | C19: Gastos de estructura recurrentes (Coworking, software SaaS, SEO, eventos y marketing digital).
B20: 9_FLUJO_CAJA | C20: Detalle de inversiones iniciales, amortización mensual y estado de flujos de caja consolidado.
... B25: 17_ANALISIS_GRAFICO | C25: Dashboard ejecutivo con gráficos visuales y resumen financiero para soporte de decisiones.
B26: CÓDIGO DE COLORES DEL SIMULADOR
B28: Azul Claro Sombreado | C28: Celdas de Entrada Manual de Datos. Son las únicas celdas editables.
B29: Gris Claro | C29: Encabezados de Tabla, Fórmulas de Suma o Etiquetas Informativas.
B30: Verde Suave | C30: Celdas de KPI Positivos o Flujo de Caja Acumulado Positivo.
B31: Rojo Suave | C31: Celdas de KPI Críticos o Flujo de Caja Acumulado Negativo.
B32: Azul Slate | C32: Fórmula de Selector de Escenarios Activos.
A34: GUÍA DE NAVEGACIÓN Y ESTRUCTURA DEL MODELO
A35: 1. CÓDIGO DE COLORES DEL PROYECTO CUDI: - 🟦 AZUL: Infraestructura y Servidores. Costes de alojamiento AWS y APIs de IA (Claude y Gemini). - 🟨 AMARILLO: Marketing y Adquisición. Pauta digital (Facebook/TikTok Ads), branding y comisiones de venta. - 🟧 NARANJA: Hardware y Fabricación. Costes de fabricación física y stockage de Smart Collars. - 🟩 VERDE: Distribución y Logística. Coste de envío urgente y última milla a dueños de mascotas. - 🟪 PÚRPURA: Recursos Humanos, Estructura y Coworking. Nóminas, RETA, asesores y alquileres de oficinas. 2. NAVEGACIÓN Y USO DEL SIMULADOR: - Utilice el selector de la pestaña '1_PANEL_CONTROL' (Celda C4) para cambiar dinámicamente el escenario activo del modelo. - Las hojas están ordenadas de forma lógica: supuestos iniciales, proyección de demanda, ingresos y costes detallados, estados financieros consolidados, y finalmente las herramientas de control y gráficos interactivos.

Sheet 1_PANEL_CONTROL
B2: PANEL CENTRAL DE CONTROL DE DATOS Y PARÁMETROS
B3: Modifique únicamente las celdas sombreadas en azul claro. Todo el modelo se actualizará automáticamente.
B4: ESCENARIO DE DEMANDA ACTIVO (1=Negativo, 2=Equilibrio, 3=Positivo): | C4: 2 | D4: ← CAMBIE ESTE VALOR
B5: =CHOOSE('1_PANEL_CONTROL'!$C$4, "[NEGATIVO] PANEL DE CONTROL en Escenario Negativo. Se estiman bajas tasas de crecimiento (5%) y conversión (2,13%), con churn elevado (8%).", "[EQUILIBRIO] PANEL DE CONTROL en Escenario Equilibrio. Base del proyecto para break-even: 8% crecimiento, 2,00% conversión, 4,8% churn.", "[POSITIVO] PANEL DE CONTROL en Escenario Positivo. Supuestos optimistas: 15% crecimiento, 8% conversión, 3% churn.") -> [EQUILIBRIO] PANEL DE CONTROL en Escenario Equilibrio. Base del proyecto para break-even: 8% crecimiento, 2,00% conversión, 4,8% churn.
B6: 1. VARIABLES MACROECONÓMICAS Y FINANCIERAS
B7: Tasa de Impuesto sobre Sociedades | C7: 0.21 | D7: Tasa impositiva española para sociedades limitadas
B8: Tasa de Descuento (WACC) | C8: 0.1179 | D8: Costo promedio ponderado de capital para descontar flujos
B9: Valor Terminal de Salida | C9: 42000000 | D9: Valor terminal estimado del negocio al final del periodo
B10: Periodo de Amortización CAPEX (Meses) | C10: 60 | D10: Periodo en meses para amortizar las inversiones (5 Años de vida útil)
B11: Reserva Mínima de Caja | C11: 500 | D11: Saldo mínimo de seguridad requerido en caja de la empresa
B12: Tasa de Inflación Anual | C12: 0.03 | D12: Tasa de inflación anual proyectada para ajustar costes
B14: 2. SUSCRIPCIONES Y PRECIOS DE PRODUCTOS
B15: Precio Suscripción Premium Care CUDI (SaaS) | C15: 30 | D15: Cuota mensual del plan Premium Care
B16: Precio Venta Smart Collar (Hardware) | C16: 89.5 | D16: Precio de venta al público del dispositivo GPS
B17: Precio Seguro CUDI Shield Basic | C17: 18 | D17: Seguro de co-distribución mensual
B18: Precio Visita VetHome CUDI | C18: 75 | D18: Mensualidad de visita médica presencial a domicilio
B19: Ticket Medio Transacción Marketplace | C19: 25 | D19: Valor promedio de servicios del marketplace (paseos/estética)
B20: Comisión Marketplace (%) | C20: =CHOOSE('1_PANEL_CONTROL'!$C$4, 0.1, 0.15, 0.15) -> 0.15 | D20: Comisión (take-rate) dinámica según escenario (10%/15%/15%)
B21: Comisión Media Neta Marketplace (EUR) | C21: =C19*C20 -> 3.75 | D21: Cálculo de comisión neta por transacción en marketplace
B23: 3. COSTES DIRECTOS Y VARIABLES (COGS)
B24: Coste Fabricación Smart Collar (Hardware) | C24: 35 | D24: Coste unitario puesto en almacén (Landed Cost: incluye flete internacional y arancel UE del 3.7%)
B25: Coste de Mensajería y Envío Última Milla | C25: 6.5 | D25: Coste de transporte express para el collar
B26: Servidor AWS por cliente activo | C26: 0.6 | D26: Servidores e IoT Cloud mensual por usuario Premium
B27: Comisión Pasarela Pago (Stripe %) | C27: 0.025 | D27: Tasa de procesamiento de cobros recurrentes de Stripe
B28: Tarifa Fija API Gemini Flash | C28: 100 | D28: SaaS mensual fijo para el asistente IA Freemium
B29: API Claude Sonnet por cliente activo | C29: 0.37 | D29: Costo de procesamiento mensual del Gemelo Digital
B31: 4. PARÁMETROS LEGALES DE PERSONAL Y SALARIOS
B32: Esquema de Pagas Ordinarias (12 o 14) | C32: 12 | D32: Pagas mensuales (12 o 14 pagas reguladas por convenio)
B33: Seguridad Social a Cargo de la Empresa (%) | C33: 0.321 | D33: Carga patronal (CC, Desempleo, FOGASA, Accidentes, MEEI) | E33: Cuota RETA General | F33: 448.69
B34: Seguridad Social a Cargo del Empleado (%) | C34: 0.0647 | D34: Deducción de nómina al trabajador (CC, FP, MEEI) | E34: Cuota RETA Tarifa Plana | F34: 88.56
B35: Base Máxima de Cotización Mensual (Tope) | C35: 4720.5 | D35: Tope de cotización para salarios altos en España
B36: Base Mínima de Cotización SMI Mensual | C36: 1300 | D36: Salario Mínimo Interprofesional base
B38: Puesto / Rol | C38: Salario Bruto Anual | D38: Mes Inicio | E38: IRPF Estimado %
B39: CEO (Socio Fundador) | C39: 18000 | D39: 1 | E39: 0.15
B40: CTO (Socio Fundador) | C40: 18000 | D40: 1 | E40: 0.15
B41: CMO (Socio Fundador) | C41: 18000 | D41: 1 | E41: 0.15
B42: COO (Socio Fundador) | C42: 18000 | D42: 1 | E42: 0.15
B43: Senior Software & Cloud Eng. | C43: 45000 | D43: 13 | E43: 0.15
B44: Customer Success Specialist | C44: 24000 | D44: 13 | E44: 0.14
B45: Sales & Marketing B2B Spec. | C45: 30000 | D45: 13 | E45: 0.15
B46: Operations & Logistics Mgr | C46: 28000 | D46: 19 | E46: 0.15
B48: 5. GASTOS ESTRUCTURALES Y COMERCIALES (OPEX)
B49: Alquiler Coworking Aticco Bogatell (6 Puestos) | C49: 2160 | D49: Alquiler mensual de espacio físico en Barcelona
B50: Comunicaciones Móviles (Equipo de Campo) | C50: 100 | D50: Telefonía e internet móvil Orange 5G para 4 reps
B51: Licencia ChatGPT Team (Servicios de IA) | C51: 112 | D51: Acceso a modelos avanzados de IA ChatGPT para equipo
B52: Google Workspace (Correo y Colaboración) | C52: 60 | D52: 6 licencias Enterprise
B53: HubSpot Sales Hub Professional (CRM Ventas) | C53: 400 | D53: Licencias B2B para pipeline de 4 comerciales
B54: Mixpanel & GA4 Pro (Analítica de App) | C54: 224.4 | D54: Tracking de conversión y comportamiento de usuarios
B55: n8n Cloud Pro (Automatización Interna) | C55: 50 | D55: Servicios en la nube de workflows automatizados
B56: Almacén OhMyBox Poblenou (Stock de Collars) | C56: 187 | D56: Alquiler mensual de trastero para almacenamiento
B57: Seguro Stock Póliza OhMyBox (Hasta 7500 €) | C57: 49.5 | D57: Cobertura para stock de hardware almacenado
B58: SEO Frontend Developer (SEO Técnico) | C58: 400 | D58: Mantenimiento SEO y de velocidad en web
B59: Redactor Médico Veterinario (EEAT Content) | C59: 400.05 | D59: Creación de contenidos médicos veterinarios fiables
B60: Especialista SEO (Linkbuilding) | C60: 400.05 | D60: Servicios mensuales de estrategia SEO off-page
... B83: Stand Modular Congreso AVEPA-SEVC (Mes 10) | C83: 1800 | D83: Stand modular Congreso AVEPA CCIB Barcelona (M10)
B85: 6. INVERSIONES INICIALES (CAPEX MES 1)
B86: Equipos Informáticos (MacBooks Pro Dev/CTO) | C86: 10196 | D86: Equipamiento de hardware técnico para desarrollo
B87: Desarrollo de la Plataforma (Backend/App/UI) | C87: 17150 | D87: Frontend, backend, prototipado e integración API CUDI
B88: Licencias y Setup Inicial (CRM Onboarding) | C88: 1500 | D88: HubSpot Onboarding Professional Fee (Desembolso Único)
B89: Registro de Propiedad Industrial (Marca OEPM) | C89: 0 | D89: Registro de marca (Costo consolidado en línea 90)
B90: Cumplimiento de Privacidad y RGPD (Adaptación) | C90: 15000 | D90: CAPEX Regulatorio y Tecnológico (Homologación CE, Bluetooth, OEPM, RGPD)
B91: Homologación y Certificación de Hardware (CE) | C91: 0 | D91: Certificación de collar (Costo consolidado en línea 90)
B93: 7. PARÁMETROS DE FINANCIACIÓN (DEUDA Y SOCIOS)
B94: Préstamo ENISA Principal | C94: 75000 | D94: SÍ | E94: Préstamo público de fomento a startups (M1)
B95: Préstamo ENISA Interés Anual | C95: 0.06 | E95: Tasa de interés aplicada al préstamo
B96: Préstamo ENISA Carencia de Principal (Meses) | C96: 12 | E96: Periodo inicial de carencia de amortización
B97: Préstamo ENISA Periodo de Repago (Meses) | C97: 48 | E97: Plazo de amortización de principal en meses
B98: RBF Financiación Basada en Ingresos Principal | C98: 35000 | D98: SÍ | E98: Financiación basada en ingresos (M1)
B99: RBF % de Repago Mensual sobre Ventas | C99: 0.05 | E99: Porcentaje de facturación para repagar el RBF
B100: RBF Cap de Repago Total (Múltiplo) | C100: 1.15 | E100: Límite máximo de repago total (Múltiplo de principal)
B101: RBF Repago Total Máximo (Cap) | C101: =IF(D98="SÍ", C98*C100, 0) -> 40250 | E101: Cálculo del repago acumulado límite total (C98*C100 si activo)
B102: Bootstrap Capital Inicial de Socios | C102: =SUMIF(D108:D111,"SÍ",C108:C111) -> 60000 | E102: Capital total fundadores en Escenario 1 (Suma de socios activos)
B103: Híbrido Capital Fundadores | C103: =SUMIF(D108:D111,"SÍ",C108:C111) -> 60000 | E103: Capital total fundadores en Escenario 2 (Suma de socios activos)
B104: Híbrido Capital Business Angels (BA) | C104: 80000 | D104: SÍ | E104: Capital aportado por BA en Escenario 2 (Sustituye deuda)
B105: VC Capital Fundadores | C105: =SUMIF(D108:D111,"SÍ",C108:C111) -> 60000 | E105: Capital total fundadores en Escenario 3 (Suma de socios activos)
B106: VC Capital Venture Capital (VC) | C106: 110000 | D106: SÍ | E106: Capital institucional en Escenario 3 (Sustituye deuda)
B107: VC Capital Equity Crowdfunding | C107: 20000 | D107: SÍ | E107: Capital micromecenazgo en Escenario 3
B108: Aporte Fundador CEO (Socio 1) | C108: 15000 | D108: SÍ | E108: Aportación de capital individual del CEO
B109: Aporte Fundador COO (Socio 2) | C109: 15000 | D109: SÍ | E109: Aportación de capital individual del COO
B110: Aporte Fundador CTO (Socio 3) | C110: 15000 | D110: SÍ | E110: Aportación de capital individual del CTO
B111: Aporte Fundador CMO (Socio 4) | C111: 15000 | D111: SÍ | E111: Aportación de capital individual del CMO
B113: 8. ESTRUCTURA DE INGRESOS B2B Y AFILIADOS
B114: SaaS Clínicas - Escenario Negativo (EUR/mes) | C114: 60 | D114: Cuota SaaS Clínicas en escenario negativo
B115: SaaS Clínicas - Escenario Equilibrio (EUR/mes) | C115: 80 | D115: Cuota SaaS Clínicas en escenario moderado
B116: SaaS Clínicas - Escenario Positivo (EUR/mes) | C116: 100 | D116: Cuota SaaS Clínicas en escenario optimista
B117: Suscripción Petme Negocios (EUR/mes) | C117: 39.99 | D117: SaaS B2B para profesionales locales (paseadores/estéticas)
B118: Insurtech - Tasa Lead - Escenario Negativo | C118: 0.1 | D118: Porcentaje de usuarios que consienten lead en Esc 1
B119: Insurtech - Tasa Lead - Escenario Equilibrio | C119: 0.25 | D119: Porcentaje de usuarios que consienten lead en Esc 2
B120: Insurtech - Tasa Lead - Escenario Positivo | C120: 0.25 | D120: Porcentaje de usuarios que consienten lead en Esc 3
B121: Insurtech - CPL Lead - Escenario Negativo | C121: 10 | D121: Tarifa por lead cualificado en Esc 1
B122: Insurtech - CPL Lead - Escenario Equilibrio | C122: 22 | D122: Tarifa por lead cualificado en Esc 2
B123: Insurtech - CPL Lead - Escenario Positivo | C123: 22 | D123: Tarifa por lead cualificado en Esc 3
B124: Insurtech - Tasa Conversión Póliza - Esc 1 | C124: 0.3 | D124: Tasa de conversión de lead a póliza en Esc 1
B125: Insurtech - Tasa Conversión Póliza - Esc 2 | C125: 0.5 | D125: Tasa de conversión de lead a póliza en Esc 2
... B135: Ads - Rendimiento Mensual por Usuario (EUR) | C135: 0.18 | D135: Ingreso estimado por usuario Freemium activo
B137: 9. PARÁMETROS DE SUSCRIPCIÓN ANTICIPADA (PREPAGO)
B138: Porcentaje Clientes Prepago Anual | C138: =CHOOSE('1_PANEL_CONTROL'!$C$4, 0, 0.3, 0.3) -> 0.3 | D138: Porcentaje de clientes que eligen pago anual anticipado (0% en Esc 1, 30% en Esc 2/3)
B139: Descuento Prepago Anual (%) | C139: =CHOOSE('1_PANEL_CONTROL'!$C$4, 0, 0.15, 0.15) -> 0.15 | D139: Descuento aplicado sobre la suscripción mensual (0% en Esc 1, 15% en Esc 2/3)
B141: GUÍA DEL PANEL DE CONTROL Y CONFIGURADOR DE ESCENARIOS
B142: 1. SELECTOR DINÁMICO DE ESCENARIOS (Celda C4): - 🔴 Escenario 1 (Negativo): Menor conversión (2.13%), mayor churn (8.00%) y CPL elevado. Pérdidas recurrentes. - 🟡 Escenario 2 (Equilibrio - Target): Hipótesis base calibradas. CVR del 3.8% total, churn del 4.80% y break-even en Año 2. - 🟢 Escenario 3 (Positivo): Tracción exponencial financiada por Venture Capital y baja fricción comercial. 2. CONFIGURACIÓN DE PRECIOS Y PARÁMETROS CLAVE: - Smart Collar PVP: Fijado en 89,50 € para eliminar subsidios (Margen bruto del 53.63% frente a Landed Cost de 41,50 €). - Suscripción Premium Care: Tarifa base de 30,00 €/mes (con 15% de descuento en prepago anual a 25,50 €/mes). - Seguros (CUDI Shield): Attach rate del 30% de la base activa a una comisión de corretaje del 30% mensual.

Sheet 2_AJUSTES_MACRO
B2: CONFIGURACIÓN GENERAL (MACRO) | E2: Escenario Activo: | F2: =CHOOSE('1_PANEL_CONTROL'!$C$4, "🔴 1: NEGATIVO", "🟡 2: EQUILIBRIO", "🟢 3: POSITIVO") -> 🟡 2: EQUILIBRIO
B3: =CHOOSE('1_PANEL_CONTROL'!$C$4, "[NEGATIVO] VARIABLES MACRO DE AJUSTE. Se aplica 21% de impuestos y 11,79% WACC. En este escenario adverso de menor liquidez, controlar la caja es crítico.", "[EQUILIBRIO] VARIABLES MACRO DE AJUSTE. Estructura de capital híbrido (WACC 11,79%). Caja inicial recomendada de " & TEXT('13_CAP_TABLE_FINANCIACION'!C15, "#.##0 €") & " con apoyo ENISA.", "[POSITIVO] VARIABLES MACRO DE AJUSTE. Estructura de Venture Capital (WACC 11,79%). Caja inicial óptima de " & TEXT('13_CAP_TABLE_FINANCIACION'!C15, "#.##0 €") & " para desarrollo intensivo.") -> [EQUILIBRIO] VARIABLES MACRO DE AJUSTE. Estructura de capital híbrido (WACC 11,79%). Caja inicial recomendada de 215.000 € con apoyo ENISA.
B4: Valor Terminal de Salida | C4: ='1_PANEL_CONTROL'!$C$9 -> 42000000 | D4: Valor terminal estimado para valoración de salida
B5: Tasa de Descuento (WACC) | C5: ='1_PANEL_CONTROL'!$C$8 -> 0.1179 | D5: Tasa de descuento de flujos de caja
B6: Tasa Impositiva (Sociedades) | C6: ='1_PANEL_CONTROL'!$C$7 -> 0.21 | D6: Tasa de impuesto sobre sociedades en España
B7: Inicio Año Fiscal (Mes) | C7: 1 | D7: Mes de inicio del año fiscal (Enero = 1)
B8: Reserva Mínima de Caja | C8: ='1_PANEL_CONTROL'!$C$11 -> 500 | D8: Reserva de seguridad mínima en caja
B9: Tasa de Inflación Anual | C9: ='1_PANEL_CONTROL'!$C$12 -> 0.03 | D9: Tasa de inflación anual proyectada
B12: PERIODOS DE AMORTIZACIÓN DE CAPEX
B14: Equipos Informáticos / Hardware | C14: ='1_PANEL_CONTROL'!$C$10/12 -> 5 | D14: Años | Amortización de ordenadores en años
B15: Reforma de Oficina / Coworking | C15: 5 | D15: Años | 20.0% anual
B16: Mobiliario y Enseres | C16: 5 | D16: Años | 20.0% anual
B17: Telecomunicaciones | C17: 3 | D17: Años | 33.3% anual
B18: Infraestructura de Servidores & Apps | C18: ='1_PANEL_CONTROL'!$C$10/12 -> 5 | D18: Años | Desarrollo plataforma CUDI
B20: GUÍA DE CONFIGURACIÓN MACROECONÓMICA Y PARÁMETROS FISCALES
B21: 1. SUPUESTOS MACRO Y FISCALES: - IPC / Ajuste Salarial: Aplicado un 3.50% de ajuste por inflación en Años 2 y 3 para la masa salarial. - Impuesto de Sociedades: Modelado al 21.00% según la legislación vigente en España para startups. - RETA (Autónomos): Tarifa plana de 88,56 €/mes en Año 1 para cofundadores, escalando a cuota regular en Año 2. - Seguridad Social Empresa: 32.10% para el personal contratado por cuenta ajena (Régimen General). 2. TASA DE DESCUENTO E INVERSIÓN: - WACC de Descuento: Fijado en 11.79% para el cálculo de VAN/TIR, ponderando el coste de deuda y equity.

Sheet 3_HIPOTESIS_NEGOCIO
B2: SUPUESTOS OPERATIVOS DEL NEGOCIO (ESCENARIO ACTIVO) | E2: Escenario Activo: | F2: =CHOOSE('1_PANEL_CONTROL'!$C$4, "🔴 1: NEGATIVO", "🟡 2: EQUILIBRIO", "🟢 3: POSITIVO") -> 🟡 2: EQUILIBRIO
B3: =CHOOSE('1_PANEL_CONTROL'!$C$4, "[NEGATIVO] SUPUESTOS OPERATIVOS DEL NEGOCIO. Tasas activas del escenario. Churn elevado del " & TEXT('3_HIPOTESIS_NEGOCIO'!C6, "0,0%") & " y coste de captación CPL de " & TEXT('3_HIPOTESIS_NEGOCIO'!C20, "0,00 €") & " dificultan la rentabilidad.", "[EQUILIBRIO] SUPUESTOS OPERATIVOS DEL NEGOCIO. Tasas activas del escenario. Churn moderado del " & TEXT('3_HIPOTESIS_NEGOCIO'!C6, "0,0%") & " y CPL de " & TEXT('3_HIPOTESIS_NEGOCIO'!C20, "0,00 €") & " para el break-even.", "[POSITIVO] SUPUESTOS OPERATIVOS DEL NEGOCIO. Tasas activas del escenario. Tracción muy alta con churn del " & TEXT('3_HIPOTESIS_NEGOCIO'!C6, "0,0%") & " y CPL de " & TEXT('3_HIPOTESIS_NEGOCIO'!C20, "0,00 €") & " (alta eficiencia de Ads).") -> [EQUILIBRIO] SUPUESTOS OPERATIVOS DEL NEGOCIO. Tasas activas del escenario. Churn moderado del 4,8% y CPL de 11,00 € para el break-even.
B4: Tasa Conversión (Visita a Premium) | C4: ='4_PROY_DEMANDA'!$D$73 -> 0.02 | D4: Tasa de conversión en el escenario activo
B5: Precio Premium Care CUDI (SaaS) | C5: ='1_PANEL_CONTROL'!$C$15 -> 30 | D5: Membresía recurrente mensual del plan Premium Care
B6: Tasa Cancelación Mensual (Churn) | C6: ='4_PROY_DEMANDA'!$D$80 -> 0.048 | D6: Tasa de bajas del plan Premium Care
B7: CAC Teórico (Lead Orgánico) | C7: 5 | D7: Costo implícito de adquisición orgánico (SEO y RRSS)
B8: Tráfico Orgánico Inicial (Mes 1) | C8: ='4_PROY_DEMANDA'!$D$72 -> 2027 | D8: Tráfico inicial mensual orgánico de la web
B9: Crecimiento Tráfico Orgánico Mensual | C9: ='4_PROY_DEMANDA'!$D$71 -> 0.08 | D9: Tasa de crecimiento mensual del tráfico orgánico
B10: Tasa Adhesión CUDI Shield Basic | C10: ='4_PROY_DEMANDA'!$D$82 -> 0.3 | D10: Porcentaje de adhesión del seguro CUDI Shield
B11: Precio CUDI Shield Basic (Seguro) | C11: ='1_PANEL_CONTROL'!$C$17 -> 18 | D11: Mensualidad del Seguro CUDI Shield
B12: Tasa Visitas VetHome Mensuales | C12: ='4_PROY_DEMANDA'!$D$85 -> 0.045 | D12: Tasa mensual de visitas VetHome por usuario Premium
B13: Precio Visita VetHome CUDI | C13: ='1_PANEL_CONTROL'!$C$18 -> 75 | D13: Precio cobrado por visita veterinaria a domicilio
B14: Tasa Compras en Marketplace | C14: ='4_PROY_DEMANDA'!$D$87 -> 0.2 | D14: Porcentaje de compras de la base Premium en marketplace
B15: Comisión Media Marketplace | C15: ='1_PANEL_CONTROL'!$C$21 -> 3.75 | D15: Comisión neta promedio ganada por transacción
B16: Mes Inicio Pauta Publicitaria | C16: 1 | D16: Mes en que se inicia la captación de pago (Ene-26 = 1)
B17: Presupuesto Publicitario Social Ads | C17: ='1_PANEL_CONTROL'!$C$80 -> 2000 | D17: Presupuesto plano constante de Meta/TikTok Ads
B18: Incremento Mensual del Presupuesto | C18: 0 | D18: Estrategia de inversión plana (no incremental)
B19: Presupuesto Publicitario Máximo | C19: ='1_PANEL_CONTROL'!$C$80 -> 2000 | D19: Techo de la inversión publicitaria mensual
B20: Coste por Lead de Pago (CPL) | C20: ='4_PROY_DEMANDA'!$D$76 -> 11 | D20: Coste de captación del lead publicitario
B21: Coste Servidor AWS por cliente activo | C21: ='1_PANEL_CONTROL'!$C$26 -> 0.6 | D21: Costo mensual de base de datos e IoT por cliente activo
B22: Comisión Pasarela Pago (Stripe %) | C22: ='1_PANEL_CONTROL'!$C$27 -> 0.025 | D22: Comisión Stripe por procesamiento de cobros
B23: Tarifa Fija API Gemini Flash | C23: ='1_PANEL_CONTROL'!$C$28 -> 100 | D23: Coste de la suite de chat de asistencia Freemium
B24: API Claude Sonnet por usuario | C24: ='1_PANEL_CONTROL'!$C$29 -> 0.37 | D24: Coste de API mensual del Gemelo Digital
B25: Coste Fabricación Smart Collar | C25: ='1_PANEL_CONTROL'!$C$24 -> 35 | D25: Costo unitario de fabricación del hardware
B26: Coste de Mensajería Última Milla | C26: ='1_PANEL_CONTROL'!$C$25 -> 6.5 | D26: Costo de envío urgente nacional del collar a domicilio
B28: ESTRATEGIA GLOBAL DE MARKETING (TFM CUDI 2026) - ENFOQUE ADQUISICIÓN Y RETENCIÓN B2C/B2B
B29: La estrategia global de marketing de CUDI se basa en un modelo Inbound Omnicanal con fuerte enfoque en coste de adquisición de cliente (CAC) controlado y posicionamiento de marca de confianza (E-E-A-T): 1. ADQUISICIÓN ORGÁNICA (EEAT SEO & CONTENIDOS): Se destina un redactor médico veterinario dedicado para generar contenidos de salud, comportamiento y nutrición animal avalados profesionalmente. Esto posiciona a CUDI en buscadores para keywords transaccionales locales de Barcelona, atrayendo tráfico de alta intención a coste marginal cero. 2. ALIANZAS CON LA RED DE SOCIOS B2B: Se establece una red de clínicas veterinarias, peluquerías caninas, paseadores y guarderías de confianza en Barcelona. CUDI distribuye welcome packs físicos a través de estos partners, quienes prescriben la suscripción Premium Care y el collar GPS en sus locales a cambio de comisiones (take-rate). 3. PAUTA PUBLICITARIA DIGITAL (PERFORMANCE ADS): Estrategia plana 'Always-on' de 2.000 €/mes en Meta Ads (Instagram/Facebook) y TikTok Ads. Se divide el funnel en: Fase de Branding (Creatividades fijas e historias de éxito), Fase de Captación de Leads (Descarga de e-books de salud canina), y Fase de Remarketing (BOFU retargeting con cupones de descuento del Smart Collar) para maximizar la conversión. 4. EVENTOS Y MARKETING DE GUERRILLA B2B/B2C: Presencia en ferias y congresos clave del sector pet-tech y veterinario (como Iberzoo+Propet en IFEMA y el Congreso AVEPA-SEVC en el CCIB de Barcelona) mediante stands modulares diseñados para captar distribuidores y clínicas asociadas a gran escala. 5. AUTOMATIZACIÓN INBOUND CRM (HUBSPOT): Nutrición automatizada de leads (lead nurturing) mediante correos electrónicos segmentados por tipo de mascota, edad y nivel de actividad, forzando la conversión recurrente a Premium.
B37: GUÍA DE HIPÓTESIS DE NEGOCIO Y CONVERSIÓN
B38: 1. HIPÓTESIS DE ADQUISICIÓN Y MARKETING: - Crecimiento Tráfico Orgánico: Inicia en 1.000 visitas/mes y crece del 5% al 15% según el escenario activo. - Coste por Lead (CPL) y Ads: Presupuesto publicitario plano de 2.000 €/mes con CPL variable por escenario (7 € a 15 €). - Conversión Web: Se asume que el 2.00% del tráfico general se convierte en Lead Calificado. 2. RETENCIÓN Y VIDA ÚTIL (LTV): - Tasa de Churn Mensual: Factor crítico de retención, calibrado en 4.80% para el escenario de Equilibrio. - Vida Útil Media (Lifetime): Calculada como 1 / Churn Rate, equivaliendo a 20.83 meses de retención en Equilibrio.

Sheet 4_PROY_DEMANDA
A4: PROYECCIONES DE DEMANDA POR ESCENARIO (84 MESES) | E4: Escenario Activo: | F4: =CHOOSE('1_PANEL_CONTROL'!$C$4, "🔴 1: NEGATIVO", "🟡 2: EQUILIBRIO", "🟢 3: POSITIVO") -> 🟡 2: EQUILIBRIO
A5: =CHOOSE('1_PANEL_CONTROL'!$C$4, "[NEGATIVO] PROYECCIÓN DE DEMANDA MENSUAL. En el mes 12 alcanzamos solo " & TEXT('4_PROY_DEMANDA'!O21, "#.##0") & " usuarios activos en Premium Care, generando un total de " & TEXT('4_PROY_DEMANDA'!O23, "#.##0") & " clientes en seguros Shield.", "[EQUILIBRIO] PROYECCIÓN DE DEMANDA MENSUAL. En el mes 12 alcanzamos el hito de " & TEXT('4_PROY_DEMANDA'!O41, "#.##0") & " usuarios Premium Care y " & TEXT('4_PROY_DEMANDA'!O43, "#.##0") & " asegurados.", "[POSITIVO] PROYECCIÓN DE DEMANDA MENSUAL. En el mes 12 logramos los " & TEXT('4_PROY_DEMANDA'!O61, "#.##0") & " usuarios activos y vendemos " & TEXT(SUM('4_PROY_DEMANDA'!D64:O64), "#.##0") & " Smart Collars en Año 1.") -> [EQUILIBRIO] PROYECCIÓN DE DEMANDA MENSUAL. En el mes 12 alcanzamos el hito de 670 usuarios Premium Care y 201 asegurados.
A8: Métrica de Demanda | B8: Unidad | C8: Escenario / Regla | D8: Ene-26 | E8: Feb-26 | F8: Mar-26 | G8: Abr-26 | H8: May-26 | I8: Jun-26 | J8: Jul-26 | K8: Ago-26 | L8: Sep-26 | M8: Oct-26 | N8: Nov-26 | O8: Dic-26 | P8: Ene-27 | Q8: Feb-27 | R8: Mar-27 | S8: Abr-27 | T8: May-27 | U8: Jun-27 | V8: Jul-27 | W8: Ago-27 | X8: Sep-27 | Y8: Oct-27 | Z8: Nov-27 | AA8: Dic-27 | AB8: Ene-28 | AC8: Feb-28 | AD8: Mar-28 | AE8: Abr-28 | AF8: May-28 | AG8: Jun-28 | AH8: Jul-28 | AI8: Ago-28 | AJ8: Sep-28 | AK8: Oct-28 | AL8: Nov-28 | AM8: Dic-28 | AN8: Ene-29 | AO8: Feb-29 | AP8: Mar-29 | AQ8: Abr-29 | AR8: May-29 | AS8: Jun-29 | AT8: Jul-29 | AU8: Ago-29 | AV8: Sep-29 | AW8: Oct-29 | AX8: Nov-29 | AY8: Dic-29 | AZ8: Ene-30 | BA8: Feb-30 | BB8: Mar-30 | BC8: Abr-30 | BD8: May-30 | BE8: Jun-30 | BF8: Jul-30 | BG8: Ago-30 | BH8: Sep-30 | BI8: Oct-30 | BJ8: Nov-30 | BK8: Dic-30 | BL8: Ene-31 | BM8: Feb-31 | BN8: Mar-31 | BO8: Abr-31 | BP8: May-31 | BQ8: Jun-31 | BR8: Jul-31 | BS8: Ago-31 | BT8: Sep-31 | BU8: Oct-31 | BV8: Nov-31 | BW8: Dic-31 | BX8: Ene-32 | BY8: Feb-32 | BZ8: Mar-32 | CA8: Abr-32 | CB8: May-32 | CC8: Jun-32 | CD8: Jul-32 | CE8: Ago-32 | CF8: Sep-32 | CG8: Oct-32 | CH8: Nov-32 | CI8: Dic-32
A10: ESCENARIO 1: NEGATIVO
A11: Crecimiento Tráfico Orgánico | B11: % | C11: 0.05 | D11: 0.05 | E11: 0.05 | F11: 0.05 | G11: 0.05 | H11: 0.05 | I11: 0.05 | J11: 0.05 | K11: 0.05 | L11: 0.05 | M11: 0.05 | N11: 0.05 | O11: 0.05 | P11: 0.05 | Q11: 0.05 | R11: 0.05 | S11: 0.05 | T11: 0.05 | U11: 0.05 | V11: 0.05 | W11: 0.05 | X11: 0.05 | Y11: 0.05 | Z11: 0.05 | AA11: 0.05 | AB11: 0.05 | AC11: 0.05 | AD11: 0.05 | AE11: 0.05 | AF11: 0.05 | AG11: 0.05 | AH11: 0.05 | AI11: 0.05 | AJ11: 0.05 | AK11: 0.05 | AL11: 0.05 | AM11: 0.05 | AN11: 0.05 | AO11: 0.05 | AP11: 0.05 | AQ11: 0.05 | AR11: 0.05 | AS11: 0.05 | AT11: 0.05 | AU11: 0.05 | AV11: 0.05 | AW11: 0.05 | AX11: 0.05 | AY11: 0.05 | AZ11: 0.05 | BA11: 0.05 | BB11: 0.05 | BC11: 0.05 | BD11: 0.05 | BE11: 0.05 | BF11: 0.05 | BG11: 0.05 | BH11: 0.05 | BI11: 0.05 | BJ11: 0.05 | BK11: 0.05 | BL11: 0.05 | BM11: 0.05 | BN11: 0.05 | BO11: 0.05 | BP11: 0.05 | BQ11: 0.05 | BR11: 0.05 | BS11: 0.05 | BT11: 0.05 | BU11: 0.05 | BV11: 0.05 | BW11: 0.05 | BX11: 0.05 | BY11: 0.05 | BZ11: 0.05 | CA11: 0.05 | CB11: 0.05 | CC11: 0.05 | CD11: 0.05 | CE11: 0.05 | CF11: 0.05 | CG11: 0.05 | CH11: 0.05 | CI11: 0.05
A12: Tráfico Orgánico Mensual | B12: # | C12: M1=1000, Mt=Prev*(1+Growth) | D12: 1000 | E12: =D12*(1+E11) -> 1050 | F12: =E12*(1+F11) -> 1102.5 | G12: =F12*(1+G11) -> 1157.625 | H12: =G12*(1+H11) -> 1215.5063 | I12: =H12*(1+I11) -> 1276.2816 | J12: =I12*(1+J11) -> 1340.0956 | K12: =J12*(1+K11) -> 1407.1004 | L12: =K12*(1+L11) -> 1477.4554 | ... CI12: =CH12*(1+CI11) -> 57373.563
A13: Tasa de Conversión | B13: % | C13: 0.0213 | D13: 0.0213 | E13: 0.0213 | F13: 0.0213 | G13: 0.0213 | H13: 0.0213 | I13: 0.0213 | J13: 0.0213 | K13: 0.0213 | L13: 0.0213 | M13: 0.0213 | N13: 0.0213 | O13: 0.0213 | P13: 0.0213 | Q13: 0.0213 | R13: 0.0213 | S13: 0.0213 | T13: 0.0213 | U13: 0.0213 | V13: 0.0213 | W13: 0.0213 | X13: 0.0213 | Y13: 0.0213 | Z13: 0.0213 | AA13: 0.0213 | AB13: 0.0213 | AC13: 0.0213 | AD13: 0.0213 | AE13: 0.0213 | AF13: 0.0213 | AG13: 0.0213 | AH13: 0.0213 | AI13: 0.0213 | AJ13: 0.0213 | AK13: 0.0213 | AL13: 0.0213 | AM13: 0.0213 | AN13: 0.0213 | AO13: 0.0213 | AP13: 0.0213 | AQ13: 0.0213 | AR13: 0.0213 | AS13: 0.0213 | AT13: 0.0213 | AU13: 0.0213 | AV13: 0.0213 | AW13: 0.0213 | AX13: 0.0213 | AY13: 0.0213 | AZ13: 0.0213 | BA13: 0.0213 | BB13: 0.0213 | BC13: 0.0213 | BD13: 0.0213 | BE13: 0.0213 | BF13: 0.0213 | BG13: 0.0213 | BH13: 0.0213 | BI13: 0.0213 | BJ13: 0.0213 | BK13: 0.0213 | BL13: 0.0213 | BM13: 0.0213 | BN13: 0.0213 | BO13: 0.0213 | BP13: 0.0213 | BQ13: 0.0213 | BR13: 0.0213 | BS13: 0.0213 | BT13: 0.0213 | BU13: 0.0213 | BV13: 0.0213 | BW13: 0.0213 | BX13: 0.0213 | BY13: 0.0213 | BZ13: 0.0213 | CA13: 0.0213 | CB13: 0.0213 | CC13: 0.0213 | CD13: 0.0213 | CE13: 0.0213 | CF13: 0.0213 | CG13: 0.0213 | CH13: 0.0213 | CI13: 0.0213
A14: Nuevos Clientes (Orgánicos) | B14: # | C14: ROUND(Tráfico*Conversión, 0) | D14: =ROUND(D12*D13, 0) -> 21 | E14: =ROUND(E12*E13, 0) -> 22 | F14: =ROUND(F12*F13, 0) -> 23 | G14: =ROUND(G12*G13, 0) -> 25 | H14: =ROUND(H12*H13, 0) -> 26 | I14: =ROUND(I12*I13, 0) -> 27 | J14: =ROUND(J12*J13, 0) -> 29 | K14: =ROUND(K12*K13, 0) -> 30 | ... CI14: =ROUND(CI12*CI13, 0) -> 1222
A15: Presupuesto Social Ads | B15: EUR | C15: '1_PANEL_CONTROL'!$C$80 | D15: ='1_PANEL_CONTROL'!$C$80+'1_PANEL_CONTROL'!$C$69+'1_PANEL_CONTROL'!$C$68 -> 2955 | E15: ='1_PANEL_CONTROL'!$C$80+'1_PANEL_CONTROL'!$C$69+'1_PANEL_CONTROL'!$C$68 -> 2955 | F15: ='1_PANEL_CONTROL'!$C$80+'1_PANEL_CONTROL'!$C$69+'1_PANEL_CONTROL'!$C$68 -> 2955 | G15: ='1_PANEL_CONTROL'!$C$80+'1_PANEL_CONTROL'!$C$69+'1_PANEL_CONTROL'!$C$68 -> 2955 | H15: ='1_PANEL_CONTROL'!$C$80+'1_PANEL_CONTROL'!$C$69+'1_PANEL_CONTROL'!$C$68 -> 2955 | I15: ='1_PANEL_CONTROL'!$C$80+'1_PANEL_CONTROL'!$C$69+'1_PANEL_CONTROL'!$C$68 -> 2955 | J15: ='1_PANEL_CONTROL'!$C$80+'1_PANEL_CONTROL'!$C$69+'1_PANEL_CONTROL'!$C$68 -> 2955 | K15: ='1_PANEL_CONTROL'!$C$80+'1_PANEL_CONTROL'!$C$69+'1_PANEL_CONTROL'!$C$68 -> 2955 | ... CI15: ='1_PANEL_CONTROL'!$C$80+'1_PANEL_CONTROL'!$C$69+'1_PANEL_CONTROL'!$C$68 -> 2955
A16: CPL Paid (Coste por Lead) | B16: EUR | C16: 15.0 | D16: 15 | E16: 15 | F16: 15 | G16: 15 | H16: 15 | I16: 15 | J16: 15 | K16: 15 | L16: 15 | M16: 15 | N16: 15 | O16: 15 | P16: 15 | Q16: 15 | R16: 15 | S16: 15 | T16: 15 | U16: 15 | V16: 15 | W16: 15 | X16: 15 | Y16: 15 | Z16: 15 | AA16: 15 | AB16: 15 | AC16: 15 | AD16: 15 | AE16: 15 | AF16: 15 | AG16: 15 | AH16: 15 | AI16: 15 | AJ16: 15 | AK16: 15 | AL16: 15 | AM16: 15 | AN16: 15 | AO16: 15 | AP16: 15 | AQ16: 15 | AR16: 15 | AS16: 15 | AT16: 15 | AU16: 15 | AV16: 15 | AW16: 15 | AX16: 15 | AY16: 15 | AZ16: 15 | BA16: 15 | BB16: 15 | BC16: 15 | BD16: 15 | BE16: 15 | BF16: 15 | BG16: 15 | BH16: 15 | BI16: 15 | BJ16: 15 | BK16: 15 | BL16: 15 | BM16: 15 | BN16: 15 | BO16: 15 | BP16: 15 | BQ16: 15 | BR16: 15 | BS16: 15 | BT16: 15 | BU16: 15 | BV16: 15 | BW16: 15 | BX16: 15 | BY16: 15 | BZ16: 15 | CA16: 15 | CB16: 15 | CC16: 15 | CD16: 15 | CE16: 15 | CF16: 15 | CG16: 15 | CH16: 15 | CI16: 15
A17: Leads de Pago Adquiridos | B17: # | C17: ROUND(Presupuesto/CPL, 0) | D17: =ROUND(D15/D16, 0) -> 197 | E17: =ROUND(E15/E16, 0) -> 197 | F17: =ROUND(F15/F16, 0) -> 197 | G17: =ROUND(G15/G16, 0) -> 197 | H17: =ROUND(H15/H16, 0) -> 197 | I17: =ROUND(I15/I16, 0) -> 197 | J17: =ROUND(J15/J16, 0) -> 197 | K17: =ROUND(K15/K16, 0) -> 197 | ... CI17: =ROUND(CI15/CI16, 0) -> 197
A18: Nuevos Clientes (Pauta/Paid) | B18: # | C18: ROUND(Leads*Conversión, 0) | D18: =ROUND(D17*D13, 0) -> 4 | E18: =ROUND(E17*E13, 0) -> 4 | F18: =ROUND(F17*F13, 0) -> 4 | G18: =ROUND(G17*G13, 0) -> 4 | H18: =ROUND(H17*H13, 0) -> 4 | I18: =ROUND(I17*I13, 0) -> 4 | J18: =ROUND(J17*J13, 0) -> 4 | K18: =ROUND(K17*K13, 0) -> 4 | ... CI18: =ROUND(CI17*CI13, 0) -> 4
A19: Nuevos Clientes Totales | B19: # | C19: Orgánicos + Paid | D19: =D14+D18 -> 25 | E19: =E14+E18 -> 26 | F19: =F14+F18 -> 27 | G19: =G14+G18 -> 29 | H19: =H14+H18 -> 30 | I19: =I14+I18 -> 31 | J19: =J14+J18 -> 33 | K19: =K14+K18 -> 34 | ... CI19: =CI14+CI18 -> 1226
A20: Tasa Cancelación (Churn) | B20: % | C20: 0.08 | D20: 0.08 | E20: 0.08 | F20: 0.08 | G20: 0.08 | H20: 0.08 | I20: 0.08 | J20: 0.08 | K20: 0.08 | L20: 0.08 | M20: 0.08 | N20: 0.08 | O20: 0.08 | P20: 0.08 | Q20: 0.08 | R20: 0.08 | S20: 0.08 | T20: 0.08 | U20: 0.08 | V20: 0.08 | W20: 0.08 | X20: 0.08 | Y20: 0.08 | Z20: 0.08 | AA20: 0.08 | AB20: 0.08 | AC20: 0.08 | AD20: 0.08 | AE20: 0.08 | AF20: 0.08 | AG20: 0.08 | AH20: 0.08 | AI20: 0.08 | AJ20: 0.08 | AK20: 0.08 | AL20: 0.08 | AM20: 0.08 | AN20: 0.08 | AO20: 0.08 | AP20: 0.08 | AQ20: 0.08 | AR20: 0.08 | AS20: 0.08 | AT20: 0.08 | AU20: 0.08 | AV20: 0.08 | AW20: 0.08 | AX20: 0.08 | AY20: 0.08 | AZ20: 0.08 | BA20: 0.08 | BB20: 0.08 | BC20: 0.08 | BD20: 0.08 | BE20: 0.08 | BF20: 0.08 | BG20: 0.08 | BH20: 0.08 | BI20: 0.08 | BJ20: 0.08 | BK20: 0.08 | BL20: 0.08 | BM20: 0.08 | BN20: 0.08 | BO20: 0.08 | BP20: 0.08 | BQ20: 0.08 | BR20: 0.08 | BS20: 0.08 | BT20: 0.08 | BU20: 0.08 | BV20: 0.08 | BW20: 0.08 | BX20: 0.08 | BY20: 0.08 | BZ20: 0.08 | CA20: 0.08 | CB20: 0.08 | CC20: 0.08 | CD20: 0.08 | CE20: 0.08 | CF20: 0.08 | CG20: 0.08 | CH20: 0.08 | CI20: 0.08
A21: Clientes Activos (Premium Care) | B21: # | C21: M1=Nuevos, Mt=ROUND(Prev*(1-Churn)+Nuevos, 0) | D21: =D19 -> 25 | E21: =ROUND(D21*(1-E20)+E19, 0) -> 49 | F21: =ROUND(E21*(1-F20)+F19, 0) -> 72 | G21: =ROUND(F21*(1-G20)+G19, 0) -> 95 | H21: =ROUND(G21*(1-H20)+H19, 0) -> 117 | I21: =ROUND(H21*(1-I20)+I19, 0) -> 139 | J21: =ROUND(I21*(1-J20)+J19, 0) -> 161 | K21: =ROUND(J21*(1-K20)+K19, 0) -> 182 | L21: =ROUND(K21*(1-L20)+L19, 0) -> 202 | ... CI21: =ROUND(CH21*(1-CI20)+CI19, 0) -> 9919
A22: Attachment CUDI Shield Basic | B22: % | C22: 0.15 | D22: 0.15 | E22: 0.15 | F22: 0.15 | G22: 0.15 | H22: 0.15 | I22: 0.15 | J22: 0.15 | K22: 0.15 | L22: 0.15 | M22: 0.15 | N22: 0.15 | O22: 0.15 | P22: 0.15 | Q22: 0.15 | R22: 0.15 | S22: 0.15 | T22: 0.15 | U22: 0.15 | V22: 0.15 | W22: 0.15 | X22: 0.15 | Y22: 0.15 | Z22: 0.15 | AA22: 0.15 | AB22: 0.15 | AC22: 0.15 | AD22: 0.15 | AE22: 0.15 | AF22: 0.15 | AG22: 0.15 | AH22: 0.15 | AI22: 0.15 | AJ22: 0.15 | AK22: 0.15 | AL22: 0.15 | AM22: 0.15 | AN22: 0.15 | AO22: 0.15 | AP22: 0.15 | AQ22: 0.15 | AR22: 0.15 | AS22: 0.15 | AT22: 0.15 | AU22: 0.15 | AV22: 0.15 | AW22: 0.15 | AX22: 0.15 | AY22: 0.15 | AZ22: 0.15 | BA22: 0.15 | BB22: 0.15 | BC22: 0.15 | BD22: 0.15 | BE22: 0.15 | BF22: 0.15 | BG22: 0.15 | BH22: 0.15 | BI22: 0.15 | BJ22: 0.15 | BK22: 0.15 | BL22: 0.15 | BM22: 0.15 | BN22: 0.15 | BO22: 0.15 | BP22: 0.15 | BQ22: 0.15 | BR22: 0.15 | BS22: 0.15 | BT22: 0.15 | BU22: 0.15 | BV22: 0.15 | BW22: 0.15 | BX22: 0.15 | BY22: 0.15 | BZ22: 0.15 | CA22: 0.15 | CB22: 0.15 | CC22: 0.15 | CD22: 0.15 | CE22: 0.15 | CF22: 0.15 | CG22: 0.15 | CH22: 0.15 | CI22: 0.15
A23: Clientes Activos Shield Seguro | B23: # | C23: ROUND(Premium_Activos*Attachment, 0) | D23: =ROUND(D21*D22, 0) -> 4 | E23: =ROUND(E21*E22, 0) -> 7 | F23: =ROUND(F21*F22, 0) -> 11 | G23: =ROUND(G21*G22, 0) -> 14 | H23: =ROUND(H21*H22, 0) -> 18 | I23: =ROUND(I21*I22, 0) -> 21 | J23: =ROUND(J21*J22, 0) -> 24 | K23: =ROUND(K21*K22, 0) -> 27 | ... CI23: =ROUND(CI21*CI22, 0) -> 1488
A24: Smart Collars Vendidos | B24: # | C24: Nuevos Clientes Totales | D24: =D19 -> 25 | E24: =E19 -> 26 | F24: =F19 -> 27 | G24: =G19 -> 29 | H24: =H19 -> 30 | I24: =I19 -> 31 | J24: =J19 -> 33 | K24: =K19 -> 34 | ... CI24: =CI19 -> 1226
A25: Tasa Visitas VetHome | B25: % | C25: 0.02 | D25: 0.02 | E25: 0.02 | F25: 0.02 | G25: 0.02 | H25: 0.02 | I25: 0.02 | J25: 0.02 | K25: 0.02 | L25: 0.02 | M25: 0.02 | N25: 0.02 | O25: 0.02 | P25: 0.02 | Q25: 0.02 | R25: 0.02 | S25: 0.02 | T25: 0.02 | U25: 0.02 | V25: 0.02 | W25: 0.02 | X25: 0.02 | Y25: 0.02 | Z25: 0.02 | AA25: 0.02 | AB25: 0.02 | AC25: 0.02 | AD25: 0.02 | AE25: 0.02 | AF25: 0.02 | AG25: 0.02 | AH25: 0.02 | AI25: 0.02 | AJ25: 0.02 | AK25: 0.02 | AL25: 0.02 | AM25: 0.02 | AN25: 0.02 | AO25: 0.02 | AP25: 0.02 | AQ25: 0.02 | AR25: 0.02 | AS25: 0.02 | AT25: 0.02 | AU25: 0.02 | AV25: 0.02 | AW25: 0.02 | AX25: 0.02 | AY25: 0.02 | AZ25: 0.02 | BA25: 0.02 | BB25: 0.02 | BC25: 0.02 | BD25: 0.02 | BE25: 0.02 | BF25: 0.02 | BG25: 0.02 | BH25: 0.02 | BI25: 0.02 | BJ25: 0.02 | BK25: 0.02 | BL25: 0.02 | BM25: 0.02 | BN25: 0.02 | BO25: 0.02 | BP25: 0.02 | BQ25: 0.02 | BR25: 0.02 | BS25: 0.02 | BT25: 0.02 | BU25: 0.02 | BV25: 0.02 | BW25: 0.02 | BX25: 0.02 | BY25: 0.02 | BZ25: 0.02 | CA25: 0.02 | CB25: 0.02 | CC25: 0.02 | CD25: 0.02 | CE25: 0.02 | CF25: 0.02 | CG25: 0.02 | CH25: 0.02 | CI25: 0.02
A26: Visitas VetHome Proyectadas | B26: # | C26: ROUND(Premium_Activos*VetHome_Rate, 0) | D26: =ROUND(D21*D25, 0) -> 1 | E26: =ROUND(E21*E25, 0) -> 1 | F26: =ROUND(F21*F25, 0) -> 1 | G26: =ROUND(G21*G25, 0) -> 2 | H26: =ROUND(H21*H25, 0) -> 2 | I26: =ROUND(I21*I25, 0) -> 3 | J26: =ROUND(J21*J25, 0) -> 3 | K26: =ROUND(K21*K25, 0) -> 4 | ... CI26: =ROUND(CI21*CI25, 0) -> 198
A27: Tasa Compras Marketplace | B27: % | C27: 0.05 | D27: 0.05 | E27: 0.05 | F27: 0.05 | G27: 0.05 | H27: 0.05 | I27: 0.05 | J27: 0.05 | K27: 0.05 | L27: 0.05 | M27: 0.05 | N27: 0.05 | O27: 0.05 | P27: 0.05 | Q27: 0.05 | R27: 0.05 | S27: 0.05 | T27: 0.05 | U27: 0.05 | V27: 0.05 | W27: 0.05 | X27: 0.05 | Y27: 0.05 | Z27: 0.05 | AA27: 0.05 | AB27: 0.05 | AC27: 0.05 | AD27: 0.05 | AE27: 0.05 | AF27: 0.05 | AG27: 0.05 | AH27: 0.05 | AI27: 0.05 | AJ27: 0.05 | AK27: 0.05 | AL27: 0.05 | AM27: 0.05 | AN27: 0.05 | AO27: 0.05 | AP27: 0.05 | AQ27: 0.05 | AR27: 0.05 | AS27: 0.05 | AT27: 0.05 | AU27: 0.05 | AV27: 0.05 | AW27: 0.05 | AX27: 0.05 | AY27: 0.05 | AZ27: 0.05 | BA27: 0.05 | BB27: 0.05 | BC27: 0.05 | BD27: 0.05 | BE27: 0.05 | BF27: 0.05 | BG27: 0.05 | BH27: 0.05 | BI27: 0.05 | BJ27: 0.05 | BK27: 0.05 | BL27: 0.05 | BM27: 0.05 | BN27: 0.05 | BO27: 0.05 | BP27: 0.05 | BQ27: 0.05 | BR27: 0.05 | BS27: 0.05 | BT27: 0.05 | BU27: 0.05 | BV27: 0.05 | BW27: 0.05 | BX27: 0.05 | BY27: 0.05 | BZ27: 0.05 | CA27: 0.05 | CB27: 0.05 | CC27: 0.05 | CD27: 0.05 | CE27: 0.05 | CF27: 0.05 | CG27: 0.05 | CH27: 0.05 | CI27: 0.05
A28: Transacciones Marketplace | B28: # | C28: ROUND(Premium_Activos*Market_Rate, 0) | D28: =ROUND(D21*D27, 0) -> 1 | E28: =ROUND(E21*E27, 0) -> 2 | F28: =ROUND(F21*F27, 0) -> 4 | G28: =ROUND(G21*G27, 0) -> 5 | H28: =ROUND(H21*H27, 0) -> 6 | I28: =ROUND(I21*I27, 0) -> 7 | J28: =ROUND(J21*J27, 0) -> 8 | K28: =ROUND(K21*K27, 0) -> 9 | ... CI28: =ROUND(CI21*CI27, 0) -> 496
A30: ESCENARIO 2: EQUILIBRIO (BREAK-EVEN) - 670 Hito
A31: Crecimiento Tráfico Orgánico | B31: % | C31: 0.08 | D31: 0.08 | E31: 0.08 | F31: 0.08 | G31: 0.08 | H31: 0.08 | I31: 0.08 | J31: 0.08 | K31: 0.08 | L31: 0.08 | M31: 0.08 | N31: 0.08 | O31: 0.08 | P31: 0.08 | Q31: 0.08 | R31: 0.08 | S31: 0.08 | T31: 0.08 | U31: 0.08 | V31: 0.08 | W31: 0.08 | X31: 0.08 | Y31: 0.08 | Z31: 0.08 | AA31: 0.08 | AB31: 0.08 | AC31: 0.08 | AD31: 0.08 | AE31: 0.08 | AF31: 0.08 | AG31: 0.08 | AH31: 0.08 | AI31: 0.08 | AJ31: 0.08 | AK31: 0.08 | AL31: 0.08 | AM31: 0.08 | AN31: 0.08 | AO31: 0.08 | AP31: 0.08 | AQ31: 0.08 | AR31: 0.08 | AS31: 0.08 | AT31: 0.08 | AU31: 0.08 | AV31: 0.08 | AW31: 0.08 | AX31: 0.08 | AY31: 0.08 | AZ31: 0.08 | BA31: 0.08 | BB31: 0.08 | BC31: 0.08 | BD31: 0.08 | BE31: 0.08 | BF31: 0.08 | BG31: 0.08 | BH31: 0.08 | BI31: 0.08 | BJ31: 0.08 | BK31: 0.08 | BL31: 0.08 | BM31: 0.08 | BN31: 0.08 | BO31: 0.08 | BP31: 0.08 | BQ31: 0.08 | BR31: 0.08 | BS31: 0.08 | BT31: 0.08 | BU31: 0.08 | BV31: 0.08 | BW31: 0.08 | BX31: 0.08 | BY31: 0.08 | BZ31: 0.08 | CA31: 0.08 | CB31: 0.08 | CC31: 0.08 | CD31: 0.08 | CE31: 0.08 | CF31: 0.08 | CG31: 0.08 | CH31: 0.08 | CI31: 0.08
A32: Tráfico Orgánico Mensual | B32: # | C32: M1=1000, Mt=Prev*(1+Growth) | D32: 2027 | E32: =D32*(1+E31) -> 2189.16 | F32: =E32*(1+F31) -> 2364.2928 | G32: =F32*(1+G31) -> 2553.4362 | H32: =G32*(1+H31) -> 2757.7111 | I32: =H32*(1+I31) -> 2978.328 | J32: =I32*(1+J31) -> 3216.5943 | K32: =J32*(1+K31) -> 3473.9218 | L32: =K32*(1+L31) -> 3751.8355 | ... CI32: =CH32*(1+CI31) -> 1205106.6
A33: Tasa de Conversión | B33: % | C33: 0.02 | D33: 0.02 | E33: 0.02 | F33: 0.02 | G33: 0.02 | H33: 0.02 | I33: 0.02 | J33: 0.02 | K33: 0.02 | L33: 0.02 | M33: 0.02 | N33: 0.02 | O33: 0.02 | P33: 0.02 | Q33: 0.02 | R33: 0.02 | S33: 0.02 | T33: 0.02 | U33: 0.02 | V33: 0.02 | W33: 0.02 | X33: 0.02 | Y33: 0.02 | Z33: 0.02 | AA33: 0.02 | AB33: 0.02 | AC33: 0.02 | AD33: 0.02 | AE33: 0.02 | AF33: 0.02 | AG33: 0.02 | AH33: 0.02 | AI33: 0.02 | AJ33: 0.02 | AK33: 0.02 | AL33: 0.02 | AM33: 0.02 | AN33: 0.02 | AO33: 0.02 | AP33: 0.02 | AQ33: 0.02 | AR33: 0.02 | AS33: 0.02 | AT33: 0.02 | AU33: 0.02 | AV33: 0.02 | AW33: 0.02 | AX33: 0.02 | AY33: 0.02 | AZ33: 0.02 | BA33: 0.02 | BB33: 0.02 | BC33: 0.02 | BD33: 0.02 | BE33: 0.02 | BF33: 0.02 | BG33: 0.02 | BH33: 0.02 | BI33: 0.02 | BJ33: 0.02 | BK33: 0.02 | BL33: 0.02 | BM33: 0.02 | BN33: 0.02 | BO33: 0.02 | BP33: 0.02 | BQ33: 0.02 | BR33: 0.02 | BS33: 0.02 | BT33: 0.02 | BU33: 0.02 | BV33: 0.02 | BW33: 0.02 | BX33: 0.02 | BY33: 0.02 | BZ33: 0.02 | CA33: 0.02 | CB33: 0.02 | CC33: 0.02 | CD33: 0.02 | CE33: 0.02 | CF33: 0.02 | CG33: 0.02 | CH33: 0.02 | CI33: 0.02
A34: Nuevos Clientes (Orgánicos) | B34: # | C34: ROUND(Tráfico*Conversión, 0) | D34: =ROUND(D32*D33, 0) -> 41 | E34: =ROUND(E32*E33, 0) -> 44 | F34: =ROUND(F32*F33, 0) -> 47 | G34: =ROUND(G32*G33, 0) -> 51 | H34: =ROUND(H32*H33, 0) -> 55 | I34: =ROUND(I32*I33, 0) -> 60 | J34: =ROUND(J32*J33, 0) -> 64 | K34: =ROUND(K32*K33, 0) -> 69 | ... CI34: =ROUND(CI32*CI33, 0) -> 24102
A35: Presupuesto Social Ads | B35: EUR | C35: '1_PANEL_CONTROL'!$C$80 | D35: ='1_PANEL_CONTROL'!$C$80+'1_PANEL_CONTROL'!$C$69+'1_PANEL_CONTROL'!$C$68 -> 2955 | E35: ='1_PANEL_CONTROL'!$C$80+'1_PANEL_CONTROL'!$C$69+'1_PANEL_CONTROL'!$C$68 -> 2955 | F35: ='1_PANEL_CONTROL'!$C$80+'1_PANEL_CONTROL'!$C$69+'1_PANEL_CONTROL'!$C$68 -> 2955 | G35: ='1_PANEL_CONTROL'!$C$80+'1_PANEL_CONTROL'!$C$69+'1_PANEL_CONTROL'!$C$68 -> 2955 | H35: ='1_PANEL_CONTROL'!$C$80+'1_PANEL_CONTROL'!$C$69+'1_PANEL_CONTROL'!$C$68 -> 2955 | I35: ='1_PANEL_CONTROL'!$C$80+'1_PANEL_CONTROL'!$C$69+'1_PANEL_CONTROL'!$C$68 -> 2955 | J35: ='1_PANEL_CONTROL'!$C$80+'1_PANEL_CONTROL'!$C$69+'1_PANEL_CONTROL'!$C$68 -> 2955 | K35: ='1_PANEL_CONTROL'!$C$80+'1_PANEL_CONTROL'!$C$69+'1_PANEL_CONTROL'!$C$68 -> 2955 | ... CI35: ='1_PANEL_CONTROL'!$C$80+'1_PANEL_CONTROL'!$C$69+'1_PANEL_CONTROL'!$C$68 -> 2955
A36: CPL Paid (Coste por Lead) | B36: EUR | C36: 11.0 | D36: 11 | E36: 11 | F36: 11 | G36: 11 | H36: 11 | I36: 11 | J36: 11 | K36: 11 | L36: 11 | M36: 11 | N36: 11 | O36: 11 | P36: 11 | Q36: 11 | R36: 11 | S36: 11 | T36: 11 | U36: 11 | V36: 11 | W36: 11 | X36: 11 | Y36: 11 | Z36: 11 | AA36: 11 | AB36: 11 | AC36: 11 | AD36: 11 | AE36: 11 | AF36: 11 | AG36: 11 | AH36: 11 | AI36: 11 | AJ36: 11 | AK36: 11 | AL36: 11 | AM36: 11 | AN36: 11 | AO36: 11 | AP36: 11 | AQ36: 11 | AR36: 11 | AS36: 11 | AT36: 11 | AU36: 11 | AV36: 11 | AW36: 11 | AX36: 11 | AY36: 11 | AZ36: 11 | BA36: 11 | BB36: 11 | BC36: 11 | BD36: 11 | BE36: 11 | BF36: 11 | BG36: 11 | BH36: 11 | BI36: 11 | BJ36: 11 | BK36: 11 | BL36: 11 | BM36: 11 | BN36: 11 | BO36: 11 | BP36: 11 | BQ36: 11 | BR36: 11 | BS36: 11 | BT36: 11 | BU36: 11 | BV36: 11 | BW36: 11 | BX36: 11 | BY36: 11 | BZ36: 11 | CA36: 11 | CB36: 11 | CC36: 11 | CD36: 11 | CE36: 11 | CF36: 11 | CG36: 11 | CH36: 11 | CI36: 11
A37: Leads de Pago Adquiridos | B37: # | C37: ROUND(Presupuesto/CPL, 0) | D37: =ROUND(D35/D36, 0) -> 269 | E37: =ROUND(E35/E36, 0) -> 269 | F37: =ROUND(F35/F36, 0) -> 269 | G37: =ROUND(G35/G36, 0) -> 269 | H37: =ROUND(H35/H36, 0) -> 269 | I37: =ROUND(I35/I36, 0) -> 269 | J37: =ROUND(J35/J36, 0) -> 269 | K37: =ROUND(K35/K36, 0) -> 269 | ... CI37: =ROUND(CI35/CI36, 0) -> 269
A38: Nuevos Clientes (Pauta/Paid) | B38: # | C38: ROUND(Leads*Conversión, 0) | D38: =ROUND(D37*D33, 0) -> 5 | E38: =ROUND(E37*E33, 0) -> 5 | F38: =ROUND(F37*F33, 0) -> 5 | G38: =ROUND(G37*G33, 0) -> 5 | H38: =ROUND(H37*H33, 0) -> 5 | I38: =ROUND(I37*I33, 0) -> 5 | J38: =ROUND(J37*J33, 0) -> 5 | K38: =ROUND(K37*K33, 0) -> 5 | ... CI38: =ROUND(CI37*CI33, 0) -> 5
A39: Nuevos Clientes Totales | B39: # | C39: Orgánicos + Paid | D39: =D34+D38 -> 46 | E39: =E34+E38 -> 49 | F39: =F34+F38 -> 52 | G39: =G34+G38 -> 56 | H39: =H34+H38 -> 60 | I39: =I34+I38 -> 65 | J39: =J34+J38 -> 69 | K39: =K34+K38 -> 74 | ... CI39: =CI34+CI38 -> 24107
A40: Tasa Cancelación (Churn) | B40: % | C40: 0.048 | D40: 0.048 | E40: 0.048 | F40: 0.048 | G40: 0.048 | H40: 0.048 | I40: 0.048 | J40: 0.048 | K40: 0.048 | L40: 0.048 | M40: 0.048 | N40: 0.048 | O40: 0.048 | P40: 0.048 | Q40: 0.048 | R40: 0.048 | S40: 0.048 | T40: 0.048 | U40: 0.048 | V40: 0.048 | W40: 0.048 | X40: 0.048 | Y40: 0.048 | Z40: 0.048 | AA40: 0.048 | AB40: 0.048 | AC40: 0.048 | AD40: 0.048 | AE40: 0.048 | AF40: 0.048 | AG40: 0.048 | AH40: 0.048 | AI40: 0.048 | AJ40: 0.048 | AK40: 0.048 | AL40: 0.048 | AM40: 0.048 | AN40: 0.048 | AO40: 0.048 | AP40: 0.048 | AQ40: 0.048 | AR40: 0.048 | AS40: 0.048 | AT40: 0.048 | AU40: 0.048 | AV40: 0.048 | AW40: 0.048 | AX40: 0.048 | AY40: 0.048 | AZ40: 0.048 | BA40: 0.048 | BB40: 0.048 | BC40: 0.048 | BD40: 0.048 | BE40: 0.048 | BF40: 0.048 | BG40: 0.048 | BH40: 0.048 | BI40: 0.048 | BJ40: 0.048 | BK40: 0.048 | BL40: 0.048 | BM40: 0.048 | BN40: 0.048 | BO40: 0.048 | BP40: 0.048 | BQ40: 0.048 | BR40: 0.048 | BS40: 0.048 | BT40: 0.048 | BU40: 0.048 | BV40: 0.048 | BW40: 0.048 | BX40: 0.048 | BY40: 0.048 | BZ40: 0.048 | CA40: 0.048 | CB40: 0.048 | CC40: 0.048 | CD40: 0.048 | CE40: 0.048 | CF40: 0.048 | CG40: 0.048 | CH40: 0.048 | CI40: 0.048
A41: Clientes Activos (Premium Care) | B41: # | C41: M1=Nuevos, Mt=ROUND(Prev*(1-Churn)+Nuevos, 0) | D41: =D39 -> 46 | E41: =ROUND(D41*(1-E40)+E39, 0) -> 93 | F41: =ROUND(E41*(1-F40)+F39, 0) -> 141 | G41: =ROUND(F41*(1-G40)+G39, 0) -> 190 | H41: =ROUND(G41*(1-H40)+H39, 0) -> 241 | I41: =ROUND(H41*(1-I40)+I39, 0) -> 294 | J41: =ROUND(I41*(1-J40)+J39, 0) -> 349 | K41: =ROUND(J41*(1-K40)+K39, 0) -> 406 | L41: =ROUND(K41*(1-L40)+L39, 0) -> 467 | ... CI41: =ROUND(CH41*(1-CI40)+CI39, 0) -> 203460
A42: Attachment CUDI Shield Basic | B42: % | C42: 0.3 | D42: 0.3 | E42: 0.3 | F42: 0.3 | G42: 0.3 | H42: 0.3 | I42: 0.3 | J42: 0.3 | K42: 0.3 | L42: 0.3 | M42: 0.3 | N42: 0.3 | O42: 0.3 | P42: 0.3 | Q42: 0.3 | R42: 0.3 | S42: 0.3 | T42: 0.3 | U42: 0.3 | V42: 0.3 | W42: 0.3 | X42: 0.3 | Y42: 0.3 | Z42: 0.3 | AA42: 0.3 | AB42: 0.3 | AC42: 0.3 | AD42: 0.3 | AE42: 0.3 | AF42: 0.3 | AG42: 0.3 | AH42: 0.3 | AI42: 0.3 | AJ42: 0.3 | AK42: 0.3 | AL42: 0.3 | AM42: 0.3 | AN42: 0.3 | AO42: 0.3 | AP42: 0.3 | AQ42: 0.3 | AR42: 0.3 | AS42: 0.3 | AT42: 0.3 | AU42: 0.3 | AV42: 0.3 | AW42: 0.3 | AX42: 0.3 | AY42: 0.3 | AZ42: 0.3 | BA42: 0.3 | BB42: 0.3 | BC42: 0.3 | BD42: 0.3 | BE42: 0.3 | BF42: 0.3 | BG42: 0.3 | BH42: 0.3 | BI42: 0.3 | BJ42: 0.3 | BK42: 0.3 | BL42: 0.3 | BM42: 0.3 | BN42: 0.3 | BO42: 0.3 | BP42: 0.3 | BQ42: 0.3 | BR42: 0.3 | BS42: 0.3 | BT42: 0.3 | BU42: 0.3 | BV42: 0.3 | BW42: 0.3 | BX42: 0.3 | BY42: 0.3 | BZ42: 0.3 | CA42: 0.3 | CB42: 0.3 | CC42: 0.3 | CD42: 0.3 | CE42: 0.3 | CF42: 0.3 | CG42: 0.3 | CH42: 0.3 | CI42: 0.3
A43: Clientes Activos Shield Seguro | B43: # | C43: ROUND(Premium_Activos*Attachment, 0) | D43: =ROUND(D41*D42, 0) -> 14 | E43: =ROUND(E41*E42, 0) -> 28 | F43: =ROUND(F41*F42, 0) -> 42 | G43: =ROUND(G41*G42, 0) -> 57 | H43: =ROUND(H41*H42, 0) -> 72 | I43: =ROUND(I41*I42, 0) -> 88 | J43: =ROUND(J41*J42, 0) -> 105 | K43: =ROUND(K41*K42, 0) -> 122 | ... CI43: =ROUND(CI41*CI42, 0) -> 61038
A44: Smart Collars Vendidos | B44: # | C44: Nuevos Clientes Totales | D44: =D39 -> 46 | E44: =E39 -> 49 | F44: =F39 -> 52 | G44: =G39 -> 56 | H44: =H39 -> 60 | I44: =I39 -> 65 | J44: =J39 -> 69 | K44: =K39 -> 74 | ... CI44: =CI39 -> 24107
A45: Tasa Visitas VetHome | B45: % | C45: 0.045 | D45: 0.045 | E45: 0.045 | F45: 0.045 | G45: 0.045 | H45: 0.045 | I45: 0.045 | J45: 0.045 | K45: 0.045 | L45: 0.045 | M45: 0.045 | N45: 0.045 | O45: 0.045 | P45: 0.045 | Q45: 0.045 | R45: 0.045 | S45: 0.045 | T45: 0.045 | U45: 0.045 | V45: 0.045 | W45: 0.045 | X45: 0.045 | Y45: 0.045 | Z45: 0.045 | AA45: 0.045 | AB45: 0.045 | AC45: 0.045 | AD45: 0.045 | AE45: 0.045 | AF45: 0.045 | AG45: 0.045 | AH45: 0.045 | AI45: 0.045 | AJ45: 0.045 | AK45: 0.045 | AL45: 0.045 | AM45: 0.045 | AN45: 0.045 | AO45: 0.045 | AP45: 0.045 | AQ45: 0.045 | AR45: 0.045 | AS45: 0.045 | AT45: 0.045 | AU45: 0.045 | AV45: 0.045 | AW45: 0.045 | AX45: 0.045 | AY45: 0.045 | AZ45: 0.045 | BA45: 0.045 | BB45: 0.045 | BC45: 0.045 | BD45: 0.045 | BE45: 0.045 | BF45: 0.045 | BG45: 0.045 | BH45: 0.045 | BI45: 0.045 | BJ45: 0.045 | BK45: 0.045 | BL45: 0.045 | BM45: 0.045 | BN45: 0.045 | BO45: 0.045 | BP45: 0.045 | BQ45: 0.045 | BR45: 0.045 | BS45: 0.045 | BT45: 0.045 | BU45: 0.045 | BV45: 0.045 | BW45: 0.045 | BX45: 0.045 | BY45: 0.045 | BZ45: 0.045 | CA45: 0.045 | CB45: 0.045 | CC45: 0.045 | CD45: 0.045 | CE45: 0.045 | CF45: 0.045 | CG45: 0.045 | CH45: 0.045 | CI45: 0.045
A46: Visitas VetHome Proyectadas | B46: # | C46: ROUND(Premium_Activos*VetHome_Rate, 0) | D46: =ROUND(D41*D45, 0) -> 2 | E46: =ROUND(E41*E45, 0) -> 4 | F46: =ROUND(F41*F45, 0) -> 6 | G46: =ROUND(G41*G45, 0) -> 9 | H46: =ROUND(H41*H45, 0) -> 11 | I46: =ROUND(I41*I45, 0) -> 13 | J46: =ROUND(J41*J45, 0) -> 16 | K46: =ROUND(K41*K45, 0) -> 18 | ... CI46: =ROUND(CI41*CI45, 0) -> 9156
A47: Tasa Compras Marketplace | B47: % | C47: 0.2 | D47: 0.2 | E47: 0.2 | F47: 0.2 | G47: 0.2 | H47: 0.2 | I47: 0.2 | J47: 0.2 | K47: 0.2 | L47: 0.2 | M47: 0.2 | N47: 0.2 | O47: 0.2 | P47: 0.2 | Q47: 0.2 | R47: 0.2 | S47: 0.2 | T47: 0.2 | U47: 0.2 | V47: 0.2 | W47: 0.2 | X47: 0.2 | Y47: 0.2 | Z47: 0.2 | AA47: 0.2 | AB47: 0.2 | AC47: 0.2 | AD47: 0.2 | AE47: 0.2 | AF47: 0.2 | AG47: 0.2 | AH47: 0.2 | AI47: 0.2 | AJ47: 0.2 | AK47: 0.2 | AL47: 0.2 | AM47: 0.2 | AN47: 0.2 | AO47: 0.2 | AP47: 0.2 | AQ47: 0.2 | AR47: 0.2 | AS47: 0.2 | AT47: 0.2 | AU47: 0.2 | AV47: 0.2 | AW47: 0.2 | AX47: 0.2 | AY47: 0.2 | AZ47: 0.2 | BA47: 0.2 | BB47: 0.2 | BC47: 0.2 | BD47: 0.2 | BE47: 0.2 | BF47: 0.2 | BG47: 0.2 | BH47: 0.2 | BI47: 0.2 | BJ47: 0.2 | BK47: 0.2 | BL47: 0.2 | BM47: 0.2 | BN47: 0.2 | BO47: 0.2 | BP47: 0.2 | BQ47: 0.2 | BR47: 0.2 | BS47: 0.2 | BT47: 0.2 | BU47: 0.2 | BV47: 0.2 | BW47: 0.2 | BX47: 0.2 | BY47: 0.2 | BZ47: 0.2 | CA47: 0.2 | CB47: 0.2 | CC47: 0.2 | CD47: 0.2 | CE47: 0.2 | CF47: 0.2 | CG47: 0.2 | CH47: 0.2 | CI47: 0.2
A48: Transacciones Marketplace | B48: # | C48: ROUND(Premium_Activos*Market_Rate, 0) | D48: =ROUND(D41*D47, 0) -> 9 | E48: =ROUND(E41*E47, 0) -> 19 | F48: =ROUND(F41*F47, 0) -> 28 | G48: =ROUND(G41*G47, 0) -> 38 | H48: =ROUND(H41*H47, 0) -> 48 | I48: =ROUND(I41*I47, 0) -> 59 | J48: =ROUND(J41*J47, 0) -> 70 | K48: =ROUND(K41*K47, 0) -> 81 | ... CI48: =ROUND(CI41*CI47, 0) -> 40692
A50: ESCENARIO 3: POSITIVO
A51: Crecimiento Tráfico Orgánico | B51: % | C51: 0.15 | D51: 0.15 | E51: 0.15 | F51: 0.15 | G51: 0.15 | H51: 0.15 | I51: 0.15 | J51: 0.15 | K51: 0.15 | L51: 0.15 | M51: 0.15 | N51: 0.15 | O51: 0.15 | P51: 0.15 | Q51: 0.15 | R51: 0.15 | S51: 0.15 | T51: 0.15 | U51: 0.15 | V51: 0.15 | W51: 0.15 | X51: 0.15 | Y51: 0.15 | Z51: 0.15 | AA51: 0.15 | AB51: 0.15 | AC51: 0.15 | AD51: 0.15 | AE51: 0.15 | AF51: 0.15 | AG51: 0.15 | AH51: 0.15 | AI51: 0.15 | AJ51: 0.15 | AK51: 0.15 | AL51: 0.15 | AM51: 0.15 | AN51: 0.15 | AO51: 0.15 | AP51: 0.15 | AQ51: 0.15 | AR51: 0.15 | AS51: 0.15 | AT51: 0.15 | AU51: 0.15 | AV51: 0.15 | AW51: 0.15 | AX51: 0.15 | AY51: 0.15 | AZ51: 0.15 | BA51: 0.15 | BB51: 0.15 | BC51: 0.15 | BD51: 0.15 | BE51: 0.15 | BF51: 0.15 | BG51: 0.15 | BH51: 0.15 | BI51: 0.15 | BJ51: 0.15 | BK51: 0.15 | BL51: 0.15 | BM51: 0.15 | BN51: 0.15 | BO51: 0.15 | BP51: 0.15 | BQ51: 0.15 | BR51: 0.15 | BS51: 0.15 | BT51: 0.15 | BU51: 0.15 | BV51: 0.15 | BW51: 0.15 | BX51: 0.15 | BY51: 0.15 | BZ51: 0.15 | CA51: 0.15 | CB51: 0.15 | CC51: 0.15 | CD51: 0.15 | CE51: 0.15 | CF51: 0.15 | CG51: 0.15 | CH51: 0.15 | CI51: 0.15
A52: Tráfico Orgánico Mensual | B52: # | C52: M1=1000, Mt=Prev*(1+Growth) | D52: 1000 | E52: =D52*(1+E51) -> 1150 | F52: =E52*(1+F51) -> 1322.5 | G52: =F52*(1+G51) -> 1520.875 | H52: =G52*(1+H51) -> 1749.0062 | I52: =H52*(1+I51) -> 2011.3572 | J52: =I52*(1+J51) -> 2313.0608 | K52: =J52*(1+K51) -> 2660.0199 | L52: =K52*(1+L51) -> 3059.0229 | ... CI52: =CH52*(1+CI51) -> 1.0912412e+08
A53: Tasa de Conversión | B53: % | C53: 0.08 | D53: 0.08 | E53: 0.08 | F53: 0.08 | G53: 0.08 | H53: 0.08 | I53: 0.08 | J53: 0.08 | K53: 0.08 | L53: 0.08 | M53: 0.08 | N53: 0.08 | O53: 0.08 | P53: 0.08 | Q53: 0.08 | R53: 0.08 | S53: 0.08 | T53: 0.08 | U53: 0.08 | V53: 0.08 | W53: 0.08 | X53: 0.08 | Y53: 0.08 | Z53: 0.08 | AA53: 0.08 | AB53: 0.08 | AC53: 0.08 | AD53: 0.08 | AE53: 0.08 | AF53: 0.08 | AG53: 0.08 | AH53: 0.08 | AI53: 0.08 | AJ53: 0.08 | AK53: 0.08 | AL53: 0.08 | AM53: 0.08 | AN53: 0.08 | AO53: 0.08 | AP53: 0.08 | AQ53: 0.08 | AR53: 0.08 | AS53: 0.08 | AT53: 0.08 | AU53: 0.08 | AV53: 0.08 | AW53: 0.08 | AX53: 0.08 | AY53: 0.08 | AZ53: 0.08 | BA53: 0.08 | BB53: 0.08 | BC53: 0.08 | BD53: 0.08 | BE53: 0.08 | BF53: 0.08 | BG53: 0.08 | BH53: 0.08 | BI53: 0.08 | BJ53: 0.08 | BK53: 0.08 | BL53: 0.08 | BM53: 0.08 | BN53: 0.08 | BO53: 0.08 | BP53: 0.08 | BQ53: 0.08 | BR53: 0.08 | BS53: 0.08 | BT53: 0.08 | BU53: 0.08 | BV53: 0.08 | BW53: 0.08 | BX53: 0.08 | BY53: 0.08 | BZ53: 0.08 | CA53: 0.08 | CB53: 0.08 | CC53: 0.08 | CD53: 0.08 | CE53: 0.08 | CF53: 0.08 | CG53: 0.08 | CH53: 0.08 | CI53: 0.08
A54: Nuevos Clientes (Orgánicos) | B54: # | C54: ROUND(Tráfico*Conversión, 0) | D54: =ROUND(D52*D53, 0) -> 80 | E54: =ROUND(E52*E53, 0) -> 92 | F54: =ROUND(F52*F53, 0) -> 106 | G54: =ROUND(G52*G53, 0) -> 122 | H54: =ROUND(H52*H53, 0) -> 140 | I54: =ROUND(I52*I53, 0) -> 161 | J54: =ROUND(J52*J53, 0) -> 185 | K54: =ROUND(K52*K53, 0) -> 213 | ... CI54: =ROUND(CI52*CI53, 0) -> 8729929
A55: Presupuesto Social Ads | B55: EUR | C55: '1_PANEL_CONTROL'!$C$80 | D55: ='1_PANEL_CONTROL'!$C$80+'1_PANEL_CONTROL'!$C$69+'1_PANEL_CONTROL'!$C$68 -> 2955 | E55: ='1_PANEL_CONTROL'!$C$80+'1_PANEL_CONTROL'!$C$69+'1_PANEL_CONTROL'!$C$68 -> 2955 | F55: ='1_PANEL_CONTROL'!$C$80+'1_PANEL_CONTROL'!$C$69+'1_PANEL_CONTROL'!$C$68 -> 2955 | G55: ='1_PANEL_CONTROL'!$C$80+'1_PANEL_CONTROL'!$C$69+'1_PANEL_CONTROL'!$C$68 -> 2955 | H55: ='1_PANEL_CONTROL'!$C$80+'1_PANEL_CONTROL'!$C$69+'1_PANEL_CONTROL'!$C$68 -> 2955 | I55: ='1_PANEL_CONTROL'!$C$80+'1_PANEL_CONTROL'!$C$69+'1_PANEL_CONTROL'!$C$68 -> 2955 | J55: ='1_PANEL_CONTROL'!$C$80+'1_PANEL_CONTROL'!$C$69+'1_PANEL_CONTROL'!$C$68 -> 2955 | K55: ='1_PANEL_CONTROL'!$C$80+'1_PANEL_CONTROL'!$C$69+'1_PANEL_CONTROL'!$C$68 -> 2955 | ... CI55: ='1_PANEL_CONTROL'!$C$80+'1_PANEL_CONTROL'!$C$69+'1_PANEL_CONTROL'!$C$68 -> 2955
A56: CPL Paid (Coste por Lead) | B56: EUR | C56: 7.0 | D56: 7 | E56: 7 | F56: 7 | G56: 7 | H56: 7 | I56: 7 | J56: 7 | K56: 7 | L56: 7 | M56: 7 | N56: 7 | O56: 7 | P56: 7 | Q56: 7 | R56: 7 | S56: 7 | T56: 7 | U56: 7 | V56: 7 | W56: 7 | X56: 7 | Y56: 7 | Z56: 7 | AA56: 7 | AB56: 7 | AC56: 7 | AD56: 7 | AE56: 7 | AF56: 7 | AG56: 7 | AH56: 7 | AI56: 7 | AJ56: 7 | AK56: 7 | AL56: 7 | AM56: 7 | AN56: 7 | AO56: 7 | AP56: 7 | AQ56: 7 | AR56: 7 | AS56: 7 | AT56: 7 | AU56: 7 | AV56: 7 | AW56: 7 | AX56: 7 | AY56: 7 | AZ56: 7 | BA56: 7 | BB56: 7 | BC56: 7 | BD56: 7 | BE56: 7 | BF56: 7 | BG56: 7 | BH56: 7 | BI56: 7 | BJ56: 7 | BK56: 7 | BL56: 7 | BM56: 7 | BN56: 7 | BO56: 7 | BP56: 7 | BQ56: 7 | BR56: 7 | BS56: 7 | BT56: 7 | BU56: 7 | BV56: 7 | BW56: 7 | BX56: 7 | BY56: 7 | BZ56: 7 | CA56: 7 | CB56: 7 | CC56: 7 | CD56: 7 | CE56: 7 | CF56: 7 | CG56: 7 | CH56: 7 | CI56: 7
A57: Leads de Pago Adquiridos | B57: # | C57: ROUND(Presupuesto/CPL, 0) | D57: =ROUND(D55/D56, 0) -> 422 | E57: =ROUND(E55/E56, 0) -> 422 | F57: =ROUND(F55/F56, 0) -> 422 | G57: =ROUND(G55/G56, 0) -> 422 | H57: =ROUND(H55/H56, 0) -> 422 | I57: =ROUND(I55/I56, 0) -> 422 | J57: =ROUND(J55/J56, 0) -> 422 | K57: =ROUND(K55/K56, 0) -> 422 | ... CI57: =ROUND(CI55/CI56, 0) -> 422
A58: Nuevos Clientes (Pauta/Paid) | B58: # | C58: ROUND(Leads*Conversión, 0) | D58: =ROUND(D57*D53, 0) -> 34 | E58: =ROUND(E57*E53, 0) -> 34 | F58: =ROUND(F57*F53, 0) -> 34 | G58: =ROUND(G57*G53, 0) -> 34 | H58: =ROUND(H57*H53, 0) -> 34 | I58: =ROUND(I57*I53, 0) -> 34 | J58: =ROUND(J57*J53, 0) -> 34 | K58: =ROUND(K57*K53, 0) -> 34 | ... CI58: =ROUND(CI57*CI53, 0) -> 34
A59: Nuevos Clientes Totales | B59: # | C59: Orgánicos + Paid | D59: =D54+D58 -> 114 | E59: =E54+E58 -> 126 | F59: =F54+F58 -> 140 | G59: =G54+G58 -> 156 | H59: =H54+H58 -> 174 | I59: =I54+I58 -> 195 | J59: =J54+J58 -> 219 | K59: =K54+K58 -> 247 | ... CI59: =CI54+CI58 -> 8729963
A60: Tasa Cancelación (Churn) | B60: % | C60: 0.03 | D60: 0.03 | E60: 0.03 | F60: 0.03 | G60: 0.03 | H60: 0.03 | I60: 0.03 | J60: 0.03 | K60: 0.03 | L60: 0.03 | M60: 0.03 | N60: 0.03 | O60: 0.03 | P60: 0.03 | Q60: 0.03 | R60: 0.03 | S60: 0.03 | T60: 0.03 | U60: 0.03 | V60: 0.03 | W60: 0.03 | X60: 0.03 | Y60: 0.03 | Z60: 0.03 | AA60: 0.03 | AB60: 0.03 | AC60: 0.03 | AD60: 0.03 | AE60: 0.03 | AF60: 0.03 | AG60: 0.03 | AH60: 0.03 | AI60: 0.03 | AJ60: 0.03 | AK60: 0.03 | AL60: 0.03 | AM60: 0.03 | AN60: 0.03 | AO60: 0.03 | AP60: 0.03 | AQ60: 0.03 | AR60: 0.03 | AS60: 0.03 | AT60: 0.03 | AU60: 0.03 | AV60: 0.03 | AW60: 0.03 | AX60: 0.03 | AY60: 0.03 | AZ60: 0.03 | BA60: 0.03 | BB60: 0.03 | BC60: 0.03 | BD60: 0.03 | BE60: 0.03 | BF60: 0.03 | BG60: 0.03 | BH60: 0.03 | BI60: 0.03 | BJ60: 0.03 | BK60: 0.03 | BL60: 0.03 | BM60: 0.03 | BN60: 0.03 | BO60: 0.03 | BP60: 0.03 | BQ60: 0.03 | BR60: 0.03 | BS60: 0.03 | BT60: 0.03 | BU60: 0.03 | BV60: 0.03 | BW60: 0.03 | BX60: 0.03 | BY60: 0.03 | BZ60: 0.03 | CA60: 0.03 | CB60: 0.03 | CC60: 0.03 | CD60: 0.03 | CE60: 0.03 | CF60: 0.03 | CG60: 0.03 | CH60: 0.03 | CI60: 0.03
A61: Clientes Activos (Premium Care) | B61: # | C61: M1=Nuevos, Mt=ROUND(Prev*(1-Churn)+Nuevos, 0) | D61: =D59 -> 114 | E61: =ROUND(D61*(1-E60)+E59, 0) -> 237 | F61: =ROUND(E61*(1-F60)+F59, 0) -> 370 | G61: =ROUND(F61*(1-G60)+G59, 0) -> 515 | H61: =ROUND(G61*(1-H60)+H59, 0) -> 674 | I61: =ROUND(H61*(1-I60)+I59, 0) -> 849 | J61: =ROUND(I61*(1-J60)+J59, 0) -> 1043 | K61: =ROUND(J61*(1-K60)+K59, 0) -> 1259 | L61: =ROUND(K61*(1-L60)+L59, 0) -> 1500 | ... CI61: =ROUND(CH61*(1-CI60)+CI59, 0) -> 55775561
A62: Attachment CUDI Shield Basic | B62: % | C62: 0.45 | D62: 0.45 | E62: 0.45 | F62: 0.45 | G62: 0.45 | H62: 0.45 | I62: 0.45 | J62: 0.45 | K62: 0.45 | L62: 0.45 | M62: 0.45 | N62: 0.45 | O62: 0.45 | P62: 0.45 | Q62: 0.45 | R62: 0.45 | S62: 0.45 | T62: 0.45 | U62: 0.45 | V62: 0.45 | W62: 0.45 | X62: 0.45 | Y62: 0.45 | Z62: 0.45 | AA62: 0.45 | AB62: 0.45 | AC62: 0.45 | AD62: 0.45 | AE62: 0.45 | AF62: 0.45 | AG62: 0.45 | AH62: 0.45 | AI62: 0.45 | AJ62: 0.45 | AK62: 0.45 | AL62: 0.45 | AM62: 0.45 | AN62: 0.45 | AO62: 0.45 | AP62: 0.45 | AQ62: 0.45 | AR62: 0.45 | AS62: 0.45 | AT62: 0.45 | AU62: 0.45 | AV62: 0.45 | AW62: 0.45 | AX62: 0.45 | AY62: 0.45 | AZ62: 0.45 | BA62: 0.45 | BB62: 0.45 | BC62: 0.45 | BD62: 0.45 | BE62: 0.45 | BF62: 0.45 | BG62: 0.45 | BH62: 0.45 | BI62: 0.45 | BJ62: 0.45 | BK62: 0.45 | BL62: 0.45 | BM62: 0.45 | BN62: 0.45 | BO62: 0.45 | BP62: 0.45 | BQ62: 0.45 | BR62: 0.45 | BS62: 0.45 | BT62: 0.45 | BU62: 0.45 | BV62: 0.45 | BW62: 0.45 | BX62: 0.45 | BY62: 0.45 | BZ62: 0.45 | CA62: 0.45 | CB62: 0.45 | CC62: 0.45 | CD62: 0.45 | CE62: 0.45 | CF62: 0.45 | CG62: 0.45 | CH62: 0.45 | CI62: 0.45
A63: Clientes Activos Shield Seguro | B63: # | C63: ROUND(Premium_Activos*Attachment, 0) | D63: =ROUND(D61*D62, 0) -> 51 | E63: =ROUND(E61*E62, 0) -> 107 | F63: =ROUND(F61*F62, 0) -> 167 | G63: =ROUND(G61*G62, 0) -> 232 | H63: =ROUND(H61*H62, 0) -> 303 | I63: =ROUND(I61*I62, 0) -> 382 | J63: =ROUND(J61*J62, 0) -> 469 | K63: =ROUND(K61*K62, 0) -> 567 | ... CI63: =ROUND(CI61*CI62, 0) -> 25099002
A64: Smart Collars Vendidos | B64: # | C64: Nuevos Clientes Totales | D64: =D59 -> 114 | E64: =E59 -> 126 | F64: =F59 -> 140 | G64: =G59 -> 156 | H64: =H59 -> 174 | I64: =I59 -> 195 | J64: =J59 -> 219 | K64: =K59 -> 247 | ... CI64: =CI59 -> 8729963
A65: Tasa Visitas VetHome | B65: % | C65: 0.08 | D65: 0.08 | E65: 0.08 | F65: 0.08 | G65: 0.08 | H65: 0.08 | I65: 0.08 | J65: 0.08 | K65: 0.08 | L65: 0.08 | M65: 0.08 | N65: 0.08 | O65: 0.08 | P65: 0.08 | Q65: 0.08 | R65: 0.08 | S65: 0.08 | T65: 0.08 | U65: 0.08 | V65: 0.08 | W65: 0.08 | X65: 0.08 | Y65: 0.08 | Z65: 0.08 | AA65: 0.08 | AB65: 0.08 | AC65: 0.08 | AD65: 0.08 | AE65: 0.08 | AF65: 0.08 | AG65: 0.08 | AH65: 0.08 | AI65: 0.08 | AJ65: 0.08 | AK65: 0.08 | AL65: 0.08 | AM65: 0.08 | AN65: 0.08 | AO65: 0.08 | AP65: 0.08 | AQ65: 0.08 | AR65: 0.08 | AS65: 0.08 | AT65: 0.08 | AU65: 0.08 | AV65: 0.08 | AW65: 0.08 | AX65: 0.08 | AY65: 0.08 | AZ65: 0.08 | BA65: 0.08 | BB65: 0.08 | BC65: 0.08 | BD65: 0.08 | BE65: 0.08 | BF65: 0.08 | BG65: 0.08 | BH65: 0.08 | BI65: 0.08 | BJ65: 0.08 | BK65: 0.08 | BL65: 0.08 | BM65: 0.08 | BN65: 0.08 | BO65: 0.08 | BP65: 0.08 | BQ65: 0.08 | BR65: 0.08 | BS65: 0.08 | BT65: 0.08 | BU65: 0.08 | BV65: 0.08 | BW65: 0.08 | BX65: 0.08 | BY65: 0.08 | BZ65: 0.08 | CA65: 0.08 | CB65: 0.08 | CC65: 0.08 | CD65: 0.08 | CE65: 0.08 | CF65: 0.08 | CG65: 0.08 | CH65: 0.08 | CI65: 0.08
A66: Visitas VetHome Proyectadas | B66: # | C66: ROUND(Premium_Activos*VetHome_Rate, 0) | D66: =ROUND(D61*D65, 0) -> 9 | E66: =ROUND(E61*E65, 0) -> 19 | F66: =ROUND(F61*F65, 0) -> 30 | G66: =ROUND(G61*G65, 0) -> 41 | H66: =ROUND(H61*H65, 0) -> 54 | I66: =ROUND(I61*I65, 0) -> 68 | J66: =ROUND(J61*J65, 0) -> 83 | K66: =ROUND(K61*K65, 0) -> 101 | ... CI66: =ROUND(CI61*CI65, 0) -> 4462045
A67: Tasa Compras Marketplace | B67: % | C67: 0.25 | D67: 0.25 | E67: 0.25 | F67: 0.25 | G67: 0.25 | H67: 0.25 | I67: 0.25 | J67: 0.25 | K67: 0.25 | L67: 0.25 | M67: 0.25 | N67: 0.25 | O67: 0.25 | P67: 0.25 | Q67: 0.25 | R67: 0.25 | S67: 0.25 | T67: 0.25 | U67: 0.25 | V67: 0.25 | W67: 0.25 | X67: 0.25 | Y67: 0.25 | Z67: 0.25 | AA67: 0.25 | AB67: 0.25 | AC67: 0.25 | AD67: 0.25 | AE67: 0.25 | AF67: 0.25 | AG67: 0.25 | AH67: 0.25 | AI67: 0.25 | AJ67: 0.25 | AK67: 0.25 | AL67: 0.25 | AM67: 0.25 | AN67: 0.25 | AO67: 0.25 | AP67: 0.25 | AQ67: 0.25 | AR67: 0.25 | AS67: 0.25 | AT67: 0.25 | AU67: 0.25 | AV67: 0.25 | AW67: 0.25 | AX67: 0.25 | AY67: 0.25 | AZ67: 0.25 | BA67: 0.25 | BB67: 0.25 | BC67: 0.25 | BD67: 0.25 | BE67: 0.25 | BF67: 0.25 | BG67: 0.25 | BH67: 0.25 | BI67: 0.25 | BJ67: 0.25 | BK67: 0.25 | BL67: 0.25 | BM67: 0.25 | BN67: 0.25 | BO67: 0.25 | BP67: 0.25 | BQ67: 0.25 | BR67: 0.25 | BS67: 0.25 | BT67: 0.25 | BU67: 0.25 | BV67: 0.25 | BW67: 0.25 | BX67: 0.25 | BY67: 0.25 | BZ67: 0.25 | CA67: 0.25 | CB67: 0.25 | CC67: 0.25 | CD67: 0.25 | CE67: 0.25 | CF67: 0.25 | CG67: 0.25 | CH67: 0.25 | CI67: 0.25
A68: Transacciones Marketplace | B68: # | C68: ROUND(Premium_Activos*Market_Rate, 0) | D68: =ROUND(D61*D67, 0) -> 29 | E68: =ROUND(E61*E67, 0) -> 59 | F68: =ROUND(F61*F67, 0) -> 93 | G68: =ROUND(G61*G67, 0) -> 129 | H68: =ROUND(H61*H67, 0) -> 169 | I68: =ROUND(I61*I67, 0) -> 212 | J68: =ROUND(J61*J67, 0) -> 261 | K68: =ROUND(K61*K67, 0) -> 315 | ... CI68: =ROUND(CI61*CI67, 0) -> 13943890
A70: ESCENARIO ACTIVO (SELECCIÓN DINÁMICA)
A71: Crecimiento Tráfico Orgánico | B71: % | C71: 1=Neg, 2=Equi, 3=Pos | D71: =CHOOSE('1_PANEL_CONTROL'!$C$4, D11, D31, D51) -> 0.08 | E71: =CHOOSE('1_PANEL_CONTROL'!$C$4, E11, E31, E51) -> 0.08 | F71: =CHOOSE('1_PANEL_CONTROL'!$C$4, F11, F31, F51) -> 0.08 | G71: =CHOOSE('1_PANEL_CONTROL'!$C$4, G11, G31, G51) -> 0.08 | H71: =CHOOSE('1_PANEL_CONTROL'!$C$4, H11, H31, H51) -> 0.08 | I71: =CHOOSE('1_PANEL_CONTROL'!$C$4, I11, I31, I51) -> 0.08 | J71: =CHOOSE('1_PANEL_CONTROL'!$C$4, J11, J31, J51) -> 0.08 | K71: =CHOOSE('1_PANEL_CONTROL'!$C$4, K11, K31, K51) -> 0.08 | ... CI71: =CHOOSE('1_PANEL_CONTROL'!$C$4, CI11, CI31, CI51) -> 0.08
A72: Tráfico Orgánico Mensual | B72: # | C72: Dinámico | D72: =CHOOSE('1_PANEL_CONTROL'!$C$4, D12, D32, D52) -> 2027 | E72: =CHOOSE('1_PANEL_CONTROL'!$C$4, E12, E32, E52) -> 2189.16 | F72: =CHOOSE('1_PANEL_CONTROL'!$C$4, F12, F32, F52) -> 2364.2928 | G72: =CHOOSE('1_PANEL_CONTROL'!$C$4, G12, G32, G52) -> 2553.4362 | H72: =CHOOSE('1_PANEL_CONTROL'!$C$4, H12, H32, H52) -> 2757.7111 | I72: =CHOOSE('1_PANEL_CONTROL'!$C$4, I12, I32, I52) -> 2978.328 | J72: =CHOOSE('1_PANEL_CONTROL'!$C$4, J12, J32, J52) -> 3216.5943 | K72: =CHOOSE('1_PANEL_CONTROL'!$C$4, K12, K32, K52) -> 3473.9218 | ... CI72: =CHOOSE('1_PANEL_CONTROL'!$C$4, CI12, CI32, CI52) -> 1205106.6
A73: Tasa de Conversión | B73: % | C73: Dinámico | D73: =CHOOSE('1_PANEL_CONTROL'!$C$4, D13, D33, D53) -> 0.02 | E73: =CHOOSE('1_PANEL_CONTROL'!$C$4, E13, E33, E53) -> 0.02 | F73: =CHOOSE('1_PANEL_CONTROL'!$C$4, F13, F33, F53) -> 0.02 | G73: =CHOOSE('1_PANEL_CONTROL'!$C$4, G13, G33, G53) -> 0.02 | H73: =CHOOSE('1_PANEL_CONTROL'!$C$4, H13, H33, H53) -> 0.02 | I73: =CHOOSE('1_PANEL_CONTROL'!$C$4, I13, I33, I53) -> 0.02 | J73: =CHOOSE('1_PANEL_CONTROL'!$C$4, J13, J33, J53) -> 0.02 | K73: =CHOOSE('1_PANEL_CONTROL'!$C$4, K13, K33, K53) -> 0.02 | ... CI73: =CHOOSE('1_PANEL_CONTROL'!$C$4, CI13, CI33, CI53) -> 0.02
A74: Nuevos Clientes (Orgánicos) | B74: # | C74: Dinámico | D74: =CHOOSE('1_PANEL_CONTROL'!$C$4, D14, D34, D54) -> 41 | E74: =CHOOSE('1_PANEL_CONTROL'!$C$4, E14, E34, E54) -> 44 | F74: =CHOOSE('1_PANEL_CONTROL'!$C$4, F14, F34, F54) -> 47 | G74: =CHOOSE('1_PANEL_CONTROL'!$C$4, G14, G34, G54) -> 51 | H74: =CHOOSE('1_PANEL_CONTROL'!$C$4, H14, H34, H54) -> 55 | I74: =CHOOSE('1_PANEL_CONTROL'!$C$4, I14, I34, I54) -> 60 | J74: =CHOOSE('1_PANEL_CONTROL'!$C$4, J14, J34, J54) -> 64 | K74: =CHOOSE('1_PANEL_CONTROL'!$C$4, K14, K34, K54) -> 69 | ... CI74: =CHOOSE('1_PANEL_CONTROL'!$C$4, CI14, CI34, CI54) -> 24102
A75: Presupuesto Social Ads | B75: EUR | C75: Dinámico | D75: =CHOOSE('1_PANEL_CONTROL'!$C$4, D15, D35, D55) -> 2955 | E75: =CHOOSE('1_PANEL_CONTROL'!$C$4, E15, E35, E55) -> 2955 | F75: =CHOOSE('1_PANEL_CONTROL'!$C$4, F15, F35, F55) -> 2955 | G75: =CHOOSE('1_PANEL_CONTROL'!$C$4, G15, G35, G55) -> 2955 | H75: =CHOOSE('1_PANEL_CONTROL'!$C$4, H15, H35, H55) -> 2955 | I75: =CHOOSE('1_PANEL_CONTROL'!$C$4, I15, I35, I55) -> 2955 | J75: =CHOOSE('1_PANEL_CONTROL'!$C$4, J15, J35, J55) -> 2955 | K75: =CHOOSE('1_PANEL_CONTROL'!$C$4, K15, K35, K55) -> 2955 | ... CI75: =CHOOSE('1_PANEL_CONTROL'!$C$4, CI15, CI35, CI55) -> 2955
A76: CPL Paid (Coste por Lead) | B76: EUR | C76: Dinámico | D76: =CHOOSE('1_PANEL_CONTROL'!$C$4, D16, D36, D56) -> 11 | E76: =CHOOSE('1_PANEL_CONTROL'!$C$4, E16, E36, E56) -> 11 | F76: =CHOOSE('1_PANEL_CONTROL'!$C$4, F16, F36, F56) -> 11 | G76: =CHOOSE('1_PANEL_CONTROL'!$C$4, G16, G36, G56) -> 11 | H76: =CHOOSE('1_PANEL_CONTROL'!$C$4, H16, H36, H56) -> 11 | I76: =CHOOSE('1_PANEL_CONTROL'!$C$4, I16, I36, I56) -> 11 | J76: =CHOOSE('1_PANEL_CONTROL'!$C$4, J16, J36, J56) -> 11 | K76: =CHOOSE('1_PANEL_CONTROL'!$C$4, K16, K36, K56) -> 11 | ... CI76: =CHOOSE('1_PANEL_CONTROL'!$C$4, CI16, CI36, CI56) -> 11
A77: Leads de Pago Adquiridos | B77: # | C77: Dinámico | D77: =CHOOSE('1_PANEL_CONTROL'!$C$4, D17, D37, D57) -> 269 | E77: =CHOOSE('1_PANEL_CONTROL'!$C$4, E17, E37, E57) -> 269 | F77: =CHOOSE('1_PANEL_CONTROL'!$C$4, F17, F37, F57) -> 269 | G77: =CHOOSE('1_PANEL_CONTROL'!$C$4, G17, G37, G57) -> 269 | H77: =CHOOSE('1_PANEL_CONTROL'!$C$4, H17, H37, H57) -> 269 | I77: =CHOOSE('1_PANEL_CONTROL'!$C$4, I17, I37, I57) -> 269 | J77: =CHOOSE('1_PANEL_CONTROL'!$C$4, J17, J37, J57) -> 269 | K77: =CHOOSE('1_PANEL_CONTROL'!$C$4, K17, K37, K57) -> 269 | ... CI77: =CHOOSE('1_PANEL_CONTROL'!$C$4, CI17, CI37, CI57) -> 269
A78: Nuevos Clientes (Pauta/Paid) | B78: # | C78: Dinámico | D78: =CHOOSE('1_PANEL_CONTROL'!$C$4, D18, D38, D58) -> 5 | E78: =CHOOSE('1_PANEL_CONTROL'!$C$4, E18, E38, E58) -> 5 | F78: =CHOOSE('1_PANEL_CONTROL'!$C$4, F18, F38, F58) -> 5 | G78: =CHOOSE('1_PANEL_CONTROL'!$C$4, G18, G38, G58) -> 5 | H78: =CHOOSE('1_PANEL_CONTROL'!$C$4, H18, H38, H58) -> 5 | I78: =CHOOSE('1_PANEL_CONTROL'!$C$4, I18, I38, I58) -> 5 | J78: =CHOOSE('1_PANEL_CONTROL'!$C$4, J18, J38, J58) -> 5 | K78: =CHOOSE('1_PANEL_CONTROL'!$C$4, K18, K38, K58) -> 5 | ... CI78: =CHOOSE('1_PANEL_CONTROL'!$C$4, CI18, CI38, CI58) -> 5
A79: Nuevos Clientes Totales | B79: # | C79: Dinámico | D79: =CHOOSE('1_PANEL_CONTROL'!$C$4, D19, D39, D59) -> 46 | E79: =CHOOSE('1_PANEL_CONTROL'!$C$4, E19, E39, E59) -> 49 | F79: =CHOOSE('1_PANEL_CONTROL'!$C$4, F19, F39, F59) -> 52 | G79: =CHOOSE('1_PANEL_CONTROL'!$C$4, G19, G39, G59) -> 56 | H79: =CHOOSE('1_PANEL_CONTROL'!$C$4, H19, H39, H59) -> 60 | I79: =CHOOSE('1_PANEL_CONTROL'!$C$4, I19, I39, I59) -> 65 | J79: =CHOOSE('1_PANEL_CONTROL'!$C$4, J19, J39, J59) -> 69 | K79: =CHOOSE('1_PANEL_CONTROL'!$C$4, K19, K39, K59) -> 74 | ... CI79: =CHOOSE('1_PANEL_CONTROL'!$C$4, CI19, CI39, CI59) -> 24107
A80: Tasa Cancelación (Churn) | B80: % | C80: Dinámico | D80: =CHOOSE('1_PANEL_CONTROL'!$C$4, D20, D40, D60) -> 0.048 | E80: =CHOOSE('1_PANEL_CONTROL'!$C$4, E20, E40, E60) -> 0.048 | F80: =CHOOSE('1_PANEL_CONTROL'!$C$4, F20, F40, F60) -> 0.048 | G80: =CHOOSE('1_PANEL_CONTROL'!$C$4, G20, G40, G60) -> 0.048 | H80: =CHOOSE('1_PANEL_CONTROL'!$C$4, H20, H40, H60) -> 0.048 | I80: =CHOOSE('1_PANEL_CONTROL'!$C$4, I20, I40, I60) -> 0.048 | J80: =CHOOSE('1_PANEL_CONTROL'!$C$4, J20, J40, J60) -> 0.048 | K80: =CHOOSE('1_PANEL_CONTROL'!$C$4, K20, K40, K60) -> 0.048 | ... CI80: =CHOOSE('1_PANEL_CONTROL'!$C$4, CI20, CI40, CI60) -> 0.048
A81: Clientes Activos (Premium Care) | B81: # | C81: Dinámico | D81: =CHOOSE('1_PANEL_CONTROL'!$C$4, D21, D41, D61) -> 46 | E81: =CHOOSE('1_PANEL_CONTROL'!$C$4, E21, E41, E61) -> 93 | F81: =CHOOSE('1_PANEL_CONTROL'!$C$4, F21, F41, F61) -> 141 | G81: =CHOOSE('1_PANEL_CONTROL'!$C$4, G21, G41, G61) -> 190 | H81: =CHOOSE('1_PANEL_CONTROL'!$C$4, H21, H41, H61) -> 241 | I81: =CHOOSE('1_PANEL_CONTROL'!$C$4, I21, I41, I61) -> 294 | J81: =CHOOSE('1_PANEL_CONTROL'!$C$4, J21, J41, J61) -> 349 | K81: =CHOOSE('1_PANEL_CONTROL'!$C$4, K21, K41, K61) -> 406 | ... CI81: =CHOOSE('1_PANEL_CONTROL'!$C$4, CI21, CI41, CI61) -> 203460
A82: Attachment CUDI Shield Basic | B82: % | C82: Dinámico | D82: =CHOOSE('1_PANEL_CONTROL'!$C$4, D22, D42, D62) -> 0.3 | E82: =CHOOSE('1_PANEL_CONTROL'!$C$4, E22, E42, E62) -> 0.3 | F82: =CHOOSE('1_PANEL_CONTROL'!$C$4, F22, F42, F62) -> 0.3 | G82: =CHOOSE('1_PANEL_CONTROL'!$C$4, G22, G42, G62) -> 0.3 | H82: =CHOOSE('1_PANEL_CONTROL'!$C$4, H22, H42, H62) -> 0.3 | I82: =CHOOSE('1_PANEL_CONTROL'!$C$4, I22, I42, I62) -> 0.3 | J82: =CHOOSE('1_PANEL_CONTROL'!$C$4, J22, J42, J62) -> 0.3 | K82: =CHOOSE('1_PANEL_CONTROL'!$C$4, K22, K42, K62) -> 0.3 | ... CI82: =CHOOSE('1_PANEL_CONTROL'!$C$4, CI22, CI42, CI62) -> 0.3
... A88: Transacciones Marketplace | B88: # | C88: Dinámico | D88: =CHOOSE('1_PANEL_CONTROL'!$C$4, D28, D48, D68) -> 9 | E88: =CHOOSE('1_PANEL_CONTROL'!$C$4, E28, E48, E68) -> 19 | F88: =CHOOSE('1_PANEL_CONTROL'!$C$4, F28, F48, F68) -> 28 | G88: =CHOOSE('1_PANEL_CONTROL'!$C$4, G28, G48, G68) -> 38 | H88: =CHOOSE('1_PANEL_CONTROL'!$C$4, H28, H48, H68) -> 48 | I88: =CHOOSE('1_PANEL_CONTROL'!$C$4, I28, I48, I68) -> 59 | J88: =CHOOSE('1_PANEL_CONTROL'!$C$4, J28, J48, J68) -> 70 | K88: =CHOOSE('1_PANEL_CONTROL'!$C$4, K28, K48, K68) -> 81 | ... CI88: =CHOOSE('1_PANEL_CONTROL'!$C$4, CI28, CI48, CI68) -> 40692
A90: MANUAL DE INTERPRETACIÓN DE DEMANDA (JURADO TFM)
A91: 1. ADQUISICIÓN ORGÁNICA (SEO Y CONTENIDOS - FASE 1): - Crecimiento Tráfico Orgánico: Tasa de incremento mensual de las visitas no pagadas. En Equilibrio se calibra al 8,0% mensual. - Tráfico Orgánico Mensual: Visitas brutas a la plataforma. Inicia en 1.000 y crece mediante SEO off-page e in-bound. - Tasa de Conversión: Porcentaje de visitas web (u orgánicas) y leads que se registran y contratan el plan Premium Care (SaaS) (2,0% en Equilibrio). - Nuevos Clientes (Orgánicos): Tráfico Orgánico * Tasa de Conversión. Son clientes captados a coste marginal cero. 2. ADQUISICIÓN DE PAGO (SOCIAL ADS - FASES 2 A 5): - Presupuesto Social Ads: Inversión en Meta/TikTok publicitario (2.955 €/mes en Equilibrio). Con CPL (Coste por Lead) de 11 €, genera 269 leads/mes. - Nuevos Clientes (Pauta/Paid): Leads * Tasa de Conversión. Clientes captados con inversión de pauta. - Nuevos Clientes Totales: Orgánicos + de Pago. Representa las ventas de Smart Collars mensuales (alta de hardware). 3. RETENCIÓN Y MONETIZACIÓN RECURRENTE: - Tasa Cancelación (Churn): Porcentaje de bajas mensuales de la suscripción (4,8% en Equilibrio, vida media de 20,8 meses). - Clientes Activos (Premium Care): Base total acumulada viva. Paga la suscripción mensual SaaS de 30 €/mes. - Ventas Cruzadas (Attachment Rates): * CUDI Shield Basic: 30% de los clientes Premium Care activos contratan el seguro de salud veterinaria (18 €/mes). * VetHome: 4,5% de los clientes activos solicita visitas presenciales a domicilio (75 €/visita). * Marketplace: 20% de los clientes realiza transacciones en la tienda (ticket medio de 25 €, comisión neta del 15% para CUDI).
B104: GUÍA DE PROYECCIÓN DE DEMANDA Y FUNNEL DE USUARIOS
B105: 1. FUNNEL DE CONVERSIÓN MENSUAL: - Muestra de forma detallada la conversión desde Visitas Orgánicas y Leads de Pago hasta Nuevos Clientes Totales. - La columna 'Dinámico' se conecta con el selector activo para calcular el total de usuarios activos mes a mes. 2. ANÁLISIS DE ALTAS Y BAJAS (CHURN): - La base de Clientes Activos Premium acumula las altas del mes y resta las bajas aplicando el Churn Rate. - Hito de Control: El escenario de Equilibrio persigue alcanzar **670 suscriptores Premium activos** en el Mes 12.

Sheet 5_DETALLE_INGRESOS
A4: MODELO DE INGRESOS MENSUAL DE CUDI
A5: Escenario Activo: | B5: =CHOOSE('1_PANEL_CONTROL'!$C$4, "🔴 1: NEGATIVO", "🟡 2: EQUILIBRIO", "🟢 3: POSITIVO") -> 🟡 2: EQUILIBRIO | D5: =CHOOSE('1_PANEL_CONTROL'!$C$4, "[NEGATIVO] PLAN DE INGRESOS MENSUALES. La facturación Premium Care en mes 12 es de " & TEXT('5_DETALLE_INGRESOS'!O26, "#.##0 €") & ", acumulando una facturación consolidada en el primer año de " & TEXT(SUM('5_DETALLE_INGRESOS'!$D$37:$O$37), "#.##0 €") & ".", "[EQUILIBRIO] PLAN DE INGRESOS MENSUALES. En el mes 12, el seguro Shield aporta " & TEXT('5_DETALLE_INGRESOS'!O27, "#.##0 €") & " y el B2B/Afiliados genera " & TEXT('5_DETALLE_INGRESOS'!O36, "#.##0 €") & " adicionales sobre base Premium Care.", "[POSITIVO] PLAN DE INGRESOS MENSUALES. En el mes 12, los ingresos B2B y seguros aportan " & TEXT('5_DETALLE_INGRESOS'!O36, "#.##0 €") & ", elevando la facturación total a " & TEXT(SUM('5_DETALLE_INGRESOS'!$D$37:$O$37), "#.##0 €") & " en Año 1.") -> [EQUILIBRIO] PLAN DE INGRESOS MENSUALES. En el mes 12, el seguro Shield aporta 1.868 € y el B2B/Afiliados genera 8.209 € adicionales sobre base Premium Care.
A7: Métricas de Volumen | B7: Unidad | C7: Fórmula / Regla | D7: Ene-26 | E7: Feb-26 | F7: Mar-26 | G7: Abr-26 | H7: May-26 | I7: Jun-26 | J7: Jul-26 | K7: Ago-26 | L7: Sep-26 | M7: Oct-26 | N7: Nov-26 | O7: Dic-26 | P7: Ene-27 | Q7: Feb-27 | R7: Mar-27 | S7: Abr-27 | T7: May-27 | U7: Jun-27 | V7: Jul-27 | W7: Ago-27 | X7: Sep-27 | Y7: Oct-27 | Z7: Nov-27 | AA7: Dic-27 | AB7: Ene-28 | AC7: Feb-28 | AD7: Mar-28 | AE7: Abr-28 | AF7: May-28 | AG7: Jun-28 | AH7: Jul-28 | AI7: Ago-28 | AJ7: Sep-28 | AK7: Oct-28 | AL7: Nov-28 | AM7: Dic-28 | AN7: Ene-29 | AO7: Feb-29 | AP7: Mar-29 | AQ7: Abr-29 | AR7: May-29 | AS7: Jun-29 | AT7: Jul-29 | AU7: Ago-29 | AV7: Sep-29 | AW7: Oct-29 | AX7: Nov-29 | AY7: Dic-29 | AZ7: Ene-30 | BA7: Feb-30 | BB7: Mar-30 | BC7: Abr-30 | BD7: May-30 | BE7: Jun-30 | BF7: Jul-30 | BG7: Ago-30 | BH7: Sep-30 | BI7: Oct-30 | BJ7: Nov-30 | BK7: Dic-30 | BL7: Ene-31 | BM7: Feb-31 | BN7: Mar-31 | BO7: Abr-31 | BP7: May-31 | BQ7: Jun-31 | BR7: Jul-31 | BS7: Ago-31 | BT7: Sep-31 | BU7: Oct-31 | BV7: Nov-31 | BW7: Dic-31 | BX7: Ene-32 | BY7: Feb-32 | BZ7: Mar-32 | CA7: Abr-32 | CB7: May-32 | CC7: Jun-32 | CD7: Jul-32 | CE7: Ago-32 | CF7: Sep-32 | CG7: Oct-32 | CH7: Nov-32 | CI7: Dic-32
A10: Tráfico Orgánico | B10: # | C10: Link a '4_PROY_DEMANDA'!Row 71 | D10: ='4_PROY_DEMANDA'!D72 -> 2027 | E10: ='4_PROY_DEMANDA'!E72 -> 2189.16 | F10: ='4_PROY_DEMANDA'!F72 -> 2364.2928 | G10: ='4_PROY_DEMANDA'!G72 -> 2553.4362 | H10: ='4_PROY_DEMANDA'!H72 -> 2757.7111 | I10: ='4_PROY_DEMANDA'!I72 -> 2978.328 | J10: ='4_PROY_DEMANDA'!J72 -> 3216.5943 | K10: ='4_PROY_DEMANDA'!K72 -> 3473.9218 | ... CI10: ='4_PROY_DEMANDA'!CI72 -> 1205106.6
A11: Tasa de Conversión | B11: % | C11: Link a '4_PROY_DEMANDA'!Row 72 | D11: ='4_PROY_DEMANDA'!D73 -> 0.02 | E11: ='4_PROY_DEMANDA'!E73 -> 0.02 | F11: ='4_PROY_DEMANDA'!F73 -> 0.02 | G11: ='4_PROY_DEMANDA'!G73 -> 0.02 | H11: ='4_PROY_DEMANDA'!H73 -> 0.02 | I11: ='4_PROY_DEMANDA'!I73 -> 0.02 | J11: ='4_PROY_DEMANDA'!J73 -> 0.02 | K11: ='4_PROY_DEMANDA'!K73 -> 0.02 | ... CI11: ='4_PROY_DEMANDA'!CI73 -> 0.02
A12: Nuevos Clientes (Orgánicos) | B12: # | C12: Link a '4_PROY_DEMANDA'!Row 73 | D12: ='4_PROY_DEMANDA'!D74 -> 41 | E12: ='4_PROY_DEMANDA'!E74 -> 44 | F12: ='4_PROY_DEMANDA'!F74 -> 47 | G12: ='4_PROY_DEMANDA'!G74 -> 51 | H12: ='4_PROY_DEMANDA'!H74 -> 55 | I12: ='4_PROY_DEMANDA'!I74 -> 60 | J12: ='4_PROY_DEMANDA'!J74 -> 64 | K12: ='4_PROY_DEMANDA'!K74 -> 69 | ... CI12: ='4_PROY_DEMANDA'!CI74 -> 24102
A13: Presupuesto Publicitario | B13: EUR | C13: Link a '4_PROY_DEMANDA'!Row 74 | D13: ='4_PROY_DEMANDA'!D75 -> 2955 | E13: ='4_PROY_DEMANDA'!E75 -> 2955 | F13: ='4_PROY_DEMANDA'!F75 -> 2955 | G13: ='4_PROY_DEMANDA'!G75 -> 2955 | H13: ='4_PROY_DEMANDA'!H75 -> 2955 | I13: ='4_PROY_DEMANDA'!I75 -> 2955 | J13: ='4_PROY_DEMANDA'!J75 -> 2955 | K13: ='4_PROY_DEMANDA'!K75 -> 2955 | ... CI13: ='4_PROY_DEMANDA'!CI75 -> 2955
A14: CAC Paid (CPL de Pago) | B14: EUR | C14: Link a '4_PROY_DEMANDA'!Row 75 | D14: ='4_PROY_DEMANDA'!D76 -> 11 | E14: ='4_PROY_DEMANDA'!E76 -> 11 | F14: ='4_PROY_DEMANDA'!F76 -> 11 | G14: ='4_PROY_DEMANDA'!G76 -> 11 | H14: ='4_PROY_DEMANDA'!H76 -> 11 | I14: ='4_PROY_DEMANDA'!I76 -> 11 | J14: ='4_PROY_DEMANDA'!J76 -> 11 | K14: ='4_PROY_DEMANDA'!K76 -> 11 | ... CI14: ='4_PROY_DEMANDA'!CI76 -> 11
A15: Nuevos Clientes (Pauta/Paid) | B15: # | C15: Link a '4_PROY_DEMANDA'!Row 77 | D15: ='4_PROY_DEMANDA'!D78 -> 5 | E15: ='4_PROY_DEMANDA'!E78 -> 5 | F15: ='4_PROY_DEMANDA'!F78 -> 5 | G15: ='4_PROY_DEMANDA'!G78 -> 5 | H15: ='4_PROY_DEMANDA'!H78 -> 5 | I15: ='4_PROY_DEMANDA'!I78 -> 5 | J15: ='4_PROY_DEMANDA'!J78 -> 5 | K15: ='4_PROY_DEMANDA'!K78 -> 5 | ... CI15: ='4_PROY_DEMANDA'!CI78 -> 5
A16: Nuevos Clientes Totales | B16: # | C16: Link a '4_PROY_DEMANDA'!Row 78 | D16: ='4_PROY_DEMANDA'!D79 -> 46 | E16: ='4_PROY_DEMANDA'!E79 -> 49 | F16: ='4_PROY_DEMANDA'!F79 -> 52 | G16: ='4_PROY_DEMANDA'!G79 -> 56 | H16: ='4_PROY_DEMANDA'!H79 -> 60 | I16: ='4_PROY_DEMANDA'!I79 -> 65 | J16: ='4_PROY_DEMANDA'!J79 -> 69 | K16: ='4_PROY_DEMANDA'!K79 -> 74 | ... CI16: ='4_PROY_DEMANDA'!CI79 -> 24107
A17: Tasa de Cancelación (Churn) | B17: % | C17: Link a '4_PROY_DEMANDA'!Row 79 | D17: ='4_PROY_DEMANDA'!D80 -> 0.048 | E17: ='4_PROY_DEMANDA'!E80 -> 0.048 | F17: ='4_PROY_DEMANDA'!F80 -> 0.048 | G17: ='4_PROY_DEMANDA'!G80 -> 0.048 | H17: ='4_PROY_DEMANDA'!H80 -> 0.048 | I17: ='4_PROY_DEMANDA'!I80 -> 0.048 | J17: ='4_PROY_DEMANDA'!J80 -> 0.048 | K17: ='4_PROY_DEMANDA'!K80 -> 0.048 | ... CI17: ='4_PROY_DEMANDA'!CI80 -> 0.048
A18: Clientes Activos (Premium Care) | B18: # | C18: Link a '4_PROY_DEMANDA'!Row 80 | D18: ='4_PROY_DEMANDA'!D81 -> 46 | E18: ='4_PROY_DEMANDA'!E81 -> 93 | F18: ='4_PROY_DEMANDA'!F81 -> 141 | G18: ='4_PROY_DEMANDA'!G81 -> 190 | H18: ='4_PROY_DEMANDA'!H81 -> 241 | I18: ='4_PROY_DEMANDA'!I81 -> 294 | J18: ='4_PROY_DEMANDA'!J81 -> 349 | K18: ='4_PROY_DEMANDA'!K81 -> 406 | ... CI18: ='4_PROY_DEMANDA'!CI81 -> 203460
A19: Clientes Activos (Shield Seguro) | B19: # | C19: Link a '4_PROY_DEMANDA'!Row 82 | D19: ='4_PROY_DEMANDA'!D83 -> 14 | E19: ='4_PROY_DEMANDA'!E83 -> 28 | F19: ='4_PROY_DEMANDA'!F83 -> 42 | G19: ='4_PROY_DEMANDA'!G83 -> 57 | H19: ='4_PROY_DEMANDA'!H83 -> 72 | I19: ='4_PROY_DEMANDA'!I83 -> 88 | J19: ='4_PROY_DEMANDA'!J83 -> 105 | K19: ='4_PROY_DEMANDA'!K83 -> 122 | ... CI19: ='4_PROY_DEMANDA'!CI83 -> 61038
A20: Smart Collars Vendidos | B20: # | C20: Link a '4_PROY_DEMANDA'!Row 83 | D20: ='4_PROY_DEMANDA'!D84 -> 46 | E20: ='4_PROY_DEMANDA'!E84 -> 49 | F20: ='4_PROY_DEMANDA'!F84 -> 52 | G20: ='4_PROY_DEMANDA'!G84 -> 56 | H20: ='4_PROY_DEMANDA'!H84 -> 60 | I20: ='4_PROY_DEMANDA'!I84 -> 65 | J20: ='4_PROY_DEMANDA'!J84 -> 69 | K20: ='4_PROY_DEMANDA'!K84 -> 74 | ... CI20: ='4_PROY_DEMANDA'!CI84 -> 24107
A21: Visitas VetHome | B21: # | C21: Link a '4_PROY_DEMANDA'!Row 85 | D21: ='4_PROY_DEMANDA'!D86 -> 2 | E21: ='4_PROY_DEMANDA'!E86 -> 4 | F21: ='4_PROY_DEMANDA'!F86 -> 6 | G21: ='4_PROY_DEMANDA'!G86 -> 9 | H21: ='4_PROY_DEMANDA'!H86 -> 11 | I21: ='4_PROY_DEMANDA'!I86 -> 13 | J21: ='4_PROY_DEMANDA'!J86 -> 16 | K21: ='4_PROY_DEMANDA'!K86 -> 18 | ... CI21: ='4_PROY_DEMANDA'!CI86 -> 9156
A22: Compradores Marketplace | B22: # | C22: Link a '4_PROY_DEMANDA'!Row 87 | D22: ='4_PROY_DEMANDA'!D88 -> 9 | E22: ='4_PROY_DEMANDA'!E88 -> 19 | F22: ='4_PROY_DEMANDA'!F88 -> 28 | G22: ='4_PROY_DEMANDA'!G88 -> 38 | H22: ='4_PROY_DEMANDA'!H88 -> 48 | I22: ='4_PROY_DEMANDA'!I88 -> 59 | J22: ='4_PROY_DEMANDA'!J88 -> 70 | K22: ='4_PROY_DEMANDA'!K88 -> 81 | ... CI22: ='4_PROY_DEMANDA'!CI88 -> 40692
A24: DESGLOSE DE INGRESOS (EUR)
A26: Suscripción Premium Care (SaaS) | B26: EUR | C26: ActivePremium * PriceSuscrip | D26: =D18*(1-'1_PANEL_CONTROL'!$C$138)*'1_PANEL_CONTROL'!$C$15 + D18*'1_PANEL_CONTROL'!$C$138*'1_PANEL_CONTROL'!$C$15*(1-'1_PANEL_CONTROL'!$C$139) -> 1317.9 | E26: =E18*(1-'1_PANEL_CONTROL'!$C$138)*'1_PANEL_CONTROL'!$C$15 + E18*'1_PANEL_CONTROL'!$C$138*'1_PANEL_CONTROL'!$C$15*(1-'1_PANEL_CONTROL'!$C$139) -> 2664.45 | F26: =F18*(1-'1_PANEL_CONTROL'!$C$138)*'1_PANEL_CONTROL'!$C$15 + F18*'1_PANEL_CONTROL'!$C$138*'1_PANEL_CONTROL'!$C$15*(1-'1_PANEL_CONTROL'!$C$139) -> 4039.65 | G26: =G18*(1-'1_PANEL_CONTROL'!$C$138)*'1_PANEL_CONTROL'!$C$15 + G18*'1_PANEL_CONTROL'!$C$138*'1_PANEL_CONTROL'!$C$15*(1-'1_PANEL_CONTROL'!$C$139) -> 5443.5 | H26: =H18*(1-'1_PANEL_CONTROL'!$C$138)*'1_PANEL_CONTROL'!$C$15 + H18*'1_PANEL_CONTROL'!$C$138*'1_PANEL_CONTROL'!$C$15*(1-'1_PANEL_CONTROL'!$C$139) -> 6904.65 | I26: =I18*(1-'1_PANEL_CONTROL'!$C$138)*'1_PANEL_CONTROL'!$C$15 + I18*'1_PANEL_CONTROL'!$C$138*'1_PANEL_CONTROL'!$C$15*(1-'1_PANEL_CONTROL'!$C$139) -> 8423.1 | J26: =J18*(1-'1_PANEL_CONTROL'!$C$138)*'1_PANEL_CONTROL'!$C$15 + J18*'1_PANEL_CONTROL'!$C$138*'1_PANEL_CONTROL'!$C$15*(1-'1_PANEL_CONTROL'!$C$139) -> 9998.85 | K26: =K18*(1-'1_PANEL_CONTROL'!$C$138)*'1_PANEL_CONTROL'!$C$15 + K18*'1_PANEL_CONTROL'!$C$138*'1_PANEL_CONTROL'!$C$15*(1-'1_PANEL_CONTROL'!$C$139) -> 11631.9 | ... CI26: =CI18*(1-'1_PANEL_CONTROL'!$C$138)*'1_PANEL_CONTROL'!$C$15 + CI18*'1_PANEL_CONTROL'!$C$138*'1_PANEL_CONTROL'!$C$15*(1-'1_PANEL_CONTROL'!$C$139) -> 5829129
A27: Seguro CUDI Shield Basic | B27: EUR | C27: ActiveShield * PriceShield | D27: =D19*'1_PANEL_CONTROL'!$C$128+D16*CHOOSE('1_PANEL_CONTROL'!$C$4, '1_PANEL_CONTROL'!$C$118, '1_PANEL_CONTROL'!$C$119, '1_PANEL_CONTROL'!$C$120)*CHOOSE('1_PANEL_CONTROL'!$C$4, '1_PANEL_CONTROL'!$C$121, '1_PANEL_CONTROL'!$C$122, '1_PANEL_CONTROL'!$C$123)+D16*CHOOSE('1_PANEL_CONTROL'!$C$4, '1_PANEL_CONTROL'!$C$118, '1_PANEL_CONTROL'!$C$119, '1_PANEL_CONTROL'!$C$120)*CHOOSE('1_PANEL_CONTROL'!$C$4, '1_PANEL_CONTROL'!$C$124, '1_PANEL_CONTROL'!$C$125, '1_PANEL_CONTROL'!$C$126)*'1_PANEL_CONTROL'!$C$127 -> 466.75 | E27: =E19*'1_PANEL_CONTROL'!$C$128+E16*CHOOSE('1_PANEL_CONTROL'!$C$4, '1_PANEL_CONTROL'!$C$118, '1_PANEL_CONTROL'!$C$119, '1_PANEL_CONTROL'!$C$120)*CHOOSE('1_PANEL_CONTROL'!$C$4, '1_PANEL_CONTROL'!$C$121, '1_PANEL_CONTROL'!$C$122, '1_PANEL_CONTROL'!$C$123)+E16*CHOOSE('1_PANEL_CONTROL'!$C$4, '1_PANEL_CONTROL'!$C$118, '1_PANEL_CONTROL'!$C$119, '1_PANEL_CONTROL'!$C$120)*CHOOSE('1_PANEL_CONTROL'!$C$4, '1_PANEL_CONTROL'!$C$124, '1_PANEL_CONTROL'!$C$125, '1_PANEL_CONTROL'!$C$126)*'1_PANEL_CONTROL'!$C$127 -> 562.625 | F27: =F19*'1_PANEL_CONTROL'!$C$128+F16*CHOOSE('1_PANEL_CONTROL'!$C$4, '1_PANEL_CONTROL'!$C$118, '1_PANEL_CONTROL'!$C$119, '1_PANEL_CONTROL'!$C$120)*CHOOSE('1_PANEL_CONTROL'!$C$4, '1_PANEL_CONTROL'!$C$121, '1_PANEL_CONTROL'!$C$122, '1_PANEL_CONTROL'!$C$123)+F16*CHOOSE('1_PANEL_CONTROL'!$C$4, '1_PANEL_CONTROL'!$C$118, '1_PANEL_CONTROL'!$C$119, '1_PANEL_CONTROL'!$C$120)*CHOOSE('1_PANEL_CONTROL'!$C$4, '1_PANEL_CONTROL'!$C$124, '1_PANEL_CONTROL'!$C$125, '1_PANEL_CONTROL'!$C$126)*'1_PANEL_CONTROL'!$C$127 -> 658.5 | G27: =G19*'1_PANEL_CONTROL'!$C$128+G16*CHOOSE('1_PANEL_CONTROL'!$C$4, '1_PANEL_CONTROL'!$C$118, '1_PANEL_CONTROL'!$C$119, '1_PANEL_CONTROL'!$C$120)*CHOOSE('1_PANEL_CONTROL'!$C$4, '1_PANEL_CONTROL'!$C$121, '1_PANEL_CONTROL'!$C$122, '1_PANEL_CONTROL'!$C$123)+G16*CHOOSE('1_PANEL_CONTROL'!$C$4, '1_PANEL_CONTROL'!$C$118, '1_PANEL_CONTROL'!$C$119, '1_PANEL_CONTROL'!$C$120)*CHOOSE('1_PANEL_CONTROL'!$C$4, '1_PANEL_CONTROL'!$C$124, '1_PANEL_CONTROL'!$C$125, '1_PANEL_CONTROL'!$C$126)*'1_PANEL_CONTROL'!$C$127 -> 768 | H27: =H19*'1_PANEL_CONTROL'!$C$128+H16*CHOOSE('1_PANEL_CONTROL'!$C$4, '1_PANEL_CONTROL'!$C$118, '1_PANEL_CONTROL'!$C$119, '1_PANEL_CONTROL'!$C$120)*CHOOSE('1_PANEL_CONTROL'!$C$4, '1_PANEL_CONTROL'!$C$121, '1_PANEL_CONTROL'!$C$122, '1_PANEL_CONTROL'!$C$123)+H16*CHOOSE('1_PANEL_CONTROL'!$C$4, '1_PANEL_CONTROL'!$C$118, '1_PANEL_CONTROL'!$C$119, '1_PANEL_CONTROL'!$C$120)*CHOOSE('1_PANEL_CONTROL'!$C$4, '1_PANEL_CONTROL'!$C$124, '1_PANEL_CONTROL'!$C$125, '1_PANEL_CONTROL'!$C$126)*'1_PANEL_CONTROL'!$C$127 -> 877.5 | I27: =I19*'1_PANEL_CONTROL'!$C$128+I16*CHOOSE('1_PANEL_CONTROL'!$C$4, '1_PANEL_CONTROL'!$C$118, '1_PANEL_CONTROL'!$C$119, '1_PANEL_CONTROL'!$C$120)*CHOOSE('1_PANEL_CONTROL'!$C$4, '1_PANEL_CONTROL'!$C$121, '1_PANEL_CONTROL'!$C$122, '1_PANEL_CONTROL'!$C$123)+I16*CHOOSE('1_PANEL_CONTROL'!$C$4, '1_PANEL_CONTROL'!$C$118, '1_PANEL_CONTROL'!$C$119, '1_PANEL_CONTROL'!$C$120)*CHOOSE('1_PANEL_CONTROL'!$C$4, '1_PANEL_CONTROL'!$C$124, '1_PANEL_CONTROL'!$C$125, '1_PANEL_CONTROL'!$C$126)*'1_PANEL_CONTROL'!$C$127 -> 1000.625 | J27: =J19*'1_PANEL_CONTROL'!$C$128+J16*CHOOSE('1_PANEL_CONTROL'!$C$4, '1_PANEL_CONTROL'!$C$118, '1_PANEL_CONTROL'!$C$119, '1_PANEL_CONTROL'!$C$120)*CHOOSE('1_PANEL_CONTROL'!$C$4, '1_PANEL_CONTROL'!$C$121, '1_PANEL_CONTROL'!$C$122, '1_PANEL_CONTROL'!$C$123)+J16*CHOOSE('1_PANEL_CONTROL'!$C$4, '1_PANEL_CONTROL'!$C$118, '1_PANEL_CONTROL'!$C$119, '1_PANEL_CONTROL'!$C$120)*CHOOSE('1_PANEL_CONTROL'!$C$4, '1_PANEL_CONTROL'!$C$124, '1_PANEL_CONTROL'!$C$125, '1_PANEL_CONTROL'!$C$126)*'1_PANEL_CONTROL'!$C$127 -> 1120.125 | K27: =K19*'1_PANEL_CONTROL'!$C$128+K16*CHOOSE('1_PANEL_CONTROL'!$C$4, '1_PANEL_CONTROL'!$C$118, '1_PANEL_CONTROL'!$C$119, '1_PANEL_CONTROL'!$C$120)*CHOOSE('1_PANEL_CONTROL'!$C$4, '1_PANEL_CONTROL'!$C$121, '1_PANEL_CONTROL'!$C$122, '1_PANEL_CONTROL'!$C$123)+K16*CHOOSE('1_PANEL_CONTROL'!$C$4, '1_PANEL_CONTROL'!$C$118, '1_PANEL_CONTROL'!$C$119, '1_PANEL_CONTROL'!$C$120)*CHOOSE('1_PANEL_CONTROL'!$C$4, '1_PANEL_CONTROL'!$C$124, '1_PANEL_CONTROL'!$C$125, '1_PANEL_CONTROL'!$C$126)*'1_PANEL_CONTROL'!$C$127 -> 1248.25 | ... CI27: =CI19*'1_PANEL_CONTROL'!$C$128+CI16*CHOOSE('1_PANEL_CONTROL'!$C$4, '1_PANEL_CONTROL'!$C$118, '1_PANEL_CONTROL'!$C$119, '1_PANEL_CONTROL'!$C$120)*CHOOSE('1_PANEL_CONTROL'!$C$4, '1_PANEL_CONTROL'!$C$121, '1_PANEL_CONTROL'!$C$122, '1_PANEL_CONTROL'!$C$123)+CI16*CHOOSE('1_PANEL_CONTROL'!$C$4, '1_PANEL_CONTROL'!$C$118, '1_PANEL_CONTROL'!$C$119, '1_PANEL_CONTROL'!$C$120)*CHOOSE('1_PANEL_CONTROL'!$C$4, '1_PANEL_CONTROL'!$C$124, '1_PANEL_CONTROL'!$C$125, '1_PANEL_CONTROL'!$C$126)*'1_PANEL_CONTROL'!$C$127 -> 513112.88
A28: Venta Collares (Hardware) | B28: EUR | C28: CollarsSold * PriceCollar | D28: =D20*'1_PANEL_CONTROL'!$C$16 -> 4117 | E28: =E20*'1_PANEL_CONTROL'!$C$16 -> 4385.5 | F28: =F20*'1_PANEL_CONTROL'!$C$16 -> 4654 | G28: =G20*'1_PANEL_CONTROL'!$C$16 -> 5012 | H28: =H20*'1_PANEL_CONTROL'!$C$16 -> 5370 | I28: =I20*'1_PANEL_CONTROL'!$C$16 -> 5817.5 | J28: =J20*'1_PANEL_CONTROL'!$C$16 -> 6175.5 | K28: =K20*'1_PANEL_CONTROL'!$C$16 -> 6623 | ... CI28: =CI20*'1_PANEL_CONTROL'!$C$16 -> 2157576.5
A29: Servicios VetHome CUDI | B29: EUR | C29: Visits * PriceVetHome | D29: =D21*'1_PANEL_CONTROL'!$C$18 -> 150 | E29: =E21*'1_PANEL_CONTROL'!$C$18 -> 300 | F29: =F21*'1_PANEL_CONTROL'!$C$18 -> 450 | G29: =G21*'1_PANEL_CONTROL'!$C$18 -> 675 | H29: =H21*'1_PANEL_CONTROL'!$C$18 -> 825 | I29: =I21*'1_PANEL_CONTROL'!$C$18 -> 975 | J29: =J21*'1_PANEL_CONTROL'!$C$18 -> 1200 | K29: =K21*'1_PANEL_CONTROL'!$C$18 -> 1350 | ... CI29: =CI21*'1_PANEL_CONTROL'!$C$18 -> 686700
A30: Comisiones Marketplace | B30: EUR | C30: MarketplaceUsers * CommissionMarket | D30: =D22*'1_PANEL_CONTROL'!$C$21 -> 33.75 | E30: =E22*'1_PANEL_CONTROL'!$C$21 -> 71.25 | F30: =F22*'1_PANEL_CONTROL'!$C$21 -> 105 | G30: =G22*'1_PANEL_CONTROL'!$C$21 -> 142.5 | H30: =H22*'1_PANEL_CONTROL'!$C$21 -> 180 | I30: =I22*'1_PANEL_CONTROL'!$C$21 -> 221.25 | J30: =J22*'1_PANEL_CONTROL'!$C$21 -> 262.5 | K30: =K22*'1_PANEL_CONTROL'!$C$21 -> 303.75 | ... CI30: =CI22*'1_PANEL_CONTROL'!$C$21 -> 152595
A31: SaaS Clínicas Veterinarias (B2B) | B31: EUR | C31: ActiveClinics * VetSaaS_Fee | D31: =CHOOSE('1_PANEL_CONTROL'!$C$4, MIN(5+INT(D18/100), 15), MIN(10+INT(D18/50), 30), MIN(20+INT(D18/25), 60))*CHOOSE('1_PANEL_CONTROL'!$C$4, '1_PANEL_CONTROL'!$C$114, '1_PANEL_CONTROL'!$C$115, '1_PANEL_CONTROL'!$C$116) -> 800 | E31: =CHOOSE('1_PANEL_CONTROL'!$C$4, MIN(5+INT(E18/100), 15), MIN(10+INT(E18/50), 30), MIN(20+INT(E18/25), 60))*CHOOSE('1_PANEL_CONTROL'!$C$4, '1_PANEL_CONTROL'!$C$114, '1_PANEL_CONTROL'!$C$115, '1_PANEL_CONTROL'!$C$116) -> 880 | F31: =CHOOSE('1_PANEL_CONTROL'!$C$4, MIN(5+INT(F18/100), 15), MIN(10+INT(F18/50), 30), MIN(20+INT(F18/25), 60))*CHOOSE('1_PANEL_CONTROL'!$C$4, '1_PANEL_CONTROL'!$C$114, '1_PANEL_CONTROL'!$C$115, '1_PANEL_CONTROL'!$C$116) -> 960 | G31: =CHOOSE('1_PANEL_CONTROL'!$C$4, MIN(5+INT(G18/100), 15), MIN(10+INT(G18/50), 30), MIN(20+INT(G18/25), 60))*CHOOSE('1_PANEL_CONTROL'!$C$4, '1_PANEL_CONTROL'!$C$114, '1_PANEL_CONTROL'!$C$115, '1_PANEL_CONTROL'!$C$116) -> 1040 | H31: =CHOOSE('1_PANEL_CONTROL'!$C$4, MIN(5+INT(H18/100), 15), MIN(10+INT(H18/50), 30), MIN(20+INT(H18/25), 60))*CHOOSE('1_PANEL_CONTROL'!$C$4, '1_PANEL_CONTROL'!$C$114, '1_PANEL_CONTROL'!$C$115, '1_PANEL_CONTROL'!$C$116) -> 1120 | I31: =CHOOSE('1_PANEL_CONTROL'!$C$4, MIN(5+INT(I18/100), 15), MIN(10+INT(I18/50), 30), MIN(20+INT(I18/25), 60))*CHOOSE('1_PANEL_CONTROL'!$C$4, '1_PANEL_CONTROL'!$C$114, '1_PANEL_CONTROL'!$C$115, '1_PANEL_CONTROL'!$C$116) -> 1200 | J31: =CHOOSE('1_PANEL_CONTROL'!$C$4, MIN(5+INT(J18/100), 15), MIN(10+INT(J18/50), 30), MIN(20+INT(J18/25), 60))*CHOOSE('1_PANEL_CONTROL'!$C$4, '1_PANEL_CONTROL'!$C$114, '1_PANEL_CONTROL'!$C$115, '1_PANEL_CONTROL'!$C$116) -> 1280 | K31: =CHOOSE('1_PANEL_CONTROL'!$C$4, MIN(5+INT(K18/100), 15), MIN(10+INT(K18/50), 30), MIN(20+INT(K18/25), 60))*CHOOSE('1_PANEL_CONTROL'!$C$4, '1_PANEL_CONTROL'!$C$114, '1_PANEL_CONTROL'!$C$115, '1_PANEL_CONTROL'!$C$116) -> 1440 | ... CI31: =CHOOSE('1_PANEL_CONTROL'!$C$4, MIN(5+INT(CI18/100), 15), MIN(10+INT(CI18/50), 30), MIN(20+INT(CI18/25), 60))*CHOOSE('1_PANEL_CONTROL'!$C$4, '1_PANEL_CONTROL'!$C$114, '1_PANEL_CONTROL'!$C$115, '1_PANEL_CONTROL'!$C$116) -> 2400
A32: SaaS Profesionales Petme (B2B) | B32: EUR | C32: ActiveProfessionals * ProfessionalSaaS_Fee | D32: =CHOOSE('1_PANEL_CONTROL'!$C$4, 0, MIN(2+INT(D18/40), 20), MIN(5+INT(D18/15), 80))*'1_PANEL_CONTROL'!$C$117 -> 119.97 | E32: =CHOOSE('1_PANEL_CONTROL'!$C$4, 0, MIN(2+INT(E18/40), 20), MIN(5+INT(E18/15), 80))*'1_PANEL_CONTROL'!$C$117 -> 159.96 | F32: =CHOOSE('1_PANEL_CONTROL'!$C$4, 0, MIN(2+INT(F18/40), 20), MIN(5+INT(F18/15), 80))*'1_PANEL_CONTROL'!$C$117 -> 199.95 | G32: =CHOOSE('1_PANEL_CONTROL'!$C$4, 0, MIN(2+INT(G18/40), 20), MIN(5+INT(G18/15), 80))*'1_PANEL_CONTROL'!$C$117 -> 239.94 | H32: =CHOOSE('1_PANEL_CONTROL'!$C$4, 0, MIN(2+INT(H18/40), 20), MIN(5+INT(H18/15), 80))*'1_PANEL_CONTROL'!$C$117 -> 319.92 | I32: =CHOOSE('1_PANEL_CONTROL'!$C$4, 0, MIN(2+INT(I18/40), 20), MIN(5+INT(I18/15), 80))*'1_PANEL_CONTROL'!$C$117 -> 359.91 | J32: =CHOOSE('1_PANEL_CONTROL'!$C$4, 0, MIN(2+INT(J18/40), 20), MIN(5+INT(J18/15), 80))*'1_PANEL_CONTROL'!$C$117 -> 399.9 | K32: =CHOOSE('1_PANEL_CONTROL'!$C$4, 0, MIN(2+INT(K18/40), 20), MIN(5+INT(K18/15), 80))*'1_PANEL_CONTROL'!$C$117 -> 479.88 | ... CI32: =CHOOSE('1_PANEL_CONTROL'!$C$4, 0, MIN(2+INT(CI18/40), 20), MIN(5+INT(CI18/15), 80))*'1_PANEL_CONTROL'!$C$117 -> 799.8
A33: Afiliación E-commerce (Partners) | B33: EUR | C33: ActivePremium * RedirectionRate * TicketEcom * CPAMed | D33: =D18*'1_PANEL_CONTROL'!$C$129*'1_PANEL_CONTROL'!$C$130*CHOOSE('1_PANEL_CONTROL'!$C$4, '1_PANEL_CONTROL'!$C$131, '1_PANEL_CONTROL'!$C$132, '1_PANEL_CONTROL'!$C$133) -> 12.144 | E33: =E18*'1_PANEL_CONTROL'!$C$129*'1_PANEL_CONTROL'!$C$130*CHOOSE('1_PANEL_CONTROL'!$C$4, '1_PANEL_CONTROL'!$C$131, '1_PANEL_CONTROL'!$C$132, '1_PANEL_CONTROL'!$C$133) -> 24.552 | F33: =F18*'1_PANEL_CONTROL'!$C$129*'1_PANEL_CONTROL'!$C$130*CHOOSE('1_PANEL_CONTROL'!$C$4, '1_PANEL_CONTROL'!$C$131, '1_PANEL_CONTROL'!$C$132, '1_PANEL_CONTROL'!$C$133) -> 37.224 | G33: =G18*'1_PANEL_CONTROL'!$C$129*'1_PANEL_CONTROL'!$C$130*CHOOSE('1_PANEL_CONTROL'!$C$4, '1_PANEL_CONTROL'!$C$131, '1_PANEL_CONTROL'!$C$132, '1_PANEL_CONTROL'!$C$133) -> 50.16 | H33: =H18*'1_PANEL_CONTROL'!$C$129*'1_PANEL_CONTROL'!$C$130*CHOOSE('1_PANEL_CONTROL'!$C$4, '1_PANEL_CONTROL'!$C$131, '1_PANEL_CONTROL'!$C$132, '1_PANEL_CONTROL'!$C$133) -> 63.624 | I33: =I18*'1_PANEL_CONTROL'!$C$129*'1_PANEL_CONTROL'!$C$130*CHOOSE('1_PANEL_CONTROL'!$C$4, '1_PANEL_CONTROL'!$C$131, '1_PANEL_CONTROL'!$C$132, '1_PANEL_CONTROL'!$C$133) -> 77.616 | J33: =J18*'1_PANEL_CONTROL'!$C$129*'1_PANEL_CONTROL'!$C$130*CHOOSE('1_PANEL_CONTROL'!$C$4, '1_PANEL_CONTROL'!$C$131, '1_PANEL_CONTROL'!$C$132, '1_PANEL_CONTROL'!$C$133) -> 92.136 | K33: =K18*'1_PANEL_CONTROL'!$C$129*'1_PANEL_CONTROL'!$C$130*CHOOSE('1_PANEL_CONTROL'!$C$4, '1_PANEL_CONTROL'!$C$131, '1_PANEL_CONTROL'!$C$132, '1_PANEL_CONTROL'!$C$133) -> 107.184 | ... CI33: =CI18*'1_PANEL_CONTROL'!$C$129*'1_PANEL_CONTROL'!$C$130*CHOOSE('1_PANEL_CONTROL'!$C$4, '1_PANEL_CONTROL'!$C$131, '1_PANEL_CONTROL'!$C$132, '1_PANEL_CONTROL'!$C$133) -> 53713.44
A34: Publicidad In-App (Freemium) | B34: EUR | C34: FreeUsers * AdRevenuePerUser | D34: =MAX(0, D10-D18)*'1_PANEL_CONTROL'!$C$135 -> 356.58 | E34: =MAX(0, E10-E18)*'1_PANEL_CONTROL'!$C$135 -> 377.3088 | F34: =MAX(0, F10-F18)*'1_PANEL_CONTROL'!$C$135 -> 400.1927 | G34: =MAX(0, G10-G18)*'1_PANEL_CONTROL'!$C$135 -> 425.41852 | H34: =MAX(0, H10-H18)*'1_PANEL_CONTROL'!$C$135 -> 453.008 | I34: =MAX(0, I10-I18)*'1_PANEL_CONTROL'!$C$135 -> 483.17904 | J34: =MAX(0, J10-J18)*'1_PANEL_CONTROL'!$C$135 -> 516.16697 | K34: =MAX(0, K10-K18)*'1_PANEL_CONTROL'!$C$135 -> 552.22592 | ... CI34: =MAX(0, CI10-CI18)*'1_PANEL_CONTROL'!$C$135 -> 180296.38
A35: Patrocinios y Alianzas B2B | B35: EUR | C35: Sponsorship fixed calibration | D35: =CHOOSE('1_PANEL_CONTROL'!$C$4, 0, 4742.6233, 20000) -> 4742.6233 | E35: =CHOOSE('1_PANEL_CONTROL'!$C$4, 0, 4742.6233, 20000) -> 4742.6233 | F35: =CHOOSE('1_PANEL_CONTROL'!$C$4, 0, 4742.6233, 20000) -> 4742.6233 | G35: =CHOOSE('1_PANEL_CONTROL'!$C$4, 0, 4742.6233, 20000) -> 4742.6233 | H35: =CHOOSE('1_PANEL_CONTROL'!$C$4, 0, 4742.6233, 20000) -> 4742.6233 | I35: =CHOOSE('1_PANEL_CONTROL'!$C$4, 0, 4742.6233, 20000) -> 4742.6233 | J35: =CHOOSE('1_PANEL_CONTROL'!$C$4, 0, 4742.6233, 20000) -> 4742.6233 | K35: =CHOOSE('1_PANEL_CONTROL'!$C$4, 0, 4742.6233, 20000) -> 4742.6233 | ... CI35: =CHOOSE('1_PANEL_CONTROL'!$C$4, 0, 4742.6233, 20000) -> 4742.6233
A36: TOTAL B2B Y AFILIACIÓN | B36: EUR | C36: SUMA(B2B) | D36: =SUM(D31:D35) -> 6031.3173 | E36: =SUM(E31:E35) -> 6184.4441 | F36: =SUM(F31:F35) -> 6339.99 | G36: =SUM(G31:G35) -> 6498.1418 | H36: =SUM(H31:H35) -> 6699.1753 | I36: =SUM(I31:I35) -> 6863.3283 | J36: =SUM(J31:J35) -> 7030.8263 | K36: =SUM(K31:K35) -> 7321.9132 | ... CI36: =SUM(CI31:CI35) -> 241952.25
A37: TOTAL INGRESOS CONSOLIDADOS | B37: EUR | C37: SUMA(Líneas) | D37: =SUM(D26:D30)+D36 -> 12116.717 | E37: =SUM(E26:E30)+E36 -> 14168.269 | F37: =SUM(F26:F30)+F36 -> 16247.14 | G37: =SUM(G26:G30)+G36 -> 18539.142 | H37: =SUM(H26:H30)+H36 -> 20856.325 | I37: =SUM(I26:I30)+I36 -> 23300.803 | J37: =SUM(J26:J30)+J36 -> 25787.801 | K37: =SUM(K26:K30)+K36 -> 28478.813 | ... CI37: =SUM(CI26:CI30)+CI36 -> 9581065.6
B39: GUÍA DE FACTURACIÓN Y DETALLE DE LAS 10 FUENTES DE INGRESO
B40: 1. ESTRUCTURA MULTI-CANAL DE MONETIZACIÓN: - SaaS B2C (Premium Care): Facturación de la cuota recurrente mensual de 30 € (o anual con descuento). - Venta Hardware (Smart Collar): Ingreso de 89,50 € por cada nuevo cliente captado (pago único en día 1). - Insurtech (Seguros): Ingresos de corretaje del CUDI Shield (co-distribución con Barkibu). - VetHome (Veterinaria a Domicilio): Ticket de 75 € por visita presencial, con un 30% de retención para CUDI. - Marketplace B2B2C: Comisión (take-rate) del 15% sobre reservas de paseadores, guarderías y estéticas. 2. RETAIL Y SaaS B2B: - Monetiza también a los profesionales de la plataforma (Petme Negocios a 39,99 €/mes) y a clínicas asociadas.

Sheet 6_COSTES_COGS
A4: COSTE DE VENTAS DIRECTOS (COGS)
A5: Escenario Activo: | B5: =CHOOSE('1_PANEL_CONTROL'!$C$4, "🔴 1: NEGATIVO", "🟡 2: EQUILIBRIO", "🟢 3: POSITIVO") -> 🟡 2: EQUILIBRIO | D5: =CHOOSE('1_PANEL_CONTROL'!$C$4, "[NEGATIVO] COSTES DIRECTOS DE VENTAS. En el primer año, el procesamiento Stripe cuesta " & TEXT('6_COSTES_COGS'!O11, "#.##0,00 €") & " y las licencias de APIs de IA ascienden a " & TEXT('6_COSTES_COGS'!O12, "#.##0,00 €") & " en el mes 12.", "[EQUILIBRIO] COSTES DIRECTOS DE VENTAS. Servidores base e IoT suponen " & TEXT('6_COSTES_COGS'!O10, "#.##0,00 €") & " y la fabricación del Smart Collar totaliza " & TEXT('6_COSTES_COGS'!O13, "#.##0,00 €") & " en el mes 12 comercial.", "[POSITIVO] COSTES DIRECTOS DE VENTAS. El elevado volumen de venta de hardware eleva el coste directo total, sumando un acumulado de COGS en el año 1 de " & TEXT(SUM('6_COSTES_COGS'!$D$15:$O$15), "#.##0 €") & ". ") -> [EQUILIBRIO] COSTES DIRECTOS DE VENTAS. Servidores base e IoT suponen 402,00 € y la fabricación del Smart Collar totaliza 3.500,00 € en el mes 12 comercial.
A7: Coste Directo | B7: Unidad | C7: Regla de Cálculo | D7: Ene-26 | E7: Feb-26 | F7: Mar-26 | G7: Abr-26 | H7: May-26 | I7: Jun-26 | J7: Jul-26 | K7: Ago-26 | L7: Sep-26 | M7: Oct-26 | N7: Nov-26 | O7: Dic-26 | P7: Ene-27 | Q7: Feb-27 | R7: Mar-27 | S7: Abr-27 | T7: May-27 | U7: Jun-27 | V7: Jul-27 | W7: Ago-27 | X7: Sep-27 | Y7: Oct-27 | Z7: Nov-27 | AA7: Dic-27 | AB7: Ene-28 | AC7: Feb-28 | AD7: Mar-28 | AE7: Abr-28 | AF7: May-28 | AG7: Jun-28 | AH7: Jul-28 | AI7: Ago-28 | AJ7: Sep-28 | AK7: Oct-28 | AL7: Nov-28 | AM7: Dic-28 | AN7: Ene-29 | AO7: Feb-29 | AP7: Mar-29 | AQ7: Abr-29 | AR7: May-29 | AS7: Jun-29 | AT7: Jul-29 | AU7: Ago-29 | AV7: Sep-29 | AW7: Oct-29 | AX7: Nov-29 | AY7: Dic-29 | AZ7: Ene-30 | BA7: Feb-30 | BB7: Mar-30 | BC7: Abr-30 | BD7: May-30 | BE7: Jun-30 | BF7: Jul-30 | BG7: Ago-30 | BH7: Sep-30 | BI7: Oct-30 | BJ7: Nov-30 | BK7: Dic-30 | BL7: Ene-31 | BM7: Feb-31 | BN7: Mar-31 | BO7: Abr-31 | BP7: May-31 | BQ7: Jun-31 | BR7: Jul-31 | BS7: Ago-31 | BT7: Sep-31 | BU7: Oct-31 | BV7: Nov-31 | BW7: Dic-31 | BX7: Ene-32 | BY7: Feb-32 | BZ7: Mar-32 | CA7: Abr-32 | CB7: May-32 | CC7: Jun-32 | CD7: Jul-32 | CE7: Ago-32 | CF7: Sep-32 | CG7: Oct-32 | CH7: Nov-32 | CI7: Dic-32
A10: Servidores AWS (Base e IoT) | B10: EUR | C10: Premium_Active * AWS_Cost_User | D10: ='5_DETALLE_INGRESOS'!D18*'1_PANEL_CONTROL'!$C$26 -> 27.6 | E10: ='5_DETALLE_INGRESOS'!E18*'1_PANEL_CONTROL'!$C$26 -> 55.8 | F10: ='5_DETALLE_INGRESOS'!F18*'1_PANEL_CONTROL'!$C$26 -> 84.6 | G10: ='5_DETALLE_INGRESOS'!G18*'1_PANEL_CONTROL'!$C$26 -> 114 | H10: ='5_DETALLE_INGRESOS'!H18*'1_PANEL_CONTROL'!$C$26 -> 144.6 | I10: ='5_DETALLE_INGRESOS'!I18*'1_PANEL_CONTROL'!$C$26 -> 176.4 | J10: ='5_DETALLE_INGRESOS'!J18*'1_PANEL_CONTROL'!$C$26 -> 209.4 | K10: ='5_DETALLE_INGRESOS'!K18*'1_PANEL_CONTROL'!$C$26 -> 243.6 | ... CI10: ='5_DETALLE_INGRESOS'!CI18*'1_PANEL_CONTROL'!$C$26 -> 122076
A11: Procesamiento Stripe (Pasarela) | B11: EUR | C11: Total_Revenue * Stripe_fee_pct | D11: ='5_DETALLE_INGRESOS'!D37*'1_PANEL_CONTROL'!$C$27 -> 302.91793 | E11: ='5_DETALLE_INGRESOS'!E37*'1_PANEL_CONTROL'!$C$27 -> 354.20673 | F11: ='5_DETALLE_INGRESOS'!F37*'1_PANEL_CONTROL'!$C$27 -> 406.1785 | G11: ='5_DETALLE_INGRESOS'!G37*'1_PANEL_CONTROL'!$C$27 -> 463.47855 | H11: ='5_DETALLE_INGRESOS'!H37*'1_PANEL_CONTROL'!$C$27 -> 521.40813 | I11: ='5_DETALLE_INGRESOS'!I37*'1_PANEL_CONTROL'!$C$27 -> 582.52008 | J11: ='5_DETALLE_INGRESOS'!J37*'1_PANEL_CONTROL'!$C$27 -> 644.69503 | K11: ='5_DETALLE_INGRESOS'!K37*'1_PANEL_CONTROL'!$C$27 -> 711.97033 | ... CI11: ='5_DETALLE_INGRESOS'!CI37*'1_PANEL_CONTROL'!$C$27 -> 239526.64
A12: Licencias APIs IA (Gemini+Claude) | B12: EUR | C12: Fixed_Gemini + Premium_Active * Claude_Cost | D12: ='1_PANEL_CONTROL'!$C$28+('5_DETALLE_INGRESOS'!D18*'1_PANEL_CONTROL'!$C$29) -> 117.02 | E12: ='1_PANEL_CONTROL'!$C$28+('5_DETALLE_INGRESOS'!E18*'1_PANEL_CONTROL'!$C$29) -> 134.41 | F12: ='1_PANEL_CONTROL'!$C$28+('5_DETALLE_INGRESOS'!F18*'1_PANEL_CONTROL'!$C$29) -> 152.17 | G12: ='1_PANEL_CONTROL'!$C$28+('5_DETALLE_INGRESOS'!G18*'1_PANEL_CONTROL'!$C$29) -> 170.3 | H12: ='1_PANEL_CONTROL'!$C$28+('5_DETALLE_INGRESOS'!H18*'1_PANEL_CONTROL'!$C$29) -> 189.17 | I12: ='1_PANEL_CONTROL'!$C$28+('5_DETALLE_INGRESOS'!I18*'1_PANEL_CONTROL'!$C$29) -> 208.78 | J12: ='1_PANEL_CONTROL'!$C$28+('5_DETALLE_INGRESOS'!J18*'1_PANEL_CONTROL'!$C$29) -> 229.13 | K12: ='1_PANEL_CONTROL'!$C$28+('5_DETALLE_INGRESOS'!K18*'1_PANEL_CONTROL'!$C$29) -> 250.22 | ... CI12: ='1_PANEL_CONTROL'!$C$28+('5_DETALLE_INGRESOS'!CI18*'1_PANEL_CONTROL'!$C$29) -> 75380.2
A13: Fabricación Dispositivo Smart Collar | B13: EUR | C13: CollarsSold * cost_fabrication | D13: ='5_DETALLE_INGRESOS'!D20*'1_PANEL_CONTROL'!$C$24 -> 1610 | E13: ='5_DETALLE_INGRESOS'!E20*'1_PANEL_CONTROL'!$C$24 -> 1715 | F13: ='5_DETALLE_INGRESOS'!F20*'1_PANEL_CONTROL'!$C$24 -> 1820 | G13: ='5_DETALLE_INGRESOS'!G20*'1_PANEL_CONTROL'!$C$24 -> 1960 | H13: ='5_DETALLE_INGRESOS'!H20*'1_PANEL_CONTROL'!$C$24 -> 2100 | I13: ='5_DETALLE_INGRESOS'!I20*'1_PANEL_CONTROL'!$C$24 -> 2275 | J13: ='5_DETALLE_INGRESOS'!J20*'1_PANEL_CONTROL'!$C$24 -> 2415 | K13: ='5_DETALLE_INGRESOS'!K20*'1_PANEL_CONTROL'!$C$24 -> 2590 | ... CI13: ='5_DETALLE_INGRESOS'!CI20*'1_PANEL_CONTROL'!$C$24 -> 843745
A14: Mensajería y Entrega Express | B14: EUR | C14: CollarsSold * delivery_cost | D14: ='5_DETALLE_INGRESOS'!D20*'1_PANEL_CONTROL'!$C$25 -> 299 | E14: ='5_DETALLE_INGRESOS'!E20*'1_PANEL_CONTROL'!$C$25 -> 318.5 | F14: ='5_DETALLE_INGRESOS'!F20*'1_PANEL_CONTROL'!$C$25 -> 338 | G14: ='5_DETALLE_INGRESOS'!G20*'1_PANEL_CONTROL'!$C$25 -> 364 | H14: ='5_DETALLE_INGRESOS'!H20*'1_PANEL_CONTROL'!$C$25 -> 390 | I14: ='5_DETALLE_INGRESOS'!I20*'1_PANEL_CONTROL'!$C$25 -> 422.5 | J14: ='5_DETALLE_INGRESOS'!J20*'1_PANEL_CONTROL'!$C$25 -> 448.5 | K14: ='5_DETALLE_INGRESOS'!K20*'1_PANEL_CONTROL'!$C$25 -> 481 | ... CI14: ='5_DETALLE_INGRESOS'!CI20*'1_PANEL_CONTROL'!$C$25 -> 156695.5
A15: TOTAL COSTES DE VENTAS (COGS) | B15: EUR | C15: SUMA(Líneas) | D15: =SUM(D10:D14) -> 2356.5379 | E15: =SUM(E10:E14) -> 2577.9167 | F15: =SUM(F10:F14) -> 2800.9485 | G15: =SUM(G10:G14) -> 3071.7785 | H15: =SUM(H10:H14) -> 3345.1781 | I15: =SUM(I10:I14) -> 3665.2001 | J15: =SUM(J10:J14) -> 3946.725 | K15: =SUM(K10:K14) -> 4276.7903 | ... CI15: =SUM(CI10:CI14) -> 1437423.3
B17: GUÍA DE COSTES DIRECTOS DE VENTAS (COGS)
B18: 1. DESGLOSE DE COSTES VARIABLES ASOCIADOS A LA ACTIVIDAD: - Servidores AWS: Coste del alojamiento cloud de la plataforma, bases de datos y APIs en tiempo real. - Stripe: Comisión de pasarela del 2.50% aplicada sobre todos los cobros B2C realizados en la app. - APIs de IA (Claude & Gemini): Coste de llamadas de procesamiento para el Gemelo Digital y asistente de triaje. - Coste Collar GPS: Establecido en **35,00 €** de fabricación (Landed Cost de 41,50 € con envío urgente nacional a 6,50 €). 2. MARGEN BRUTO HARDWARE REALISTA: - El margen bruto del hardware se sitúa en **53.63%**, eliminando pérdidas y protegiendo el flujo de caja operativo.

Sheet 7_EQUIPO_RRHH
A2: PLANIFICACIÓN DE TALENTO HUMANO Y GASTOS DE PERSONAL | C2: Escenario Activo: | D2: =CHOOSE('1_PANEL_CONTROL'!$C$4, "🔴 1: NEGATIVO", "🟡 2: EQUILIBRIO", "🟢 3: POSITIVO") -> 🟡 2: EQUILIBRIO
B3: =CHOOSE('1_PANEL_CONTROL'!$C$4, "[NEGATIVO] TALENTO HUMANO Y PERSONAL. Salarios de supervivencia (4 fundadores a " & TEXT('7_EQUIPO_RRHH'!D10, "#.##0 €") & " bruto/mes) y cotización general de autónomos (RETA) de 448,69 €/mes desde el inicio.", "[EQUILIBRIO] TALENTO HUMANO Y PERSONAL. Ahorro fiscal con cuota RETA reducida (tarifa plana de 88,56 €) para los fundadores en Año 1, incorporando 2 empleados en régimen general en Año 2.", "[POSITIVO] TALENTO HUMANO Y PERSONAL. Mismo equipo fundador inicial plano en Año 1 y contratación selectiva en Año 2, dejando el resto de vacantes inactivas para optimizar costes fijos.") -> [EQUILIBRIO] TALENTO HUMANO Y PERSONAL. Ahorro fiscal con cuota RETA reducida (tarifa plana de 88,56 €) para los fundadores en Año 1, incorporando 2 empleados en régimen general en Año 2.
A4: PARÁMETROS REGULABLES DE LEY (SEGURIDAD SOCIAL Y PAGAS)
A5: Seguridad Social a Cargo de la Empresa (%): | B5: ='1_PANEL_CONTROL'!$C$33 -> 0.321 | C5: Base de Cotización Máxima Mensual (Tope): | D5: ='1_PANEL_CONTROL'!$C$35 -> 4720.5
A6: Seguridad Social a Cargo del Empleado (%): | B6: ='1_PANEL_CONTROL'!$C$34 -> 0.0647 | C6: Base de Cotización Mínima Mensual (SMI): | D6: ='1_PANEL_CONTROL'!$C$36 -> 1300
D7: Ene-26 | E7: Feb-26 | F7: Mar-26 | G7: Abr-26 | H7: May-26 | I7: Jun-26 | J7: Jul-26 | K7: Ago-26 | L7: Sep-26 | M7: Oct-26 | N7: Nov-26 | O7: Dic-26 | P7: Ene-27 | Q7: Feb-27 | R7: Mar-27 | S7: Abr-27 | T7: May-27 | U7: Jun-27 | V7: Jul-27 | W7: Ago-27 | X7: Sep-27 | Y7: Oct-27 | Z7: Nov-27 | AA7: Dic-27 | AB7: Ene-28 | AC7: Feb-28 | AD7: Mar-28 | AE7: Abr-28 | AF7: May-28 | AG7: Jun-28 | AH7: Jul-28 | AI7: Ago-28 | AJ7: Sep-28 | AK7: Oct-28 | AL7: Nov-28 | AM7: Dic-28 | AN7: Ene-29 | AO7: Feb-29 | AP7: Mar-29 | AQ7: Abr-29 | AR7: May-29 | AS7: Jun-29 | AT7: Jul-29 | AU7: Ago-29 | AV7: Sep-29 | AW7: Oct-29 | AX7: Nov-29 | AY7: Dic-29 | AZ7: Ene-30 | BA7: Feb-30 | BB7: Mar-30 | BC7: Abr-30 | BD7: May-30 | BE7: Jun-30 | BF7: Jul-30 | BG7: Ago-30 | BH7: Sep-30 | BI7: Oct-30 | BJ7: Nov-30 | BK7: Dic-30 | BL7: Ene-31 | BM7: Feb-31 | BN7: Mar-31 | BO7: Abr-31 | BP7: May-31 | BQ7: Jun-31 | BR7: Jul-31 | BS7: Ago-31 | BT7: Sep-31 | BU7: Oct-31 | BV7: Nov-31 | BW7: Dic-31 | BX7: Ene-32 | BY7: Feb-32 | BZ7: Mar-32 | CA7: Abr-32 | CB7: May-32 | CC7: Jun-32 | CD7: Jul-32 | CE7: Ago-32 | CF7: Sep-32 | CG7: Oct-32 | CH7: Nov-32 | CI7: Dic-32
A8: Esquema de Pagas (12 o 14): | C8: ='1_PANEL_CONTROL'!$C$32 -> 12 | D8: 1 | E8: 2 | F8: 3 | G8: 4 | H8: 5 | I8: 6 | J8: 7 | K8: 8 | L8: 9 | M8: 10 | N8: 11 | O8: 12 | P8: 13 | Q8: 14 | R8: 15 | S8: 16 | T8: 17 | U8: 18 | V8: 19 | W8: 20 | X8: 21 | Y8: 22 | Z8: 23 | AA8: 24 | AB8: 25 | AC8: 26 | AD8: 27 | AE8: 28 | AF8: 29 | AG8: 30 | AH8: 31 | AI8: 32 | AJ8: 33 | AK8: 34 | AL8: 35 | AM8: 36 | AN8: 37 | AO8: 38 | AP8: 39 | AQ8: 40 | AR8: 41 | AS8: 42 | AT8: 43 | AU8: 44 | AV8: 45 | AW8: 46 | AX8: 47 | AY8: 48 | AZ8: 49 | BA8: 50 | BB8: 51 | BC8: 52 | BD8: 53 | BE8: 54 | BF8: 55 | BG8: 56 | BH8: 57 | BI8: 58 | BJ8: 59 | BK8: 60 | BL8: 61 | BM8: 62 | BN8: 63 | BO8: 64 | BP8: 65 | BQ8: 66 | BR8: 67 | BS8: 68 | BT8: 69 | BU8: 70 | BV8: 71 | BW8: 72 | BX8: 73 | BY8: 74 | BZ8: 75 | CA8: 76 | CB8: 77 | CC8: 78 | CD8: 79 | CE8: 80 | CF8: 81 | CG8: 82 | CH8: 83 | CI8: 84
A10: Salario Ordinario Mensual | B10: EUR | C10: ='1_PANEL_CONTROL'!$C$39 -> 18000 | D10: =IF(D$8>='1_PANEL_CONTROL'!$D$39, IF(D$8<=12, 18000, IF(D$8<=24, 36000, 48000))/'1_PANEL_CONTROL'!$C$32, 0) -> 1500 | E10: =IF(E$8>='1_PANEL_CONTROL'!$D$39, IF(E$8<=12, 18000, IF(E$8<=24, 36000, 48000))/'1_PANEL_CONTROL'!$C$32, 0) -> 1500 | F10: =IF(F$8>='1_PANEL_CONTROL'!$D$39, IF(F$8<=12, 18000, IF(F$8<=24, 36000, 48000))/'1_PANEL_CONTROL'!$C$32, 0) -> 1500 | G10: =IF(G$8>='1_PANEL_CONTROL'!$D$39, IF(G$8<=12, 18000, IF(G$8<=24, 36000, 48000))/'1_PANEL_CONTROL'!$C$32, 0) -> 1500 | H10: =IF(H$8>='1_PANEL_CONTROL'!$D$39, IF(H$8<=12, 18000, IF(H$8<=24, 36000, 48000))/'1_PANEL_CONTROL'!$C$32, 0) -> 1500 | I10: =IF(I$8>='1_PANEL_CONTROL'!$D$39, IF(I$8<=12, 18000, IF(I$8<=24, 36000, 48000))/'1_PANEL_CONTROL'!$C$32, 0) -> 1500 | J10: =IF(J$8>='1_PANEL_CONTROL'!$D$39, IF(J$8<=12, 18000, IF(J$8<=24, 36000, 48000))/'1_PANEL_CONTROL'!$C$32, 0) -> 1500 | K10: =IF(K$8>='1_PANEL_CONTROL'!$D$39, IF(K$8<=12, 18000, IF(K$8<=24, 36000, 48000))/'1_PANEL_CONTROL'!$C$32, 0) -> 1500 | ... CI10: =IF(CI$8>='1_PANEL_CONTROL'!$D$39, IF(CI$8<=12, 18000, IF(CI$8<=24, 36000, 48000))/'1_PANEL_CONTROL'!$C$32, 0) -> 4000
A11: Pagas Extraordinarias | B11: EUR | D11: =IF(D$8>='1_PANEL_CONTROL'!$D$39, IF('1_PANEL_CONTROL'!$C$32=14, IF(OR(MOD(D$8,12)=6, MOD(D$8,12)=0), IF(D$8<=12, 18000, IF(D$8<=24, 36000, 48000))/14, 0), 0), 0) -> 0 | E11: =IF(E$8>='1_PANEL_CONTROL'!$D$39, IF('1_PANEL_CONTROL'!$C$32=14, IF(OR(MOD(E$8,12)=6, MOD(E$8,12)=0), IF(E$8<=12, 18000, IF(E$8<=24, 36000, 48000))/14, 0), 0), 0) -> 0 | F11: =IF(F$8>='1_PANEL_CONTROL'!$D$39, IF('1_PANEL_CONTROL'!$C$32=14, IF(OR(MOD(F$8,12)=6, MOD(F$8,12)=0), IF(F$8<=12, 18000, IF(F$8<=24, 36000, 48000))/14, 0), 0), 0) -> 0 | G11: =IF(G$8>='1_PANEL_CONTROL'!$D$39, IF('1_PANEL_CONTROL'!$C$32=14, IF(OR(MOD(G$8,12)=6, MOD(G$8,12)=0), IF(G$8<=12, 18000, IF(G$8<=24, 36000, 48000))/14, 0), 0), 0) -> 0 | H11: =IF(H$8>='1_PANEL_CONTROL'!$D$39, IF('1_PANEL_CONTROL'!$C$32=14, IF(OR(MOD(H$8,12)=6, MOD(H$8,12)=0), IF(H$8<=12, 18000, IF(H$8<=24, 36000, 48000))/14, 0), 0), 0) -> 0 | I11: =IF(I$8>='1_PANEL_CONTROL'!$D$39, IF('1_PANEL_CONTROL'!$C$32=14, IF(OR(MOD(I$8,12)=6, MOD(I$8,12)=0), IF(I$8<=12, 18000, IF(I$8<=24, 36000, 48000))/14, 0), 0), 0) -> 0 | J11: =IF(J$8>='1_PANEL_CONTROL'!$D$39, IF('1_PANEL_CONTROL'!$C$32=14, IF(OR(MOD(J$8,12)=6, MOD(J$8,12)=0), IF(J$8<=12, 18000, IF(J$8<=24, 36000, 48000))/14, 0), 0), 0) -> 0 | K11: =IF(K$8>='1_PANEL_CONTROL'!$D$39, IF('1_PANEL_CONTROL'!$C$32=14, IF(OR(MOD(K$8,12)=6, MOD(K$8,12)=0), IF(K$8<=12, 18000, IF(K$8<=24, 36000, 48000))/14, 0), 0), 0) -> 0 | ... CI11: =IF(CI$8>='1_PANEL_CONTROL'!$D$39, IF('1_PANEL_CONTROL'!$C$32=14, IF(OR(MOD(CI$8,12)=6, MOD(CI$8,12)=0), IF(CI$8<=12, 18000, IF(CI$8<=24, 36000, 48000))/14, 0), 0), 0) -> 0
A12: Sueldo Bruto Devengado | B12: EUR | D12: =D10+D11 -> 1500 | E12: =E10+E11 -> 1500 | F12: =F10+F11 -> 1500 | G12: =G10+G11 -> 1500 | H12: =H10+H11 -> 1500 | I12: =I10+I11 -> 1500 | J12: =J10+J11 -> 1500 | K12: =K10+K11 -> 1500 | ... CI12: =CI10+CI11 -> 4000
A13: Base de Cotización SS (BCCC) | B13: EUR | D13: =IF(D$8>='1_PANEL_CONTROL'!$D$39, IF(D$8<=12, 18000, IF(D$8<=24, 36000, 48000))/12, 0) -> 1500 | E13: =IF(E$8>='1_PANEL_CONTROL'!$D$39, IF(E$8<=12, 18000, IF(E$8<=24, 36000, 48000))/12, 0) -> 1500 | F13: =IF(F$8>='1_PANEL_CONTROL'!$D$39, IF(F$8<=12, 18000, IF(F$8<=24, 36000, 48000))/12, 0) -> 1500 | G13: =IF(G$8>='1_PANEL_CONTROL'!$D$39, IF(G$8<=12, 18000, IF(G$8<=24, 36000, 48000))/12, 0) -> 1500 | H13: =IF(H$8>='1_PANEL_CONTROL'!$D$39, IF(H$8<=12, 18000, IF(H$8<=24, 36000, 48000))/12, 0) -> 1500 | I13: =IF(I$8>='1_PANEL_CONTROL'!$D$39, IF(I$8<=12, 18000, IF(I$8<=24, 36000, 48000))/12, 0) -> 1500 | J13: =IF(J$8>='1_PANEL_CONTROL'!$D$39, IF(J$8<=12, 18000, IF(J$8<=24, 36000, 48000))/12, 0) -> 1500 | K13: =IF(K$8>='1_PANEL_CONTROL'!$D$39, IF(K$8<=12, 18000, IF(K$8<=24, 36000, 48000))/12, 0) -> 1500 | ... CI13: =IF(CI$8>='1_PANEL_CONTROL'!$D$39, IF(CI$8<=12, 18000, IF(CI$8<=24, 36000, 48000))/12, 0) -> 4000
A14: Base Cotización Capped | B14: EUR | D14: =IF(D$8>='1_PANEL_CONTROL'!$D$39, MIN(MAX(D13, $D$6), $D$5), 0) -> 1500 | E14: =IF(E$8>='1_PANEL_CONTROL'!$D$39, MIN(MAX(E13, $D$6), $D$5), 0) -> 1500 | F14: =IF(F$8>='1_PANEL_CONTROL'!$D$39, MIN(MAX(F13, $D$6), $D$5), 0) -> 1500 | G14: =IF(G$8>='1_PANEL_CONTROL'!$D$39, MIN(MAX(G13, $D$6), $D$5), 0) -> 1500 | H14: =IF(H$8>='1_PANEL_CONTROL'!$D$39, MIN(MAX(H13, $D$6), $D$5), 0) -> 1500 | I14: =IF(I$8>='1_PANEL_CONTROL'!$D$39, MIN(MAX(I13, $D$6), $D$5), 0) -> 1500 | J14: =IF(J$8>='1_PANEL_CONTROL'!$D$39, MIN(MAX(J13, $D$6), $D$5), 0) -> 1500 | K14: =IF(K$8>='1_PANEL_CONTROL'!$D$39, MIN(MAX(K13, $D$6), $D$5), 0) -> 1500 | ... CI14: =IF(CI$8>='1_PANEL_CONTROL'!$D$39, MIN(MAX(CI13, $D$6), $D$5), 0) -> 4000
A15: SS Empresa | B15: EUR | D15: =IF(D$8>='1_PANEL_CONTROL'!$D$39, '1_PANEL_CONTROL'!$F$33, 0) -> 448.69 | E15: =IF(E$8>='1_PANEL_CONTROL'!$D$39, '1_PANEL_CONTROL'!$F$33, 0) -> 448.69 | F15: =IF(F$8>='1_PANEL_CONTROL'!$D$39, '1_PANEL_CONTROL'!$F$33, 0) -> 448.69 | G15: =IF(G$8>='1_PANEL_CONTROL'!$D$39, '1_PANEL_CONTROL'!$F$33, 0) -> 448.69 | H15: =IF(H$8>='1_PANEL_CONTROL'!$D$39, '1_PANEL_CONTROL'!$F$33, 0) -> 448.69 | I15: =IF(I$8>='1_PANEL_CONTROL'!$D$39, '1_PANEL_CONTROL'!$F$33, 0) -> 448.69 | J15: =IF(J$8>='1_PANEL_CONTROL'!$D$39, '1_PANEL_CONTROL'!$F$33, 0) -> 448.69 | K15: =IF(K$8>='1_PANEL_CONTROL'!$D$39, '1_PANEL_CONTROL'!$F$33, 0) -> 448.69 | ... CI15: =IF(CI$8>='1_PANEL_CONTROL'!$D$39, '1_PANEL_CONTROL'!$F$33, 0) -> 448.69
A16: SS Empleado | B16: EUR | D16: 0 | E16: 0 | F16: 0 | G16: 0 | H16: 0 | I16: 0 | J16: 0 | K16: 0 | L16: 0 | M16: 0 | N16: 0 | O16: 0 | P16: 0 | Q16: 0 | R16: 0 | S16: 0 | T16: 0 | U16: 0 | V16: 0 | W16: 0 | X16: 0 | Y16: 0 | Z16: 0 | AA16: 0 | AB16: 0 | AC16: 0 | AD16: 0 | AE16: 0 | AF16: 0 | AG16: 0 | AH16: 0 | AI16: 0 | AJ16: 0 | AK16: 0 | AL16: 0 | AM16: 0 | AN16: 0 | AO16: 0 | AP16: 0 | AQ16: 0 | AR16: 0 | AS16: 0 | AT16: 0 | AU16: 0 | AV16: 0 | AW16: 0 | AX16: 0 | AY16: 0 | AZ16: 0 | BA16: 0 | BB16: 0 | BC16: 0 | BD16: 0 | BE16: 0 | BF16: 0 | BG16: 0 | BH16: 0 | BI16: 0 | BJ16: 0 | BK16: 0 | BL16: 0 | BM16: 0 | BN16: 0 | BO16: 0 | BP16: 0 | BQ16: 0 | BR16: 0 | BS16: 0 | BT16: 0 | BU16: 0 | BV16: 0 | BW16: 0 | BX16: 0 | BY16: 0 | BZ16: 0 | CA16: 0 | CB16: 0 | CC16: 0 | CD16: 0 | CE16: 0 | CF16: 0 | CG16: 0 | CH16: 0 | CI16: 0
A17: Retención IRPF | B17: EUR | D17: =D12*'1_PANEL_CONTROL'!$E$39 -> 225 | E17: =E12*'1_PANEL_CONTROL'!$E$39 -> 225 | F17: =F12*'1_PANEL_CONTROL'!$E$39 -> 225 | G17: =G12*'1_PANEL_CONTROL'!$E$39 -> 225 | H17: =H12*'1_PANEL_CONTROL'!$E$39 -> 225 | I17: =I12*'1_PANEL_CONTROL'!$E$39 -> 225 | J17: =J12*'1_PANEL_CONTROL'!$E$39 -> 225 | K17: =K12*'1_PANEL_CONTROL'!$E$39 -> 225 | ... CI17: =CI12*'1_PANEL_CONTROL'!$E$39 -> 600
A18: Salario Neto Mensual | B18: EUR | D18: =D12-D16-D17 -> 1275 | E18: =E12-E16-E17 -> 1275 | F18: =F12-F16-F17 -> 1275 | G18: =G12-G16-G17 -> 1275 | H18: =H12-H16-H17 -> 1275 | I18: =I12-I16-I17 -> 1275 | J18: =J12-J16-J17 -> 1275 | K18: =K12-K16-K17 -> 1275 | ... CI18: =CI12-CI16-CI17 -> 3400
A19: Coste Total Empresa (OPEX) | B19: EUR | D19: =D12+D15 -> 1948.69 | E19: =E12+E15 -> 1948.69 | F19: =F12+F15 -> 1948.69 | G19: =G12+G15 -> 1948.69 | H19: =H12+H15 -> 1948.69 | I19: =I12+I15 -> 1948.69 | J19: =J12+J15 -> 1948.69 | K19: =K12+K15 -> 1948.69 | ... CI19: =CI12+CI15 -> 4448.69
A21: Salario Ordinario Mensual | B21: EUR | C21: ='1_PANEL_CONTROL'!$C$40 -> 18000 | D21: =IF(D$8>='1_PANEL_CONTROL'!$D$40, IF(D$8<=12, 18000, IF(D$8<=24, 30000, 40000))/'1_PANEL_CONTROL'!$C$32, 0) -> 1500 | E21: =IF(E$8>='1_PANEL_CONTROL'!$D$40, IF(E$8<=12, 18000, IF(E$8<=24, 30000, 40000))/'1_PANEL_CONTROL'!$C$32, 0) -> 1500 | F21: =IF(F$8>='1_PANEL_CONTROL'!$D$40, IF(F$8<=12, 18000, IF(F$8<=24, 30000, 40000))/'1_PANEL_CONTROL'!$C$32, 0) -> 1500 | G21: =IF(G$8>='1_PANEL_CONTROL'!$D$40, IF(G$8<=12, 18000, IF(G$8<=24, 30000, 40000))/'1_PANEL_CONTROL'!$C$32, 0) -> 1500 | H21: =IF(H$8>='1_PANEL_CONTROL'!$D$40, IF(H$8<=12, 18000, IF(H$8<=24, 30000, 40000))/'1_PANEL_CONTROL'!$C$32, 0) -> 1500 | I21: =IF(I$8>='1_PANEL_CONTROL'!$D$40, IF(I$8<=12, 18000, IF(I$8<=24, 30000, 40000))/'1_PANEL_CONTROL'!$C$32, 0) -> 1500 | J21: =IF(J$8>='1_PANEL_CONTROL'!$D$40, IF(J$8<=12, 18000, IF(J$8<=24, 30000, 40000))/'1_PANEL_CONTROL'!$C$32, 0) -> 1500 | K21: =IF(K$8>='1_PANEL_CONTROL'!$D$40, IF(K$8<=12, 18000, IF(K$8<=24, 30000, 40000))/'1_PANEL_CONTROL'!$C$32, 0) -> 1500 | ... CI21: =IF(CI$8>='1_PANEL_CONTROL'!$D$40, IF(CI$8<=12, 18000, IF(CI$8<=24, 30000, 40000))/'1_PANEL_CONTROL'!$C$32, 0) -> 3333.3333
A22: Pagas Extraordinarias | B22: EUR | D22: =IF(D$8>='1_PANEL_CONTROL'!$D$40, IF('1_PANEL_CONTROL'!$C$32=14, IF(OR(MOD(D$8,12)=6, MOD(D$8,12)=0), IF(D$8<=12, 18000, IF(D$8<=24, 30000, 40000))/14, 0), 0), 0) -> 0 | E22: =IF(E$8>='1_PANEL_CONTROL'!$D$40, IF('1_PANEL_CONTROL'!$C$32=14, IF(OR(MOD(E$8,12)=6, MOD(E$8,12)=0), IF(E$8<=12, 18000, IF(E$8<=24, 30000, 40000))/14, 0), 0), 0) -> 0 | F22: =IF(F$8>='1_PANEL_CONTROL'!$D$40, IF('1_PANEL_CONTROL'!$C$32=14, IF(OR(MOD(F$8,12)=6, MOD(F$8,12)=0), IF(F$8<=12, 18000, IF(F$8<=24, 30000, 40000))/14, 0), 0), 0) -> 0 | G22: =IF(G$8>='1_PANEL_CONTROL'!$D$40, IF('1_PANEL_CONTROL'!$C$32=14, IF(OR(MOD(G$8,12)=6, MOD(G$8,12)=0), IF(G$8<=12, 18000, IF(G$8<=24, 30000, 40000))/14, 0), 0), 0) -> 0 | H22: =IF(H$8>='1_PANEL_CONTROL'!$D$40, IF('1_PANEL_CONTROL'!$C$32=14, IF(OR(MOD(H$8,12)=6, MOD(H$8,12)=0), IF(H$8<=12, 18000, IF(H$8<=24, 30000, 40000))/14, 0), 0), 0) -> 0 | I22: =IF(I$8>='1_PANEL_CONTROL'!$D$40, IF('1_PANEL_CONTROL'!$C$32=14, IF(OR(MOD(I$8,12)=6, MOD(I$8,12)=0), IF(I$8<=12, 18000, IF(I$8<=24, 30000, 40000))/14, 0), 0), 0) -> 0 | J22: =IF(J$8>='1_PANEL_CONTROL'!$D$40, IF('1_PANEL_CONTROL'!$C$32=14, IF(OR(MOD(J$8,12)=6, MOD(J$8,12)=0), IF(J$8<=12, 18000, IF(J$8<=24, 30000, 40000))/14, 0), 0), 0) -> 0 | K22: =IF(K$8>='1_PANEL_CONTROL'!$D$40, IF('1_PANEL_CONTROL'!$C$32=14, IF(OR(MOD(K$8,12)=6, MOD(K$8,12)=0), IF(K$8<=12, 18000, IF(K$8<=24, 30000, 40000))/14, 0), 0), 0) -> 0 | ... CI22: =IF(CI$8>='1_PANEL_CONTROL'!$D$40, IF('1_PANEL_CONTROL'!$C$32=14, IF(OR(MOD(CI$8,12)=6, MOD(CI$8,12)=0), IF(CI$8<=12, 18000, IF(CI$8<=24, 30000, 40000))/14, 0), 0), 0) -> 0
A23: Sueldo Bruto Devengado | B23: EUR | D23: =D21+D22 -> 1500 | E23: =E21+E22 -> 1500 | F23: =F21+F22 -> 1500 | G23: =G21+G22 -> 1500 | H23: =H21+H22 -> 1500 | I23: =I21+I22 -> 1500 | J23: =J21+J22 -> 1500 | K23: =K21+K22 -> 1500 | ... CI23: =CI21+CI22 -> 3333.3333
A24: Base de Cotización SS (BCCC) | B24: EUR | D24: =IF(D$8>='1_PANEL_CONTROL'!$D$40, IF(D$8<=12, 18000, IF(D$8<=24, 30000, 40000))/12, 0) -> 1500 | E24: =IF(E$8>='1_PANEL_CONTROL'!$D$40, IF(E$8<=12, 18000, IF(E$8<=24, 30000, 40000))/12, 0) -> 1500 | F24: =IF(F$8>='1_PANEL_CONTROL'!$D$40, IF(F$8<=12, 18000, IF(F$8<=24, 30000, 40000))/12, 0) -> 1500 | G24: =IF(G$8>='1_PANEL_CONTROL'!$D$40, IF(G$8<=12, 18000, IF(G$8<=24, 30000, 40000))/12, 0) -> 1500 | H24: =IF(H$8>='1_PANEL_CONTROL'!$D$40, IF(H$8<=12, 18000, IF(H$8<=24, 30000, 40000))/12, 0) -> 1500 | I24: =IF(I$8>='1_PANEL_CONTROL'!$D$40, IF(I$8<=12, 18000, IF(I$8<=24, 30000, 40000))/12, 0) -> 1500 | J24: =IF(J$8>='1_PANEL_CONTROL'!$D$40, IF(J$8<=12, 18000, IF(J$8<=24, 30000, 40000))/12, 0) -> 1500 | K24: =IF(K$8>='1_PANEL_CONTROL'!$D$40, IF(K$8<=12, 18000, IF(K$8<=24, 30000, 40000))/12, 0) -> 1500 | ... CI24: =IF(CI$8>='1_PANEL_CONTROL'!$D$40, IF(CI$8<=12, 18000, IF(CI$8<=24, 30000, 40000))/12, 0) -> 3333.3333
A25: Base Cotización Capped | B25: EUR | D25: =IF(D$8>='1_PANEL_CONTROL'!$D$40, MIN(MAX(D24, $D$6), $D$5), 0) -> 1500 | E25: =IF(E$8>='1_PANEL_CONTROL'!$D$40, MIN(MAX(E24, $D$6), $D$5), 0) -> 1500 | F25: =IF(F$8>='1_PANEL_CONTROL'!$D$40, MIN(MAX(F24, $D$6), $D$5), 0) -> 1500 | G25: =IF(G$8>='1_PANEL_CONTROL'!$D$40, MIN(MAX(G24, $D$6), $D$5), 0) -> 1500 | H25: =IF(H$8>='1_PANEL_CONTROL'!$D$40, MIN(MAX(H24, $D$6), $D$5), 0) -> 1500 | I25: =IF(I$8>='1_PANEL_CONTROL'!$D$40, MIN(MAX(I24, $D$6), $D$5), 0) -> 1500 | J25: =IF(J$8>='1_PANEL_CONTROL'!$D$40, MIN(MAX(J24, $D$6), $D$5), 0) -> 1500 | K25: =IF(K$8>='1_PANEL_CONTROL'!$D$40, MIN(MAX(K24, $D$6), $D$5), 0) -> 1500 | ... CI25: =IF(CI$8>='1_PANEL_CONTROL'!$D$40, MIN(MAX(CI24, $D$6), $D$5), 0) -> 3333.3333
A26: SS Empresa | B26: EUR | D26: =IF(D$8>='1_PANEL_CONTROL'!$D$40, '1_PANEL_CONTROL'!$F$33, 0) -> 448.69 | E26: =IF(E$8>='1_PANEL_CONTROL'!$D$40, '1_PANEL_CONTROL'!$F$33, 0) -> 448.69 | F26: =IF(F$8>='1_PANEL_CONTROL'!$D$40, '1_PANEL_CONTROL'!$F$33, 0) -> 448.69 | G26: =IF(G$8>='1_PANEL_CONTROL'!$D$40, '1_PANEL_CONTROL'!$F$33, 0) -> 448.69 | H26: =IF(H$8>='1_PANEL_CONTROL'!$D$40, '1_PANEL_CONTROL'!$F$33, 0) -> 448.69 | I26: =IF(I$8>='1_PANEL_CONTROL'!$D$40, '1_PANEL_CONTROL'!$F$33, 0) -> 448.69 | J26: =IF(J$8>='1_PANEL_CONTROL'!$D$40, '1_PANEL_CONTROL'!$F$33, 0) -> 448.69 | K26: =IF(K$8>='1_PANEL_CONTROL'!$D$40, '1_PANEL_CONTROL'!$F$33, 0) -> 448.69 | ... CI26: =IF(CI$8>='1_PANEL_CONTROL'!$D$40, '1_PANEL_CONTROL'!$F$33, 0) -> 448.69
A27: SS Empleado | B27: EUR | D27: 0 | E27: 0 | F27: 0 | G27: 0 | H27: 0 | I27: 0 | J27: 0 | K27: 0 | L27: 0 | M27: 0 | N27: 0 | O27: 0 | P27: 0 | Q27: 0 | R27: 0 | S27: 0 | T27: 0 | U27: 0 | V27: 0 | W27: 0 | X27: 0 | Y27: 0 | Z27: 0 | AA27: 0 | AB27: 0 | AC27: 0 | AD27: 0 | AE27: 0 | AF27: 0 | AG27: 0 | AH27: 0 | AI27: 0 | AJ27: 0 | AK27: 0 | AL27: 0 | AM27: 0 | AN27: 0 | AO27: 0 | AP27: 0 | AQ27: 0 | AR27: 0 | AS27: 0 | AT27: 0 | AU27: 0 | AV27: 0 | AW27: 0 | AX27: 0 | AY27: 0 | AZ27: 0 | BA27: 0 | BB27: 0 | BC27: 0 | BD27: 0 | BE27: 0 | BF27: 0 | BG27: 0 | BH27: 0 | BI27: 0 | BJ27: 0 | BK27: 0 | BL27: 0 | BM27: 0 | BN27: 0 | BO27: 0 | BP27: 0 | BQ27: 0 | BR27: 0 | BS27: 0 | BT27: 0 | BU27: 0 | BV27: 0 | BW27: 0 | BX27: 0 | BY27: 0 | BZ27: 0 | CA27: 0 | CB27: 0 | CC27: 0 | CD27: 0 | CE27: 0 | CF27: 0 | CG27: 0 | CH27: 0 | CI27: 0
A28: Retención IRPF | B28: EUR | D28: =D23*'1_PANEL_CONTROL'!$E$40 -> 225 | E28: =E23*'1_PANEL_CONTROL'!$E$40 -> 225 | F28: =F23*'1_PANEL_CONTROL'!$E$40 -> 225 | G28: =G23*'1_PANEL_CONTROL'!$E$40 -> 225 | H28: =H23*'1_PANEL_CONTROL'!$E$40 -> 225 | I28: =I23*'1_PANEL_CONTROL'!$E$40 -> 225 | J28: =J23*'1_PANEL_CONTROL'!$E$40 -> 225 | K28: =K23*'1_PANEL_CONTROL'!$E$40 -> 225 | ... CI28: =CI23*'1_PANEL_CONTROL'!$E$40 -> 500
A29: Salario Neto Mensual | B29: EUR | D29: =D23-D27-D28 -> 1275 | E29: =E23-E27-E28 -> 1275 | F29: =F23-F27-F28 -> 1275 | G29: =G23-G27-G28 -> 1275 | H29: =H23-H27-H28 -> 1275 | I29: =I23-I27-I28 -> 1275 | J29: =J23-J27-J28 -> 1275 | K29: =K23-K27-K28 -> 1275 | ... CI29: =CI23-CI27-CI28 -> 2833.3333
A30: Coste Total Empresa (OPEX) | B30: EUR | D30: =D23+D26 -> 1948.69 | E30: =E23+E26 -> 1948.69 | F30: =F23+F26 -> 1948.69 | G30: =G23+G26 -> 1948.69 | H30: =H23+H26 -> 1948.69 | I30: =I23+I26 -> 1948.69 | J30: =J23+J26 -> 1948.69 | K30: =K23+K26 -> 1948.69 | ... CI30: =CI23+CI26 -> 3782.0233
A32: Salario Ordinario Mensual | B32: EUR | C32: ='1_PANEL_CONTROL'!$C$41 -> 18000 | D32: =IF(D$8>='1_PANEL_CONTROL'!$D$41, IF(D$8<=12, 18000, IF(D$8<=24, 30000, 40000))/'1_PANEL_CONTROL'!$C$32, 0) -> 1500 | E32: =IF(E$8>='1_PANEL_CONTROL'!$D$41, IF(E$8<=12, 18000, IF(E$8<=24, 30000, 40000))/'1_PANEL_CONTROL'!$C$32, 0) -> 1500 | F32: =IF(F$8>='1_PANEL_CONTROL'!$D$41, IF(F$8<=12, 18000, IF(F$8<=24, 30000, 40000))/'1_PANEL_CONTROL'!$C$32, 0) -> 1500 | G32: =IF(G$8>='1_PANEL_CONTROL'!$D$41, IF(G$8<=12, 18000, IF(G$8<=24, 30000, 40000))/'1_PANEL_CONTROL'!$C$32, 0) -> 1500 | H32: =IF(H$8>='1_PANEL_CONTROL'!$D$41, IF(H$8<=12, 18000, IF(H$8<=24, 30000, 40000))/'1_PANEL_CONTROL'!$C$32, 0) -> 1500 | I32: =IF(I$8>='1_PANEL_CONTROL'!$D$41, IF(I$8<=12, 18000, IF(I$8<=24, 30000, 40000))/'1_PANEL_CONTROL'!$C$32, 0) -> 1500 | J32: =IF(J$8>='1_PANEL_CONTROL'!$D$41, IF(J$8<=12, 18000, IF(J$8<=24, 30000, 40000))/'1_PANEL_CONTROL'!$C$32, 0) -> 1500 | K32: =IF(K$8>='1_PANEL_CONTROL'!$D$41, IF(K$8<=12, 18000, IF(K$8<=24, 30000, 40000))/'1_PANEL_CONTROL'!$C$32, 0) -> 1500 | ... CI32: =IF(CI$8>='1_PANEL_CONTROL'!$D$41, IF(CI$8<=12, 18000, IF(CI$8<=24, 30000, 40000))/'1_PANEL_CONTROL'!$C$32, 0) -> 3333.3333
A33: Pagas Extraordinarias | B33: EUR | D33: =IF(D$8>='1_PANEL_CONTROL'!$D$41, IF('1_PANEL_CONTROL'!$C$32=14, IF(OR(MOD(D$8,12)=6, MOD(D$8,12)=0), IF(D$8<=12, 18000, IF(D$8<=24, 30000, 40000))/14, 0), 0), 0) -> 0 | E33: =IF(E$8>='1_PANEL_CONTROL'!$D$41, IF('1_PANEL_CONTROL'!$C$32=14, IF(OR(MOD(E$8,12)=6, MOD(E$8,12)=0), IF(E$8<=12, 18000, IF(E$8<=24, 30000, 40000))/14, 0), 0), 0) -> 0 | F33: =IF(F$8>='1_PANEL_CONTROL'!$D$41, IF('1_PANEL_CONTROL'!$C$32=14, IF(OR(MOD(F$8,12)=6, MOD(F$8,12)=0), IF(F$8<=12, 18000, IF(F$8<=24, 30000, 40000))/14, 0), 0), 0) -> 0 | G33: =IF(G$8>='1_PANEL_CONTROL'!$D$41, IF('1_PANEL_CONTROL'!$C$32=14, IF(OR(MOD(G$8,12)=6, MOD(G$8,12)=0), IF(G$8<=12, 18000, IF(G$8<=24, 30000, 40000))/14, 0), 0), 0) -> 0 | H33: =IF(H$8>='1_PANEL_CONTROL'!$D$41, IF('1_PANEL_CONTROL'!$C$32=14, IF(OR(MOD(H$8,12)=6, MOD(H$8,12)=0), IF(H$8<=12, 18000, IF(H$8<=24, 30000, 40000))/14, 0), 0), 0) -> 0 | I33: =IF(I$8>='1_PANEL_CONTROL'!$D$41, IF('1_PANEL_CONTROL'!$C$32=14, IF(OR(MOD(I$8,12)=6, MOD(I$8,12)=0), IF(I$8<=12, 18000, IF(I$8<=24, 30000, 40000))/14, 0), 0), 0) -> 0 | J33: =IF(J$8>='1_PANEL_CONTROL'!$D$41, IF('1_PANEL_CONTROL'!$C$32=14, IF(OR(MOD(J$8,12)=6, MOD(J$8,12)=0), IF(J$8<=12, 18000, IF(J$8<=24, 30000, 40000))/14, 0), 0), 0) -> 0 | K33: =IF(K$8>='1_PANEL_CONTROL'!$D$41, IF('1_PANEL_CONTROL'!$C$32=14, IF(OR(MOD(K$8,12)=6, MOD(K$8,12)=0), IF(K$8<=12, 18000, IF(K$8<=24, 30000, 40000))/14, 0), 0), 0) -> 0 | ... CI33: =IF(CI$8>='1_PANEL_CONTROL'!$D$41, IF('1_PANEL_CONTROL'!$C$32=14, IF(OR(MOD(CI$8,12)=6, MOD(CI$8,12)=0), IF(CI$8<=12, 18000, IF(CI$8<=24, 30000, 40000))/14, 0), 0), 0) -> 0
A34: Sueldo Bruto Devengado | B34: EUR | D34: =D32+D33 -> 1500 | E34: =E32+E33 -> 1500 | F34: =F32+F33 -> 1500 | G34: =G32+G33 -> 1500 | H34: =H32+H33 -> 1500 | I34: =I32+I33 -> 1500 | J34: =J32+J33 -> 1500 | K34: =K32+K33 -> 1500 | ... CI34: =CI32+CI33 -> 3333.3333
A35: Base de Cotización SS (BCCC) | B35: EUR | D35: =IF(D$8>='1_PANEL_CONTROL'!$D$41, IF(D$8<=12, 18000, IF(D$8<=24, 30000, 40000))/12, 0) -> 1500 | E35: =IF(E$8>='1_PANEL_CONTROL'!$D$41, IF(E$8<=12, 18000, IF(E$8<=24, 30000, 40000))/12, 0) -> 1500 | F35: =IF(F$8>='1_PANEL_CONTROL'!$D$41, IF(F$8<=12, 18000, IF(F$8<=24, 30000, 40000))/12, 0) -> 1500 | G35: =IF(G$8>='1_PANEL_CONTROL'!$D$41, IF(G$8<=12, 18000, IF(G$8<=24, 30000, 40000))/12, 0) -> 1500 | H35: =IF(H$8>='1_PANEL_CONTROL'!$D$41, IF(H$8<=12, 18000, IF(H$8<=24, 30000, 40000))/12, 0) -> 1500 | I35: =IF(I$8>='1_PANEL_CONTROL'!$D$41, IF(I$8<=12, 18000, IF(I$8<=24, 30000, 40000))/12, 0) -> 1500 | J35: =IF(J$8>='1_PANEL_CONTROL'!$D$41, IF(J$8<=12, 18000, IF(J$8<=24, 30000, 40000))/12, 0) -> 1500 | K35: =IF(K$8>='1_PANEL_CONTROL'!$D$41, IF(K$8<=12, 18000, IF(K$8<=24, 30000, 40000))/12, 0) -> 1500 | ... CI35: =IF(CI$8>='1_PANEL_CONTROL'!$D$41, IF(CI$8<=12, 18000, IF(CI$8<=24, 30000, 40000))/12, 0) -> 3333.3333
A36: Base Cotización Capped | B36: EUR | D36: =IF(D$8>='1_PANEL_CONTROL'!$D$41, MIN(MAX(D35, $D$6), $D$5), 0) -> 1500 | E36: =IF(E$8>='1_PANEL_CONTROL'!$D$41, MIN(MAX(E35, $D$6), $D$5), 0) -> 1500 | F36: =IF(F$8>='1_PANEL_CONTROL'!$D$41, MIN(MAX(F35, $D$6), $D$5), 0) -> 1500 | G36: =IF(G$8>='1_PANEL_CONTROL'!$D$41, MIN(MAX(G35, $D$6), $D$5), 0) -> 1500 | H36: =IF(H$8>='1_PANEL_CONTROL'!$D$41, MIN(MAX(H35, $D$6), $D$5), 0) -> 1500 | I36: =IF(I$8>='1_PANEL_CONTROL'!$D$41, MIN(MAX(I35, $D$6), $D$5), 0) -> 1500 | J36: =IF(J$8>='1_PANEL_CONTROL'!$D$41, MIN(MAX(J35, $D$6), $D$5), 0) -> 1500 | K36: =IF(K$8>='1_PANEL_CONTROL'!$D$41, MIN(MAX(K35, $D$6), $D$5), 0) -> 1500 | ... CI36: =IF(CI$8>='1_PANEL_CONTROL'!$D$41, MIN(MAX(CI35, $D$6), $D$5), 0) -> 3333.3333
A37: SS Empresa | B37: EUR | D37: =IF(D$8>='1_PANEL_CONTROL'!$D$41, '1_PANEL_CONTROL'!$F$33, 0) -> 448.69 | E37: =IF(E$8>='1_PANEL_CONTROL'!$D$41, '1_PANEL_CONTROL'!$F$33, 0) -> 448.69 | F37: =IF(F$8>='1_PANEL_CONTROL'!$D$41, '1_PANEL_CONTROL'!$F$33, 0) -> 448.69 | G37: =IF(G$8>='1_PANEL_CONTROL'!$D$41, '1_PANEL_CONTROL'!$F$33, 0) -> 448.69 | H37: =IF(H$8>='1_PANEL_CONTROL'!$D$41, '1_PANEL_CONTROL'!$F$33, 0) -> 448.69 | I37: =IF(I$8>='1_PANEL_CONTROL'!$D$41, '1_PANEL_CONTROL'!$F$33, 0) -> 448.69 | J37: =IF(J$8>='1_PANEL_CONTROL'!$D$41, '1_PANEL_CONTROL'!$F$33, 0) -> 448.69 | K37: =IF(K$8>='1_PANEL_CONTROL'!$D$41, '1_PANEL_CONTROL'!$F$33, 0) -> 448.69 | ... CI37: =IF(CI$8>='1_PANEL_CONTROL'!$D$41, '1_PANEL_CONTROL'!$F$33, 0) -> 448.69
A38: SS Empleado | B38: EUR | D38: 0 | E38: 0 | F38: 0 | G38: 0 | H38: 0 | I38: 0 | J38: 0 | K38: 0 | L38: 0 | M38: 0 | N38: 0 | O38: 0 | P38: 0 | Q38: 0 | R38: 0 | S38: 0 | T38: 0 | U38: 0 | V38: 0 | W38: 0 | X38: 0 | Y38: 0 | Z38: 0 | AA38: 0 | AB38: 0 | AC38: 0 | AD38: 0 | AE38: 0 | AF38: 0 | AG38: 0 | AH38: 0 | AI38: 0 | AJ38: 0 | AK38: 0 | AL38: 0 | AM38: 0 | AN38: 0 | AO38: 0 | AP38: 0 | AQ38: 0 | AR38: 0 | AS38: 0 | AT38: 0 | AU38: 0 | AV38: 0 | AW38: 0 | AX38: 0 | AY38: 0 | AZ38: 0 | BA38: 0 | BB38: 0 | BC38: 0 | BD38: 0 | BE38: 0 | BF38: 0 | BG38: 0 | BH38: 0 | BI38: 0 | BJ38: 0 | BK38: 0 | BL38: 0 | BM38: 0 | BN38: 0 | BO38: 0 | BP38: 0 | BQ38: 0 | BR38: 0 | BS38: 0 | BT38: 0 | BU38: 0 | BV38: 0 | BW38: 0 | BX38: 0 | BY38: 0 | BZ38: 0 | CA38: 0 | CB38: 0 | CC38: 0 | CD38: 0 | CE38: 0 | CF38: 0 | CG38: 0 | CH38: 0 | CI38: 0
A39: Retención IRPF | B39: EUR | D39: =D34*'1_PANEL_CONTROL'!$E$41 -> 225 | E39: =E34*'1_PANEL_CONTROL'!$E$41 -> 225 | F39: =F34*'1_PANEL_CONTROL'!$E$41 -> 225 | G39: =G34*'1_PANEL_CONTROL'!$E$41 -> 225 | H39: =H34*'1_PANEL_CONTROL'!$E$41 -> 225 | I39: =I34*'1_PANEL_CONTROL'!$E$41 -> 225 | J39: =J34*'1_PANEL_CONTROL'!$E$41 -> 225 | K39: =K34*'1_PANEL_CONTROL'!$E$41 -> 225 | ... CI39: =CI34*'1_PANEL_CONTROL'!$E$41 -> 500
A40: Salario Neto Mensual | B40: EUR | D40: =D34-D38-D39 -> 1275 | E40: =E34-E38-E39 -> 1275 | F40: =F34-F38-F39 -> 1275 | G40: =G34-G38-G39 -> 1275 | H40: =H34-H38-H39 -> 1275 | I40: =I34-I38-I39 -> 1275 | J40: =J34-J38-J39 -> 1275 | K40: =K34-K38-K39 -> 1275 | ... CI40: =CI34-CI38-CI39 -> 2833.3333
A41: Coste Total Empresa (OPEX) | B41: EUR | D41: =D34+D37 -> 1948.69 | E41: =E34+E37 -> 1948.69 | F41: =F34+F37 -> 1948.69 | G41: =G34+G37 -> 1948.69 | H41: =H34+H37 -> 1948.69 | I41: =I34+I37 -> 1948.69 | J41: =J34+J37 -> 1948.69 | K41: =K34+K37 -> 1948.69 | ... CI41: =CI34+CI37 -> 3782.0233
A43: Salario Ordinario Mensual | B43: EUR | C43: ='1_PANEL_CONTROL'!$C$42 -> 18000 | D43: =IF(D$8>='1_PANEL_CONTROL'!$D$42, IF(D$8<=12, 18000, IF(D$8<=24, 30000, 40000))/'1_PANEL_CONTROL'!$C$32, 0) -> 1500 | E43: =IF(E$8>='1_PANEL_CONTROL'!$D$42, IF(E$8<=12, 18000, IF(E$8<=24, 30000, 40000))/'1_PANEL_CONTROL'!$C$32, 0) -> 1500 | F43: =IF(F$8>='1_PANEL_CONTROL'!$D$42, IF(F$8<=12, 18000, IF(F$8<=24, 30000, 40000))/'1_PANEL_CONTROL'!$C$32, 0) -> 1500 | G43: =IF(G$8>='1_PANEL_CONTROL'!$D$42, IF(G$8<=12, 18000, IF(G$8<=24, 30000, 40000))/'1_PANEL_CONTROL'!$C$32, 0) -> 1500 | H43: =IF(H$8>='1_PANEL_CONTROL'!$D$42, IF(H$8<=12, 18000, IF(H$8<=24, 30000, 40000))/'1_PANEL_CONTROL'!$C$32, 0) -> 1500 | I43: =IF(I$8>='1_PANEL_CONTROL'!$D$42, IF(I$8<=12, 18000, IF(I$8<=24, 30000, 40000))/'1_PANEL_CONTROL'!$C$32, 0) -> 1500 | J43: =IF(J$8>='1_PANEL_CONTROL'!$D$42, IF(J$8<=12, 18000, IF(J$8<=24, 30000, 40000))/'1_PANEL_CONTROL'!$C$32, 0) -> 1500 | K43: =IF(K$8>='1_PANEL_CONTROL'!$D$42, IF(K$8<=12, 18000, IF(K$8<=24, 30000, 40000))/'1_PANEL_CONTROL'!$C$32, 0) -> 1500 | ... CI43: =IF(CI$8>='1_PANEL_CONTROL'!$D$42, IF(CI$8<=12, 18000, IF(CI$8<=24, 30000, 40000))/'1_PANEL_CONTROL'!$C$32, 0) -> 3333.3333
A44: Pagas Extraordinarias | B44: EUR | D44: =IF(D$8>='1_PANEL_CONTROL'!$D$42, IF('1_PANEL_CONTROL'!$C$32=14, IF(OR(MOD(D$8,12)=6, MOD(D$8,12)=0), IF(D$8<=12, 18000, IF(D$8<=24, 30000, 40000))/14, 0), 0), 0) -> 0 | E44: =IF(E$8>='1_PANEL_CONTROL'!$D$42, IF('1_PANEL_CONTROL'!$C$32=14, IF(OR(MOD(E$8,12)=6, MOD(E$8,12)=0), IF(E$8<=12, 18000, IF(E$8<=24, 30000, 40000))/14, 0), 0), 0) -> 0 | F44: =IF(F$8>='1_PANEL_CONTROL'!$D$42, IF('1_PANEL_CONTROL'!$C$32=14, IF(OR(MOD(F$8,12)=6, MOD(F$8,12)=0), IF(F$8<=12, 18000, IF(F$8<=24, 30000, 40000))/14, 0), 0), 0) -> 0 | G44: =IF(G$8>='1_PANEL_CONTROL'!$D$42, IF('1_PANEL_CONTROL'!$C$32=14, IF(OR(MOD(G$8,12)=6, MOD(G$8,12)=0), IF(G$8<=12, 18000, IF(G$8<=24, 30000, 40000))/14, 0), 0), 0) -> 0 | H44: =IF(H$8>='1_PANEL_CONTROL'!$D$42, IF('1_PANEL_CONTROL'!$C$32=14, IF(OR(MOD(H$8,12)=6, MOD(H$8,12)=0), IF(H$8<=12, 18000, IF(H$8<=24, 30000, 40000))/14, 0), 0), 0) -> 0 | I44: =IF(I$8>='1_PANEL_CONTROL'!$D$42, IF('1_PANEL_CONTROL'!$C$32=14, IF(OR(MOD(I$8,12)=6, MOD(I$8,12)=0), IF(I$8<=12, 18000, IF(I$8<=24, 30000, 40000))/14, 0), 0), 0) -> 0 | J44: =IF(J$8>='1_PANEL_CONTROL'!$D$42, IF('1_PANEL_CONTROL'!$C$32=14, IF(OR(MOD(J$8,12)=6, MOD(J$8,12)=0), IF(J$8<=12, 18000, IF(J$8<=24, 30000, 40000))/14, 0), 0), 0) -> 0 | K44: =IF(K$8>='1_PANEL_CONTROL'!$D$42, IF('1_PANEL_CONTROL'!$C$32=14, IF(OR(MOD(K$8,12)=6, MOD(K$8,12)=0), IF(K$8<=12, 18000, IF(K$8<=24, 30000, 40000))/14, 0), 0), 0) -> 0 | ... CI44: =IF(CI$8>='1_PANEL_CONTROL'!$D$42, IF('1_PANEL_CONTROL'!$C$32=14, IF(OR(MOD(CI$8,12)=6, MOD(CI$8,12)=0), IF(CI$8<=12, 18000, IF(CI$8<=24, 30000, 40000))/14, 0), 0), 0) -> 0
A45: Sueldo Bruto Devengado | B45: EUR | D45: =D43+D44 -> 1500 | E45: =E43+E44 -> 1500 | F45: =F43+F44 -> 1500 | G45: =G43+G44 -> 1500 | H45: =H43+H44 -> 1500 | I45: =I43+I44 -> 1500 | J45: =J43+J44 -> 1500 | K45: =K43+K44 -> 1500 | ... CI45: =CI43+CI44 -> 3333.3333
A46: Base de Cotización SS (BCCC) | B46: EUR | D46: =IF(D$8>='1_PANEL_CONTROL'!$D$42, IF(D$8<=12, 18000, IF(D$8<=24, 30000, 40000))/12, 0) -> 1500 | E46: =IF(E$8>='1_PANEL_CONTROL'!$D$42, IF(E$8<=12, 18000, IF(E$8<=24, 30000, 40000))/12, 0) -> 1500 | F46: =IF(F$8>='1_PANEL_CONTROL'!$D$42, IF(F$8<=12, 18000, IF(F$8<=24, 30000, 40000))/12, 0) -> 1500 | G46: =IF(G$8>='1_PANEL_CONTROL'!$D$42, IF(G$8<=12, 18000, IF(G$8<=24, 30000, 40000))/12, 0) -> 1500 | H46: =IF(H$8>='1_PANEL_CONTROL'!$D$42, IF(H$8<=12, 18000, IF(H$8<=24, 30000, 40000))/12, 0) -> 1500 | I46: =IF(I$8>='1_PANEL_CONTROL'!$D$42, IF(I$8<=12, 18000, IF(I$8<=24, 30000, 40000))/12, 0) -> 1500 | J46: =IF(J$8>='1_PANEL_CONTROL'!$D$42, IF(J$8<=12, 18000, IF(J$8<=24, 30000, 40000))/12, 0) -> 1500 | K46: =IF(K$8>='1_PANEL_CONTROL'!$D$42, IF(K$8<=12, 18000, IF(K$8<=24, 30000, 40000))/12, 0) -> 1500 | ... CI46: =IF(CI$8>='1_PANEL_CONTROL'!$D$42, IF(CI$8<=12, 18000, IF(CI$8<=24, 30000, 40000))/12, 0) -> 3333.3333
A47: Base Cotización Capped | B47: EUR | D47: =IF(D$8>='1_PANEL_CONTROL'!$D$42, MIN(MAX(D46, $D$6), $D$5), 0) -> 1500 | E47: =IF(E$8>='1_PANEL_CONTROL'!$D$42, MIN(MAX(E46, $D$6), $D$5), 0) -> 1500 | F47: =IF(F$8>='1_PANEL_CONTROL'!$D$42, MIN(MAX(F46, $D$6), $D$5), 0) -> 1500 | G47: =IF(G$8>='1_PANEL_CONTROL'!$D$42, MIN(MAX(G46, $D$6), $D$5), 0) -> 1500 | H47: =IF(H$8>='1_PANEL_CONTROL'!$D$42, MIN(MAX(H46, $D$6), $D$5), 0) -> 1500 | I47: =IF(I$8>='1_PANEL_CONTROL'!$D$42, MIN(MAX(I46, $D$6), $D$5), 0) -> 1500 | J47: =IF(J$8>='1_PANEL_CONTROL'!$D$42, MIN(MAX(J46, $D$6), $D$5), 0) -> 1500 | K47: =IF(K$8>='1_PANEL_CONTROL'!$D$42, MIN(MAX(K46, $D$6), $D$5), 0) -> 1500 | ... CI47: =IF(CI$8>='1_PANEL_CONTROL'!$D$42, MIN(MAX(CI46, $D$6), $D$5), 0) -> 3333.3333
A48: SS Empresa | B48: EUR | D48: =IF(D$8>='1_PANEL_CONTROL'!$D$42, '1_PANEL_CONTROL'!$F$33, 0) -> 448.69 | E48: =IF(E$8>='1_PANEL_CONTROL'!$D$42, '1_PANEL_CONTROL'!$F$33, 0) -> 448.69 | F48: =IF(F$8>='1_PANEL_CONTROL'!$D$42, '1_PANEL_CONTROL'!$F$33, 0) -> 448.69 | G48: =IF(G$8>='1_PANEL_CONTROL'!$D$42, '1_PANEL_CONTROL'!$F$33, 0) -> 448.69 | H48: =IF(H$8>='1_PANEL_CONTROL'!$D$42, '1_PANEL_CONTROL'!$F$33, 0) -> 448.69 | I48: =IF(I$8>='1_PANEL_CONTROL'!$D$42, '1_PANEL_CONTROL'!$F$33, 0) -> 448.69 | J48: =IF(J$8>='1_PANEL_CONTROL'!$D$42, '1_PANEL_CONTROL'!$F$33, 0) -> 448.69 | K48: =IF(K$8>='1_PANEL_CONTROL'!$D$42, '1_PANEL_CONTROL'!$F$33, 0) -> 448.69 | ... CI48: =IF(CI$8>='1_PANEL_CONTROL'!$D$42, '1_PANEL_CONTROL'!$F$33, 0) -> 448.69
A49: SS Empleado | B49: EUR | D49: 0 | E49: 0 | F49: 0 | G49: 0 | H49: 0 | I49: 0 | J49: 0 | K49: 0 | L49: 0 | M49: 0 | N49: 0 | O49: 0 | P49: 0 | Q49: 0 | R49: 0 | S49: 0 | T49: 0 | U49: 0 | V49: 0 | W49: 0 | X49: 0 | Y49: 0 | Z49: 0 | AA49: 0 | AB49: 0 | AC49: 0 | AD49: 0 | AE49: 0 | AF49: 0 | AG49: 0 | AH49: 0 | AI49: 0 | AJ49: 0 | AK49: 0 | AL49: 0 | AM49: 0 | AN49: 0 | AO49: 0 | AP49: 0 | AQ49: 0 | AR49: 0 | AS49: 0 | AT49: 0 | AU49: 0 | AV49: 0 | AW49: 0 | AX49: 0 | AY49: 0 | AZ49: 0 | BA49: 0 | BB49: 0 | BC49: 0 | BD49: 0 | BE49: 0 | BF49: 0 | BG49: 0 | BH49: 0 | BI49: 0 | BJ49: 0 | BK49: 0 | BL49: 0 | BM49: 0 | BN49: 0 | BO49: 0 | BP49: 0 | BQ49: 0 | BR49: 0 | BS49: 0 | BT49: 0 | BU49: 0 | BV49: 0 | BW49: 0 | BX49: 0 | BY49: 0 | BZ49: 0 | CA49: 0 | CB49: 0 | CC49: 0 | CD49: 0 | CE49: 0 | CF49: 0 | CG49: 0 | CH49: 0 | CI49: 0
A50: Retención IRPF | B50: EUR | D50: =D45*'1_PANEL_CONTROL'!$E$42 -> 225 | E50: =E45*'1_PANEL_CONTROL'!$E$42 -> 225 | F50: =F45*'1_PANEL_CONTROL'!$E$42 -> 225 | G50: =G45*'1_PANEL_CONTROL'!$E$42 -> 225 | H50: =H45*'1_PANEL_CONTROL'!$E$42 -> 225 | I50: =I45*'1_PANEL_CONTROL'!$E$42 -> 225 | J50: =J45*'1_PANEL_CONTROL'!$E$42 -> 225 | K50: =K45*'1_PANEL_CONTROL'!$E$42 -> 225 | ... CI50: =CI45*'1_PANEL_CONTROL'!$E$42 -> 500
A51: Salario Neto Mensual | B51: EUR | D51: =D45-D49-D50 -> 1275 | E51: =E45-E49-E50 -> 1275 | F51: =F45-F49-F50 -> 1275 | G51: =G45-G49-G50 -> 1275 | H51: =H45-H49-H50 -> 1275 | I51: =I45-I49-I50 -> 1275 | J51: =J45-J49-J50 -> 1275 | K51: =K45-K49-K50 -> 1275 | ... CI51: =CI45-CI49-CI50 -> 2833.3333
A52: Coste Total Empresa (OPEX) | B52: EUR | D52: =D45+D48 -> 1948.69 | E52: =E45+E48 -> 1948.69 | F52: =F45+F48 -> 1948.69 | G52: =G45+G48 -> 1948.69 | H52: =H45+H48 -> 1948.69 | I52: =I45+I48 -> 1948.69 | J52: =J45+J48 -> 1948.69 | K52: =K45+K48 -> 1948.69 | ... CI52: =CI45+CI48 -> 3782.0233
A54: Salario Ordinario Mensual | B54: EUR | C54: ='1_PANEL_CONTROL'!$C$43 -> 45000 | D54: =IF(D$8>='1_PANEL_CONTROL'!$D$43, '1_PANEL_CONTROL'!$C$43/'1_PANEL_CONTROL'!$C$32, 0) -> 0 | E54: =IF(E$8>='1_PANEL_CONTROL'!$D$43, '1_PANEL_CONTROL'!$C$43/'1_PANEL_CONTROL'!$C$32, 0) -> 0 | F54: =IF(F$8>='1_PANEL_CONTROL'!$D$43, '1_PANEL_CONTROL'!$C$43/'1_PANEL_CONTROL'!$C$32, 0) -> 0 | G54: =IF(G$8>='1_PANEL_CONTROL'!$D$43, '1_PANEL_CONTROL'!$C$43/'1_PANEL_CONTROL'!$C$32, 0) -> 0 | H54: =IF(H$8>='1_PANEL_CONTROL'!$D$43, '1_PANEL_CONTROL'!$C$43/'1_PANEL_CONTROL'!$C$32, 0) -> 0 | I54: =IF(I$8>='1_PANEL_CONTROL'!$D$43, '1_PANEL_CONTROL'!$C$43/'1_PANEL_CONTROL'!$C$32, 0) -> 0 | J54: =IF(J$8>='1_PANEL_CONTROL'!$D$43, '1_PANEL_CONTROL'!$C$43/'1_PANEL_CONTROL'!$C$32, 0) -> 0 | K54: =IF(K$8>='1_PANEL_CONTROL'!$D$43, '1_PANEL_CONTROL'!$C$43/'1_PANEL_CONTROL'!$C$32, 0) -> 0 | ... CI54: =IF(CI$8>='1_PANEL_CONTROL'!$D$43, '1_PANEL_CONTROL'!$C$43/'1_PANEL_CONTROL'!$C$32, 0) -> 3750
A55: Pagas Extraordinarias | B55: EUR | D55: =IF(D$8>='1_PANEL_CONTROL'!$D$43, IF('1_PANEL_CONTROL'!$C$32=14, IF(OR(MOD(D$8,12)=6, MOD(D$8,12)=0), '1_PANEL_CONTROL'!$C$43/14, 0), 0), 0) -> 0 | E55: =IF(E$8>='1_PANEL_CONTROL'!$D$43, IF('1_PANEL_CONTROL'!$C$32=14, IF(OR(MOD(E$8,12)=6, MOD(E$8,12)=0), '1_PANEL_CONTROL'!$C$43/14, 0), 0), 0) -> 0 | F55: =IF(F$8>='1_PANEL_CONTROL'!$D$43, IF('1_PANEL_CONTROL'!$C$32=14, IF(OR(MOD(F$8,12)=6, MOD(F$8,12)=0), '1_PANEL_CONTROL'!$C$43/14, 0), 0), 0) -> 0 | G55: =IF(G$8>='1_PANEL_CONTROL'!$D$43, IF('1_PANEL_CONTROL'!$C$32=14, IF(OR(MOD(G$8,12)=6, MOD(G$8,12)=0), '1_PANEL_CONTROL'!$C$43/14, 0), 0), 0) -> 0 | H55: =IF(H$8>='1_PANEL_CONTROL'!$D$43, IF('1_PANEL_CONTROL'!$C$32=14, IF(OR(MOD(H$8,12)=6, MOD(H$8,12)=0), '1_PANEL_CONTROL'!$C$43/14, 0), 0), 0) -> 0 | I55: =IF(I$8>='1_PANEL_CONTROL'!$D$43, IF('1_PANEL_CONTROL'!$C$32=14, IF(OR(MOD(I$8,12)=6, MOD(I$8,12)=0), '1_PANEL_CONTROL'!$C$43/14, 0), 0), 0) -> 0 | J55: =IF(J$8>='1_PANEL_CONTROL'!$D$43, IF('1_PANEL_CONTROL'!$C$32=14, IF(OR(MOD(J$8,12)=6, MOD(J$8,12)=0), '1_PANEL_CONTROL'!$C$43/14, 0), 0), 0) -> 0 | K55: =IF(K$8>='1_PANEL_CONTROL'!$D$43, IF('1_PANEL_CONTROL'!$C$32=14, IF(OR(MOD(K$8,12)=6, MOD(K$8,12)=0), '1_PANEL_CONTROL'!$C$43/14, 0), 0), 0) -> 0 | ... CI55: =IF(CI$8>='1_PANEL_CONTROL'!$D$43, IF('1_PANEL_CONTROL'!$C$32=14, IF(OR(MOD(CI$8,12)=6, MOD(CI$8,12)=0), '1_PANEL_CONTROL'!$C$43/14, 0), 0), 0) -> 0
A56: Sueldo Bruto Devengado | B56: EUR | D56: =D54+D55 -> 0 | E56: =E54+E55 -> 0 | F56: =F54+F55 -> 0 | G56: =G54+G55 -> 0 | H56: =H54+H55 -> 0 | I56: =I54+I55 -> 0 | J56: =J54+J55 -> 0 | K56: =K54+K55 -> 0 | ... CI56: =CI54+CI55 -> 3750
A57: Base de Cotización SS (BCCC) | B57: EUR | D57: =IF(D$8>='1_PANEL_CONTROL'!$D$43, '1_PANEL_CONTROL'!$C$43/12, 0) -> 0 | E57: =IF(E$8>='1_PANEL_CONTROL'!$D$43, '1_PANEL_CONTROL'!$C$43/12, 0) -> 0 | F57: =IF(F$8>='1_PANEL_CONTROL'!$D$43, '1_PANEL_CONTROL'!$C$43/12, 0) -> 0 | G57: =IF(G$8>='1_PANEL_CONTROL'!$D$43, '1_PANEL_CONTROL'!$C$43/12, 0) -> 0 | H57: =IF(H$8>='1_PANEL_CONTROL'!$D$43, '1_PANEL_CONTROL'!$C$43/12, 0) -> 0 | I57: =IF(I$8>='1_PANEL_CONTROL'!$D$43, '1_PANEL_CONTROL'!$C$43/12, 0) -> 0 | J57: =IF(J$8>='1_PANEL_CONTROL'!$D$43, '1_PANEL_CONTROL'!$C$43/12, 0) -> 0 | K57: =IF(K$8>='1_PANEL_CONTROL'!$D$43, '1_PANEL_CONTROL'!$C$43/12, 0) -> 0 | ... CI57: =IF(CI$8>='1_PANEL_CONTROL'!$D$43, '1_PANEL_CONTROL'!$C$43/12, 0) -> 3750
A58: Base Cotización Capped | B58: EUR | D58: =IF(D$8>='1_PANEL_CONTROL'!$D$43, MIN(MAX(D57, $D$6), $D$5), 0) -> 0 | E58: =IF(E$8>='1_PANEL_CONTROL'!$D$43, MIN(MAX(E57, $D$6), $D$5), 0) -> 0 | F58: =IF(F$8>='1_PANEL_CONTROL'!$D$43, MIN(MAX(F57, $D$6), $D$5), 0) -> 0 | G58: =IF(G$8>='1_PANEL_CONTROL'!$D$43, MIN(MAX(G57, $D$6), $D$5), 0) -> 0 | H58: =IF(H$8>='1_PANEL_CONTROL'!$D$43, MIN(MAX(H57, $D$6), $D$5), 0) -> 0 | I58: =IF(I$8>='1_PANEL_CONTROL'!$D$43, MIN(MAX(I57, $D$6), $D$5), 0) -> 0 | J58: =IF(J$8>='1_PANEL_CONTROL'!$D$43, MIN(MAX(J57, $D$6), $D$5), 0) -> 0 | K58: =IF(K$8>='1_PANEL_CONTROL'!$D$43, MIN(MAX(K57, $D$6), $D$5), 0) -> 0 | ... CI58: =IF(CI$8>='1_PANEL_CONTROL'!$D$43, MIN(MAX(CI57, $D$6), $D$5), 0) -> 3750
A59: SS Empresa | B59: EUR | D59: =D58*$B$5 -> 0 | E59: =E58*$B$5 -> 0 | F59: =F58*$B$5 -> 0 | G59: =G58*$B$5 -> 0 | H59: =H58*$B$5 -> 0 | I59: =I58*$B$5 -> 0 | J59: =J58*$B$5 -> 0 | K59: =K58*$B$5 -> 0 | ... CI59: =CI58*$B$5 -> 1203.75
A60: SS Empleado | B60: EUR | D60: =D58*$B$6 -> 0 | E60: =E58*$B$6 -> 0 | F60: =F58*$B$6 -> 0 | G60: =G58*$B$6 -> 0 | H60: =H58*$B$6 -> 0 | I60: =I58*$B$6 -> 0 | J60: =J58*$B$6 -> 0 | K60: =K58*$B$6 -> 0 | ... CI60: =CI58*$B$6 -> 242.625
A61: Retención IRPF | B61: EUR | D61: =D56*'1_PANEL_CONTROL'!$E$43 -> 0 | E61: =E56*'1_PANEL_CONTROL'!$E$43 -> 0 | F61: =F56*'1_PANEL_CONTROL'!$E$43 -> 0 | G61: =G56*'1_PANEL_CONTROL'!$E$43 -> 0 | H61: =H56*'1_PANEL_CONTROL'!$E$43 -> 0 | I61: =I56*'1_PANEL_CONTROL'!$E$43 -> 0 | J61: =J56*'1_PANEL_CONTROL'!$E$43 -> 0 | K61: =K56*'1_PANEL_CONTROL'!$E$43 -> 0 | ... CI61: =CI56*'1_PANEL_CONTROL'!$E$43 -> 562.5
A62: Salario Neto Mensual | B62: EUR | D62: =D56-D60-D61 -> 0 | E62: =E56-E60-E61 -> 0 | F62: =F56-F60-F61 -> 0 | G62: =G56-G60-G61 -> 0 | H62: =H56-H60-H61 -> 0 | I62: =I56-I60-I61 -> 0 | J62: =J56-J60-J61 -> 0 | K62: =K56-K60-K61 -> 0 | ... CI62: =CI56-CI60-CI61 -> 2944.875
A63: Coste Total Empresa (OPEX) | B63: EUR | D63: =D56+D59 -> 0 | E63: =E56+E59 -> 0 | F63: =F56+F59 -> 0 | G63: =G56+G59 -> 0 | H63: =H56+H59 -> 0 | I63: =I56+I59 -> 0 | J63: =J56+J59 -> 0 | K63: =K56+K59 -> 0 | ... CI63: =CI56+CI59 -> 4953.75
A65: Salario Ordinario Mensual | B65: EUR | C65: ='1_PANEL_CONTROL'!$C$44 -> 24000 | D65: =IF(D$8>='1_PANEL_CONTROL'!$D$44, '1_PANEL_CONTROL'!$C$44/'1_PANEL_CONTROL'!$C$32, 0) -> 0 | E65: =IF(E$8>='1_PANEL_CONTROL'!$D$44, '1_PANEL_CONTROL'!$C$44/'1_PANEL_CONTROL'!$C$32, 0) -> 0 | F65: =IF(F$8>='1_PANEL_CONTROL'!$D$44, '1_PANEL_CONTROL'!$C$44/'1_PANEL_CONTROL'!$C$32, 0) -> 0 | G65: =IF(G$8>='1_PANEL_CONTROL'!$D$44, '1_PANEL_CONTROL'!$C$44/'1_PANEL_CONTROL'!$C$32, 0) -> 0 | H65: =IF(H$8>='1_PANEL_CONTROL'!$D$44, '1_PANEL_CONTROL'!$C$44/'1_PANEL_CONTROL'!$C$32, 0) -> 0 | I65: =IF(I$8>='1_PANEL_CONTROL'!$D$44, '1_PANEL_CONTROL'!$C$44/'1_PANEL_CONTROL'!$C$32, 0) -> 0 | J65: =IF(J$8>='1_PANEL_CONTROL'!$D$44, '1_PANEL_CONTROL'!$C$44/'1_PANEL_CONTROL'!$C$32, 0) -> 0 | K65: =IF(K$8>='1_PANEL_CONTROL'!$D$44, '1_PANEL_CONTROL'!$C$44/'1_PANEL_CONTROL'!$C$32, 0) -> 0 | ... CI65: =IF(CI$8>='1_PANEL_CONTROL'!$D$44, '1_PANEL_CONTROL'!$C$44/'1_PANEL_CONTROL'!$C$32, 0) -> 2000
A66: Pagas Extraordinarias | B66: EUR | D66: =IF(D$8>='1_PANEL_CONTROL'!$D$44, IF('1_PANEL_CONTROL'!$C$32=14, IF(OR(MOD(D$8,12)=6, MOD(D$8,12)=0), '1_PANEL_CONTROL'!$C$44/14, 0), 0), 0) -> 0 | E66: =IF(E$8>='1_PANEL_CONTROL'!$D$44, IF('1_PANEL_CONTROL'!$C$32=14, IF(OR(MOD(E$8,12)=6, MOD(E$8,12)=0), '1_PANEL_CONTROL'!$C$44/14, 0), 0), 0) -> 0 | F66: =IF(F$8>='1_PANEL_CONTROL'!$D$44, IF('1_PANEL_CONTROL'!$C$32=14, IF(OR(MOD(F$8,12)=6, MOD(F$8,12)=0), '1_PANEL_CONTROL'!$C$44/14, 0), 0), 0) -> 0 | G66: =IF(G$8>='1_PANEL_CONTROL'!$D$44, IF('1_PANEL_CONTROL'!$C$32=14, IF(OR(MOD(G$8,12)=6, MOD(G$8,12)=0), '1_PANEL_CONTROL'!$C$44/14, 0), 0), 0) -> 0 | H66: =IF(H$8>='1_PANEL_CONTROL'!$D$44, IF('1_PANEL_CONTROL'!$C$32=14, IF(OR(MOD(H$8,12)=6, MOD(H$8,12)=0), '1_PANEL_CONTROL'!$C$44/14, 0), 0), 0) -> 0 | I66: =IF(I$8>='1_PANEL_CONTROL'!$D$44, IF('1_PANEL_CONTROL'!$C$32=14, IF(OR(MOD(I$8,12)=6, MOD(I$8,12)=0), '1_PANEL_CONTROL'!$C$44/14, 0), 0), 0) -> 0 | J66: =IF(J$8>='1_PANEL_CONTROL'!$D$44, IF('1_PANEL_CONTROL'!$C$32=14, IF(OR(MOD(J$8,12)=6, MOD(J$8,12)=0), '1_PANEL_CONTROL'!$C$44/14, 0), 0), 0) -> 0 | K66: =IF(K$8>='1_PANEL_CONTROL'!$D$44, IF('1_PANEL_CONTROL'!$C$32=14, IF(OR(MOD(K$8,12)=6, MOD(K$8,12)=0), '1_PANEL_CONTROL'!$C$44/14, 0), 0), 0) -> 0 | ... CI66: =IF(CI$8>='1_PANEL_CONTROL'!$D$44, IF('1_PANEL_CONTROL'!$C$32=14, IF(OR(MOD(CI$8,12)=6, MOD(CI$8,12)=0), '1_PANEL_CONTROL'!$C$44/14, 0), 0), 0) -> 0
A67: Sueldo Bruto Devengado | B67: EUR | D67: =D65+D66 -> 0 | E67: =E65+E66 -> 0 | F67: =F65+F66 -> 0 | G67: =G65+G66 -> 0 | H67: =H65+H66 -> 0 | I67: =I65+I66 -> 0 | J67: =J65+J66 -> 0 | K67: =K65+K66 -> 0 | ... CI67: =CI65+CI66 -> 2000
A68: Base de Cotización SS (BCCC) | B68: EUR | D68: =IF(D$8>='1_PANEL_CONTROL'!$D$44, '1_PANEL_CONTROL'!$C$44/12, 0) -> 0 | E68: =IF(E$8>='1_PANEL_CONTROL'!$D$44, '1_PANEL_CONTROL'!$C$44/12, 0) -> 0 | F68: =IF(F$8>='1_PANEL_CONTROL'!$D$44, '1_PANEL_CONTROL'!$C$44/12, 0) -> 0 | G68: =IF(G$8>='1_PANEL_CONTROL'!$D$44, '1_PANEL_CONTROL'!$C$44/12, 0) -> 0 | H68: =IF(H$8>='1_PANEL_CONTROL'!$D$44, '1_PANEL_CONTROL'!$C$44/12, 0) -> 0 | I68: =IF(I$8>='1_PANEL_CONTROL'!$D$44, '1_PANEL_CONTROL'!$C$44/12, 0) -> 0 | J68: =IF(J$8>='1_PANEL_CONTROL'!$D$44, '1_PANEL_CONTROL'!$C$44/12, 0) -> 0 | K68: =IF(K$8>='1_PANEL_CONTROL'!$D$44, '1_PANEL_CONTROL'!$C$44/12, 0) -> 0 | ... CI68: =IF(CI$8>='1_PANEL_CONTROL'!$D$44, '1_PANEL_CONTROL'!$C$44/12, 0) -> 2000
A69: Base Cotización Capped | B69: EUR | D69: =IF(D$8>='1_PANEL_CONTROL'!$D$44, MIN(MAX(D68, $D$6), $D$5), 0) -> 0 | E69: =IF(E$8>='1_PANEL_CONTROL'!$D$44, MIN(MAX(E68, $D$6), $D$5), 0) -> 0 | F69: =IF(F$8>='1_PANEL_CONTROL'!$D$44, MIN(MAX(F68, $D$6), $D$5), 0) -> 0 | G69: =IF(G$8>='1_PANEL_CONTROL'!$D$44, MIN(MAX(G68, $D$6), $D$5), 0) -> 0 | H69: =IF(H$8>='1_PANEL_CONTROL'!$D$44, MIN(MAX(H68, $D$6), $D$5), 0) -> 0 | I69: =IF(I$8>='1_PANEL_CONTROL'!$D$44, MIN(MAX(I68, $D$6), $D$5), 0) -> 0 | J69: =IF(J$8>='1_PANEL_CONTROL'!$D$44, MIN(MAX(J68, $D$6), $D$5), 0) -> 0 | K69: =IF(K$8>='1_PANEL_CONTROL'!$D$44, MIN(MAX(K68, $D$6), $D$5), 0) -> 0 | ... CI69: =IF(CI$8>='1_PANEL_CONTROL'!$D$44, MIN(MAX(CI68, $D$6), $D$5), 0) -> 2000
A70: SS Empresa | B70: EUR | D70: =D69*$B$5 -> 0 | E70: =E69*$B$5 -> 0 | F70: =F69*$B$5 -> 0 | G70: =G69*$B$5 -> 0 | H70: =H69*$B$5 -> 0 | I70: =I69*$B$5 -> 0 | J70: =J69*$B$5 -> 0 | K70: =K69*$B$5 -> 0 | ... CI70: =CI69*$B$5 -> 642
A71: SS Empleado | B71: EUR | D71: =D69*$B$6 -> 0 | E71: =E69*$B$6 -> 0 | F71: =F69*$B$6 -> 0 | G71: =G69*$B$6 -> 0 | H71: =H69*$B$6 -> 0 | I71: =I69*$B$6 -> 0 | J71: =J69*$B$6 -> 0 | K71: =K69*$B$6 -> 0 | ... CI71: =CI69*$B$6 -> 129.4
A72: Retención IRPF | B72: EUR | D72: =D67*'1_PANEL_CONTROL'!$E$44 -> 0 | E72: =E67*'1_PANEL_CONTROL'!$E$44 -> 0 | F72: =F67*'1_PANEL_CONTROL'!$E$44 -> 0 | G72: =G67*'1_PANEL_CONTROL'!$E$44 -> 0 | H72: =H67*'1_PANEL_CONTROL'!$E$44 -> 0 | I72: =I67*'1_PANEL_CONTROL'!$E$44 -> 0 | J72: =J67*'1_PANEL_CONTROL'!$E$44 -> 0 | K72: =K67*'1_PANEL_CONTROL'!$E$44 -> 0 | ... CI72: =CI67*'1_PANEL_CONTROL'!$E$44 -> 280
A73: Salario Neto Mensual | B73: EUR | D73: =D67-D71-D72 -> 0 | E73: =E67-E71-E72 -> 0 | F73: =F67-F71-F72 -> 0 | G73: =G67-G71-G72 -> 0 | H73: =H67-H71-H72 -> 0 | I73: =I67-I71-I72 -> 0 | J73: =J67-J71-J72 -> 0 | K73: =K67-K71-K72 -> 0 | ... CI73: =CI67-CI71-CI72 -> 1590.6
A74: Coste Total Empresa (OPEX) | B74: EUR | D74: =D67+D70 -> 0 | E74: =E67+E70 -> 0 | F74: =F67+F70 -> 0 | G74: =G67+G70 -> 0 | H74: =H67+H70 -> 0 | I74: =I67+I70 -> 0 | J74: =J67+J70 -> 0 | K74: =K67+K70 -> 0 | ... CI74: =CI67+CI70 -> 2642
A76: Salario Ordinario Mensual | B76: EUR | C76: ='1_PANEL_CONTROL'!$C$45 -> 30000 | D76: =IF(D$8>='1_PANEL_CONTROL'!$D$45, '1_PANEL_CONTROL'!$C$45/'1_PANEL_CONTROL'!$C$32, 0) -> 0 | E76: =IF(E$8>='1_PANEL_CONTROL'!$D$45, '1_PANEL_CONTROL'!$C$45/'1_PANEL_CONTROL'!$C$32, 0) -> 0 | F76: =IF(F$8>='1_PANEL_CONTROL'!$D$45, '1_PANEL_CONTROL'!$C$45/'1_PANEL_CONTROL'!$C$32, 0) -> 0 | G76: =IF(G$8>='1_PANEL_CONTROL'!$D$45, '1_PANEL_CONTROL'!$C$45/'1_PANEL_CONTROL'!$C$32, 0) -> 0 | H76: =IF(H$8>='1_PANEL_CONTROL'!$D$45, '1_PANEL_CONTROL'!$C$45/'1_PANEL_CONTROL'!$C$32, 0) -> 0 | I76: =IF(I$8>='1_PANEL_CONTROL'!$D$45, '1_PANEL_CONTROL'!$C$45/'1_PANEL_CONTROL'!$C$32, 0) -> 0 | J76: =IF(J$8>='1_PANEL_CONTROL'!$D$45, '1_PANEL_CONTROL'!$C$45/'1_PANEL_CONTROL'!$C$32, 0) -> 0 | K76: =IF(K$8>='1_PANEL_CONTROL'!$D$45, '1_PANEL_CONTROL'!$C$45/'1_PANEL_CONTROL'!$C$32, 0) -> 0 | ... CI76: =IF(CI$8>='1_PANEL_CONTROL'!$D$45, '1_PANEL_CONTROL'!$C$45/'1_PANEL_CONTROL'!$C$32, 0) -> 2500
A77: Pagas Extraordinarias | B77: EUR | D77: =IF(D$8>='1_PANEL_CONTROL'!$D$45, IF('1_PANEL_CONTROL'!$C$32=14, IF(OR(MOD(D$8,12)=6, MOD(D$8,12)=0), '1_PANEL_CONTROL'!$C$45/14, 0), 0), 0) -> 0 | E77: =IF(E$8>='1_PANEL_CONTROL'!$D$45, IF('1_PANEL_CONTROL'!$C$32=14, IF(OR(MOD(E$8,12)=6, MOD(E$8,12)=0), '1_PANEL_CONTROL'!$C$45/14, 0), 0), 0) -> 0 | F77: =IF(F$8>='1_PANEL_CONTROL'!$D$45, IF('1_PANEL_CONTROL'!$C$32=14, IF(OR(MOD(F$8,12)=6, MOD(F$8,12)=0), '1_PANEL_CONTROL'!$C$45/14, 0), 0), 0) -> 0 | G77: =IF(G$8>='1_PANEL_CONTROL'!$D$45, IF('1_PANEL_CONTROL'!$C$32=14, IF(OR(MOD(G$8,12)=6, MOD(G$8,12)=0), '1_PANEL_CONTROL'!$C$45/14, 0), 0), 0) -> 0 | H77: =IF(H$8>='1_PANEL_CONTROL'!$D$45, IF('1_PANEL_CONTROL'!$C$32=14, IF(OR(MOD(H$8,12)=6, MOD(H$8,12)=0), '1_PANEL_CONTROL'!$C$45/14, 0), 0), 0) -> 0 | I77: =IF(I$8>='1_PANEL_CONTROL'!$D$45, IF('1_PANEL_CONTROL'!$C$32=14, IF(OR(MOD(I$8,12)=6, MOD(I$8,12)=0), '1_PANEL_CONTROL'!$C$45/14, 0), 0), 0) -> 0 | J77: =IF(J$8>='1_PANEL_CONTROL'!$D$45, IF('1_PANEL_CONTROL'!$C$32=14, IF(OR(MOD(J$8,12)=6, MOD(J$8,12)=0), '1_PANEL_CONTROL'!$C$45/14, 0), 0), 0) -> 0 | K77: =IF(K$8>='1_PANEL_CONTROL'!$D$45, IF('1_PANEL_CONTROL'!$C$32=14, IF(OR(MOD(K$8,12)=6, MOD(K$8,12)=0), '1_PANEL_CONTROL'!$C$45/14, 0), 0), 0) -> 0 | ... CI77: =IF(CI$8>='1_PANEL_CONTROL'!$D$45, IF('1_PANEL_CONTROL'!$C$32=14, IF(OR(MOD(CI$8,12)=6, MOD(CI$8,12)=0), '1_PANEL_CONTROL'!$C$45/14, 0), 0), 0) -> 0
A78: Sueldo Bruto Devengado | B78: EUR | D78: =D76+D77 -> 0 | E78: =E76+E77 -> 0 | F78: =F76+F77 -> 0 | G78: =G76+G77 -> 0 | H78: =H76+H77 -> 0 | I78: =I76+I77 -> 0 | J78: =J76+J77 -> 0 | K78: =K76+K77 -> 0 | ... CI78: =CI76+CI77 -> 2500
A79: Base de Cotización SS (BCCC) | B79: EUR | D79: =IF(D$8>='1_PANEL_CONTROL'!$D$45, '1_PANEL_CONTROL'!$C$45/12, 0) -> 0 | E79: =IF(E$8>='1_PANEL_CONTROL'!$D$45, '1_PANEL_CONTROL'!$C$45/12, 0) -> 0 | F79: =IF(F$8>='1_PANEL_CONTROL'!$D$45, '1_PANEL_CONTROL'!$C$45/12, 0) -> 0 | G79: =IF(G$8>='1_PANEL_CONTROL'!$D$45, '1_PANEL_CONTROL'!$C$45/12, 0) -> 0 | H79: =IF(H$8>='1_PANEL_CONTROL'!$D$45, '1_PANEL_CONTROL'!$C$45/12, 0) -> 0 | I79: =IF(I$8>='1_PANEL_CONTROL'!$D$45, '1_PANEL_CONTROL'!$C$45/12, 0) -> 0 | J79: =IF(J$8>='1_PANEL_CONTROL'!$D$45, '1_PANEL_CONTROL'!$C$45/12, 0) -> 0 | K79: =IF(K$8>='1_PANEL_CONTROL'!$D$45, '1_PANEL_CONTROL'!$C$45/12, 0) -> 0 | ... CI79: =IF(CI$8>='1_PANEL_CONTROL'!$D$45, '1_PANEL_CONTROL'!$C$45/12, 0) -> 2500
A80: Base Cotización Capped | B80: EUR | D80: =IF(D$8>='1_PANEL_CONTROL'!$D$45, MIN(MAX(D79, $D$6), $D$5), 0) -> 0 | E80: =IF(E$8>='1_PANEL_CONTROL'!$D$45, MIN(MAX(E79, $D$6), $D$5), 0) -> 0 | F80: =IF(F$8>='1_PANEL_CONTROL'!$D$45, MIN(MAX(F79, $D$6), $D$5), 0) -> 0 | G80: =IF(G$8>='1_PANEL_CONTROL'!$D$45, MIN(MAX(G79, $D$6), $D$5), 0) -> 0 | H80: =IF(H$8>='1_PANEL_CONTROL'!$D$45, MIN(MAX(H79, $D$6), $D$5), 0) -> 0 | I80: =IF(I$8>='1_PANEL_CONTROL'!$D$45, MIN(MAX(I79, $D$6), $D$5), 0) -> 0 | J80: =IF(J$8>='1_PANEL_CONTROL'!$D$45, MIN(MAX(J79, $D$6), $D$5), 0) -> 0 | K80: =IF(K$8>='1_PANEL_CONTROL'!$D$45, MIN(MAX(K79, $D$6), $D$5), 0) -> 0 | ... CI80: =IF(CI$8>='1_PANEL_CONTROL'!$D$45, MIN(MAX(CI79, $D$6), $D$5), 0) -> 2500
A81: SS Empresa | B81: EUR | D81: =D80*$B$5 -> 0 | E81: =E80*$B$5 -> 0 | F81: =F80*$B$5 -> 0 | G81: =G80*$B$5 -> 0 | H81: =H80*$B$5 -> 0 | I81: =I80*$B$5 -> 0 | J81: =J80*$B$5 -> 0 | K81: =K80*$B$5 -> 0 | ... CI81: =CI80*$B$5 -> 802.5
A82: SS Empleado | B82: EUR | D82: =D80*$B$6 -> 0 | E82: =E80*$B$6 -> 0 | F82: =F80*$B$6 -> 0 | G82: =G80*$B$6 -> 0 | H82: =H80*$B$6 -> 0 | I82: =I80*$B$6 -> 0 | J82: =J80*$B$6 -> 0 | K82: =K80*$B$6 -> 0 | ... CI82: =CI80*$B$6 -> 161.75
A83: Retención IRPF | B83: EUR | D83: =D78*'1_PANEL_CONTROL'!$E$45 -> 0 | E83: =E78*'1_PANEL_CONTROL'!$E$45 -> 0 | F83: =F78*'1_PANEL_CONTROL'!$E$45 -> 0 | G83: =G78*'1_PANEL_CONTROL'!$E$45 -> 0 | H83: =H78*'1_PANEL_CONTROL'!$E$45 -> 0 | I83: =I78*'1_PANEL_CONTROL'!$E$45 -> 0 | J83: =J78*'1_PANEL_CONTROL'!$E$45 -> 0 | K83: =K78*'1_PANEL_CONTROL'!$E$45 -> 0 | ... CI83: =CI78*'1_PANEL_CONTROL'!$E$45 -> 375
A84: Salario Neto Mensual | B84: EUR | D84: =D78-D82-D83 -> 0 | E84: =E78-E82-E83 -> 0 | F84: =F78-F82-F83 -> 0 | G84: =G78-G82-G83 -> 0 | H84: =H78-H82-H83 -> 0 | I84: =I78-I82-I83 -> 0 | J84: =J78-J82-J83 -> 0 | K84: =K78-K82-K83 -> 0 | ... CI84: =CI78-CI82-CI83 -> 1963.25
A85: Coste Total Empresa (OPEX) | B85: EUR | D85: =D78+D81 -> 0 | E85: =E78+E81 -> 0 | F85: =F78+F81 -> 0 | G85: =G78+G81 -> 0 | H85: =H78+H81 -> 0 | I85: =I78+I81 -> 0 | J85: =J78+J81 -> 0 | K85: =K78+K81 -> 0 | ... CI85: =CI78+CI81 -> 3302.5
A87: Salario Ordinario Mensual | B87: EUR | C87: ='1_PANEL_CONTROL'!$C$46 -> 28000 | D87: =IF(D$8>='1_PANEL_CONTROL'!$D$46, '1_PANEL_CONTROL'!$C$46/'1_PANEL_CONTROL'!$C$32, 0) -> 0 | E87: =IF(E$8>='1_PANEL_CONTROL'!$D$46, '1_PANEL_CONTROL'!$C$46/'1_PANEL_CONTROL'!$C$32, 0) -> 0 | F87: =IF(F$8>='1_PANEL_CONTROL'!$D$46, '1_PANEL_CONTROL'!$C$46/'1_PANEL_CONTROL'!$C$32, 0) -> 0 | G87: =IF(G$8>='1_PANEL_CONTROL'!$D$46, '1_PANEL_CONTROL'!$C$46/'1_PANEL_CONTROL'!$C$32, 0) -> 0 | H87: =IF(H$8>='1_PANEL_CONTROL'!$D$46, '1_PANEL_CONTROL'!$C$46/'1_PANEL_CONTROL'!$C$32, 0) -> 0 | I87: =IF(I$8>='1_PANEL_CONTROL'!$D$46, '1_PANEL_CONTROL'!$C$46/'1_PANEL_CONTROL'!$C$32, 0) -> 0 | J87: =IF(J$8>='1_PANEL_CONTROL'!$D$46, '1_PANEL_CONTROL'!$C$46/'1_PANEL_CONTROL'!$C$32, 0) -> 0 | K87: =IF(K$8>='1_PANEL_CONTROL'!$D$46, '1_PANEL_CONTROL'!$C$46/'1_PANEL_CONTROL'!$C$32, 0) -> 0 | ... CI87: =IF(CI$8>='1_PANEL_CONTROL'!$D$46, '1_PANEL_CONTROL'!$C$46/'1_PANEL_CONTROL'!$C$32, 0) -> 2333.3333
A88: Pagas Extraordinarias | B88: EUR | D88: =IF(D$8>='1_PANEL_CONTROL'!$D$46, IF('1_PANEL_CONTROL'!$C$32=14, IF(OR(MOD(D$8,12)=6, MOD(D$8,12)=0), '1_PANEL_CONTROL'!$C$46/14, 0), 0), 0) -> 0 | E88: =IF(E$8>='1_PANEL_CONTROL'!$D$46, IF('1_PANEL_CONTROL'!$C$32=14, IF(OR(MOD(E$8,12)=6, MOD(E$8,12)=0), '1_PANEL_CONTROL'!$C$46/14, 0), 0), 0) -> 0 | F88: =IF(F$8>='1_PANEL_CONTROL'!$D$46, IF('1_PANEL_CONTROL'!$C$32=14, IF(OR(MOD(F$8,12)=6, MOD(F$8,12)=0), '1_PANEL_CONTROL'!$C$46/14, 0), 0), 0) -> 0 | G88: =IF(G$8>='1_PANEL_CONTROL'!$D$46, IF('1_PANEL_CONTROL'!$C$32=14, IF(OR(MOD(G$8,12)=6, MOD(G$8,12)=0), '1_PANEL_CONTROL'!$C$46/14, 0), 0), 0) -> 0 | H88: =IF(H$8>='1_PANEL_CONTROL'!$D$46, IF('1_PANEL_CONTROL'!$C$32=14, IF(OR(MOD(H$8,12)=6, MOD(H$8,12)=0), '1_PANEL_CONTROL'!$C$46/14, 0), 0), 0) -> 0 | I88: =IF(I$8>='1_PANEL_CONTROL'!$D$46, IF('1_PANEL_CONTROL'!$C$32=14, IF(OR(MOD(I$8,12)=6, MOD(I$8,12)=0), '1_PANEL_CONTROL'!$C$46/14, 0), 0), 0) -> 0 | J88: =IF(J$8>='1_PANEL_CONTROL'!$D$46, IF('1_PANEL_CONTROL'!$C$32=14, IF(OR(MOD(J$8,12)=6, MOD(J$8,12)=0), '1_PANEL_CONTROL'!$C$46/14, 0), 0), 0) -> 0 | K88: =IF(K$8>='1_PANEL_CONTROL'!$D$46, IF('1_PANEL_CONTROL'!$C$32=14, IF(OR(MOD(K$8,12)=6, MOD(K$8,12)=0), '1_PANEL_CONTROL'!$C$46/14, 0), 0), 0) -> 0 | ... CI88: =IF(CI$8>='1_PANEL_CONTROL'!$D$46, IF('1_PANEL_CONTROL'!$C$32=14, IF(OR(MOD(CI$8,12)=6, MOD(CI$8,12)=0), '1_PANEL_CONTROL'!$C$46/14, 0), 0), 0) -> 0
A89: Sueldo Bruto Devengado | B89: EUR | D89: =D87+D88 -> 0 | E89: =E87+E88 -> 0 | F89: =F87+F88 -> 0 | G89: =G87+G88 -> 0 | H89: =H87+H88 -> 0 | I89: =I87+I88 -> 0 | J89: =J87+J88 -> 0 | K89: =K87+K88 -> 0 | ... CI89: =CI87+CI88 -> 2333.3333
A90: Base de Cotización SS (BCCC) | B90: EUR | D90: =IF(D$8>='1_PANEL_CONTROL'!$D$46, '1_PANEL_CONTROL'!$C$46/12, 0) -> 0 | E90: =IF(E$8>='1_PANEL_CONTROL'!$D$46, '1_PANEL_CONTROL'!$C$46/12, 0) -> 0 | F90: =IF(F$8>='1_PANEL_CONTROL'!$D$46, '1_PANEL_CONTROL'!$C$46/12, 0) -> 0 | G90: =IF(G$8>='1_PANEL_CONTROL'!$D$46, '1_PANEL_CONTROL'!$C$46/12, 0) -> 0 | H90: =IF(H$8>='1_PANEL_CONTROL'!$D$46, '1_PANEL_CONTROL'!$C$46/12, 0) -> 0 | I90: =IF(I$8>='1_PANEL_CONTROL'!$D$46, '1_PANEL_CONTROL'!$C$46/12, 0) -> 0 | J90: =IF(J$8>='1_PANEL_CONTROL'!$D$46, '1_PANEL_CONTROL'!$C$46/12, 0) -> 0 | K90: =IF(K$8>='1_PANEL_CONTROL'!$D$46, '1_PANEL_CONTROL'!$C$46/12, 0) -> 0 | ... CI90: =IF(CI$8>='1_PANEL_CONTROL'!$D$46, '1_PANEL_CONTROL'!$C$46/12, 0) -> 2333.3333
A91: Base Cotización Capped | B91: EUR | D91: =IF(D$8>='1_PANEL_CONTROL'!$D$46, MIN(MAX(D90, $D$6), $D$5), 0) -> 0 | E91: =IF(E$8>='1_PANEL_CONTROL'!$D$46, MIN(MAX(E90, $D$6), $D$5), 0) -> 0 | F91: =IF(F$8>='1_PANEL_CONTROL'!$D$46, MIN(MAX(F90, $D$6), $D$5), 0) -> 0 | G91: =IF(G$8>='1_PANEL_CONTROL'!$D$46, MIN(MAX(G90, $D$6), $D$5), 0) -> 0 | H91: =IF(H$8>='1_PANEL_CONTROL'!$D$46, MIN(MAX(H90, $D$6), $D$5), 0) -> 0 | I91: =IF(I$8>='1_PANEL_CONTROL'!$D$46, MIN(MAX(I90, $D$6), $D$5), 0) -> 0 | J91: =IF(J$8>='1_PANEL_CONTROL'!$D$46, MIN(MAX(J90, $D$6), $D$5), 0) -> 0 | K91: =IF(K$8>='1_PANEL_CONTROL'!$D$46, MIN(MAX(K90, $D$6), $D$5), 0) -> 0 | ... CI91: =IF(CI$8>='1_PANEL_CONTROL'!$D$46, MIN(MAX(CI90, $D$6), $D$5), 0) -> 2333.3333
A92: SS Empresa | B92: EUR | D92: =D91*$B$5 -> 0 | E92: =E91*$B$5 -> 0 | F92: =F91*$B$5 -> 0 | G92: =G91*$B$5 -> 0 | H92: =H91*$B$5 -> 0 | I92: =I91*$B$5 -> 0 | J92: =J91*$B$5 -> 0 | K92: =K91*$B$5 -> 0 | ... CI92: =CI91*$B$5 -> 749
A93: SS Empleado | B93: EUR | D93: =D91*$B$6 -> 0 | E93: =E91*$B$6 -> 0 | F93: =F91*$B$6 -> 0 | G93: =G91*$B$6 -> 0 | H93: =H91*$B$6 -> 0 | I93: =I91*$B$6 -> 0 | J93: =J91*$B$6 -> 0 | K93: =K91*$B$6 -> 0 | ... CI93: =CI91*$B$6 -> 150.96667
A94: Retención IRPF | B94: EUR | D94: =D89*'1_PANEL_CONTROL'!$E$46 -> 0 | E94: =E89*'1_PANEL_CONTROL'!$E$46 -> 0 | F94: =F89*'1_PANEL_CONTROL'!$E$46 -> 0 | G94: =G89*'1_PANEL_CONTROL'!$E$46 -> 0 | H94: =H89*'1_PANEL_CONTROL'!$E$46 -> 0 | I94: =I89*'1_PANEL_CONTROL'!$E$46 -> 0 | J94: =J89*'1_PANEL_CONTROL'!$E$46 -> 0 | K94: =K89*'1_PANEL_CONTROL'!$E$46 -> 0 | ... CI94: =CI89*'1_PANEL_CONTROL'!$E$46 -> 350
A95: Salario Neto Mensual | B95: EUR | D95: =D89-D93-D94 -> 0 | E95: =E89-E93-E94 -> 0 | F95: =F89-F93-F94 -> 0 | G95: =G89-G93-G94 -> 0 | H95: =H89-H93-H94 -> 0 | I95: =I89-I93-I94 -> 0 | J95: =J89-J93-J94 -> 0 | K95: =K89-K93-K94 -> 0 | ... CI95: =CI89-CI93-CI94 -> 1832.3667
A96: Coste Total Empresa (OPEX) | B96: EUR | D96: =D89+D92 -> 0 | E96: =E89+E92 -> 0 | F96: =F89+F92 -> 0 | G96: =G89+G92 -> 0 | H96: =H89+H92 -> 0 | I96: =I89+I92 -> 0 | J96: =J89+J92 -> 0 | K96: =K89+K92 -> 0 | ... CI96: =CI89+CI92 -> 3082.3333
A98: TOTALES DE PERSONAL CONSOLIDADOS
A99: Salario Ordinario Mensual Total | B99: EUR | D99: =SUM(D10,D21,D32,D43,D54,D65,D76,D87) -> 6000 | E99: =SUM(E10,E21,E32,E43,E54,E65,E76,E87) -> 6000 | F99: =SUM(F10,F21,F32,F43,F54,F65,F76,F87) -> 6000 | G99: =SUM(G10,G21,G32,G43,G54,G65,G76,G87) -> 6000 | H99: =SUM(H10,H21,H32,H43,H54,H65,H76,H87) -> 6000 | I99: =SUM(I10,I21,I32,I43,I54,I65,I76,I87) -> 6000 | J99: =SUM(J10,J21,J32,J43,J54,J65,J76,J87) -> 6000 | K99: =SUM(K10,K21,K32,K43,K54,K65,K76,K87) -> 6000 | ... CI99: =SUM(CI10,CI21,CI32,CI43,CI54,CI65,CI76,CI87) -> 24583.333
A100: Pagas Extraordinarias Total | B100: EUR | D100: =SUM(D11,D22,D33,D44,D55,D66,D77,D88) -> 0 | E100: =SUM(E11,E22,E33,E44,E55,E66,E77,E88) -> 0 | F100: =SUM(F11,F22,F33,F44,F55,F66,F77,F88) -> 0 | G100: =SUM(G11,G22,G33,G44,G55,G66,G77,G88) -> 0 | H100: =SUM(H11,H22,H33,H44,H55,H66,H77,H88) -> 0 | I100: =SUM(I11,I22,I33,I44,I55,I66,I77,I88) -> 0 | J100: =SUM(J11,J22,J33,J44,J55,J66,J77,J88) -> 0 | K100: =SUM(K11,K22,K33,K44,K55,K66,K77,K88) -> 0 | ... CI100: =SUM(CI11,CI22,CI33,CI44,CI55,CI66,CI77,CI88) -> 0
A101: Sueldo Bruto Devengado Total | B101: EUR | D101: =SUM(D12,D23,D34,D45,D56,D67,D78,D89) -> 6000 | E101: =SUM(E12,E23,E34,E45,E56,E67,E78,E89) -> 6000 | F101: =SUM(F12,F23,F34,F45,F56,F67,F78,F89) -> 6000 | G101: =SUM(G12,G23,G34,G45,G56,G67,G78,G89) -> 6000 | H101: =SUM(H12,H23,H34,H45,H56,H67,H78,H89) -> 6000 | I101: =SUM(I12,I23,I34,I45,I56,I67,I78,I89) -> 6000 | J101: =SUM(J12,J23,J34,J45,J56,J67,J78,J89) -> 6000 | K101: =SUM(K12,K23,K34,K45,K56,K67,K78,K89) -> 6000 | ... CI101: =SUM(CI12,CI23,CI34,CI45,CI56,CI67,CI78,CI89) -> 24583.333
A102: Base de Cotización SS (BCCC) Total | B102: EUR | D102: =SUM(D13,D24,D35,D46,D57,D68,D79,D90) -> 6000 | E102: =SUM(E13,E24,E35,E46,E57,E68,E79,E90) -> 6000 | F102: =SUM(F13,F24,F35,F46,F57,F68,F79,F90) -> 6000 | G102: =SUM(G13,G24,G35,G46,G57,G68,G79,G90) -> 6000 | H102: =SUM(H13,H24,H35,H46,H57,H68,H79,H90) -> 6000 | I102: =SUM(I13,I24,I35,I46,I57,I68,I79,I90) -> 6000 | J102: =SUM(J13,J24,J35,J46,J57,J68,J79,J90) -> 6000 | K102: =SUM(K13,K24,K35,K46,K57,K68,K79,K90) -> 6000 | ... CI102: =SUM(CI13,CI24,CI35,CI46,CI57,CI68,CI79,CI90) -> 24583.333
A103: Base Cotización Capped Total | B103: EUR | D103: =SUM(D14,D25,D36,D47,D58,D69,D80,D91) -> 6000 | E103: =SUM(E14,E25,E36,E47,E58,E69,E80,E91) -> 6000 | F103: =SUM(F14,F25,F36,F47,F58,F69,F80,F91) -> 6000 | G103: =SUM(G14,G25,G36,G47,G58,G69,G80,G91) -> 6000 | H103: =SUM(H14,H25,H36,H47,H58,H69,H80,H91) -> 6000 | I103: =SUM(I14,I25,I36,I47,I58,I69,I80,I91) -> 6000 | J103: =SUM(J14,J25,J36,J47,J58,J69,J80,J91) -> 6000 | K103: =SUM(K14,K25,K36,K47,K58,K69,K80,K91) -> 6000 | ... CI103: =SUM(CI14,CI25,CI36,CI47,CI58,CI69,CI80,CI91) -> 24583.333
A104: Seguridad Social a Cargo Empresa Total | B104: EUR | D104: =SUM(D15,D26,D37,D48,D59,D70,D81,D92) -> 1794.76 | E104: =SUM(E15,E26,E37,E48,E59,E70,E81,E92) -> 1794.76 | F104: =SUM(F15,F26,F37,F48,F59,F70,F81,F92) -> 1794.76 | G104: =SUM(G15,G26,G37,G48,G59,G70,G81,G92) -> 1794.76 | H104: =SUM(H15,H26,H37,H48,H59,H70,H81,H92) -> 1794.76 | I104: =SUM(I15,I26,I37,I48,I59,I70,I81,I92) -> 1794.76 | J104: =SUM(J15,J26,J37,J48,J59,J70,J81,J92) -> 1794.76 | K104: =SUM(K15,K26,K37,K48,K59,K70,K81,K92) -> 1794.76 | ... CI104: =SUM(CI15,CI26,CI37,CI48,CI59,CI70,CI81,CI92) -> 5192.01
A105: Seguridad Social a Cargo Empleado Total | B105: EUR | D105: =SUM(D16,D27,D38,D49,D60,D71,D82,D93) -> 0 | E105: =SUM(E16,E27,E38,E49,E60,E71,E82,E93) -> 0 | F105: =SUM(F16,F27,F38,F49,F60,F71,F82,F93) -> 0 | G105: =SUM(G16,G27,G38,G49,G60,G71,G82,G93) -> 0 | H105: =SUM(H16,H27,H38,H49,H60,H71,H82,H93) -> 0 | I105: =SUM(I16,I27,I38,I49,I60,I71,I82,I93) -> 0 | J105: =SUM(J16,J27,J38,J49,J60,J71,J82,J93) -> 0 | K105: =SUM(K16,K27,K38,K49,K60,K71,K82,K93) -> 0 | ... CI105: =SUM(CI16,CI27,CI38,CI49,CI60,CI71,CI82,CI93) -> 684.74167
A106: Retención IRPF Total | B106: EUR | D106: =SUM(D17,D28,D39,D50,D61,D72,D83,D94) -> 900 | E106: =SUM(E17,E28,E39,E50,E61,E72,E83,E94) -> 900 | F106: =SUM(F17,F28,F39,F50,F61,F72,F83,F94) -> 900 | G106: =SUM(G17,G28,G39,G50,G61,G72,G83,G94) -> 900 | H106: =SUM(H17,H28,H39,H50,H61,H72,H83,H94) -> 900 | I106: =SUM(I17,I28,I39,I50,I61,I72,I83,I94) -> 900 | J106: =SUM(J17,J28,J39,J50,J61,J72,J83,J94) -> 900 | K106: =SUM(K17,K28,K39,K50,K61,K72,K83,K94) -> 900 | ... CI106: =SUM(CI17,CI28,CI39,CI50,CI61,CI72,CI83,CI94) -> 3667.5
A107: Salario Neto Mensual Total | B107: EUR | D107: =SUM(D18,D29,D40,D51,D62,D73,D84,D95) -> 5100 | E107: =SUM(E18,E29,E40,E51,E62,E73,E84,E95) -> 5100 | F107: =SUM(F18,F29,F40,F51,F62,F73,F84,F95) -> 5100 | G107: =SUM(G18,G29,G40,G51,G62,G73,G84,G95) -> 5100 | H107: =SUM(H18,H29,H40,H51,H62,H73,H84,H95) -> 5100 | I107: =SUM(I18,I29,I40,I51,I62,I73,I84,I95) -> 5100 | J107: =SUM(J18,J29,J40,J51,J62,J73,J84,J95) -> 5100 | K107: =SUM(K18,K29,K40,K51,K62,K73,K84,K95) -> 5100 | ... CI107: =SUM(CI18,CI29,CI40,CI51,CI62,CI73,CI84,CI95) -> 20231.092
A108: COSTE TOTAL EMPRESA (OPEX PERSONAL) | B108: EUR | D108: =SUM(D19,D30,D41,D52,D63,D74,D85,D96) -> 7794.76 | E108: =SUM(E19,E30,E41,E52,E63,E74,E85,E96) -> 7794.76 | F108: =SUM(F19,F30,F41,F52,F63,F74,F85,F96) -> 7794.76 | G108: =SUM(G19,G30,G41,G52,G63,G74,G85,G96) -> 7794.76 | H108: =SUM(H19,H30,H41,H52,H63,H74,H85,H96) -> 7794.76 | I108: =SUM(I19,I30,I41,I52,I63,I74,I85,I96) -> 7794.76 | J108: =SUM(J19,J30,J41,J52,J63,J74,J85,J96) -> 7794.76 | K108: =SUM(K19,K30,K41,K52,K63,K74,K85,K96) -> 7794.76 | ... CI108: =SUM(CI19,CI30,CI41,CI52,CI63,CI74,CI85,CI96) -> 29775.343
A110: Resumen de Costes del Personal (Año 1)
A111: Rol / Puesto | B111: Coste Año 1 (EUR)
...

Sheet 8_COSTES_OPEX
A4: GASTOS OPERATIVOS DE EXPLOTACIÓN (SG&A)
A5: Escenario Activo: | B5: =CHOOSE('1_PANEL_CONTROL'!$C$4, "🔴 1: NEGATIVO", "🟡 2: EQUILIBRIO", "🟢 3: POSITIVO") -> 🟡 2: EQUILIBRIO | D5: =CHOOSE('1_PANEL_CONTROL'!$C$4, "[NEGATIVO] GASTOS DE EXPLOTACIÓN (OPEX). Inversión en Ads de " & TEXT('8_COSTES_OPEX'!O20, "#.##0 €") & " en el mes 12 y total de OPEX recurrente mensual de " & TEXT('8_COSTES_OPEX'!O39, "#.##0 €") & ".", "[EQUILIBRIO] GASTOS DE EXPLOTACIÓN (OPEX). El alquiler Aticco Coworking representa " & TEXT('8_COSTES_OPEX'!D11, "#.##0 €") & " y las licencias SEO Semrush suponen " & TEXT('8_COSTES_OPEX'!D24, "#.##0 €") & " mensuales.", "[POSITIVO] GASTOS DE EXPLOTACIÓN (OPEX). Alta inversión comercial en marketing digital para captar tráfico, sumando un OPEX acumulado en Año 1 de " & TEXT(SUM('8_COSTES_OPEX'!$D$39:$O$39), "#.##0 €") & ".") -> [EQUILIBRIO] GASTOS DE EXPLOTACIÓN (OPEX). El alquiler Aticco Coworking representa 2.160 € y las licencias SEO Semrush suponen 250 € mensuales.
A7: Partida Operativa | B7: Unidad | C7: Fórmula / Tipo | D7: Ene-26 | E7: Feb-26 | F7: Mar-26 | G7: Abr-26 | H7: May-26 | I7: Jun-26 | J7: Jul-26 | K7: Ago-26 | L7: Sep-26 | M7: Oct-26 | N7: Nov-26 | O7: Dic-26 | P7: Ene-27 | Q7: Feb-27 | R7: Mar-27 | S7: Abr-27 | T7: May-27 | U7: Jun-27 | V7: Jul-27 | W7: Ago-27 | X7: Sep-27 | Y7: Oct-27 | Z7: Nov-27 | AA7: Dic-27 | AB7: Ene-28 | AC7: Feb-28 | AD7: Mar-28 | AE7: Abr-28 | AF7: May-28 | AG7: Jun-28 | AH7: Jul-28 | AI7: Ago-28 | AJ7: Sep-28 | AK7: Oct-28 | AL7: Nov-28 | AM7: Dic-28 | AN7: Ene-29 | AO7: Feb-29 | AP7: Mar-29 | AQ7: Abr-29 | AR7: May-29 | AS7: Jun-29 | AT7: Jul-29 | AU7: Ago-29 | AV7: Sep-29 | AW7: Oct-29 | AX7: Nov-29 | AY7: Dic-29 | AZ7: Ene-30 | BA7: Feb-30 | BB7: Mar-30 | BC7: Abr-30 | BD7: May-30 | BE7: Jun-30 | BF7: Jul-30 | BG7: Ago-30 | BH7: Sep-30 | BI7: Oct-30 | BJ7: Nov-30 | BK7: Dic-30 | BL7: Ene-31 | BM7: Feb-31 | BN7: Mar-31 | BO7: Abr-31 | BP7: May-31 | BQ7: Jun-31 | BR7: Jul-31 | BS7: Ago-31 | BT7: Sep-31 | BU7: Oct-31 | BV7: Nov-31 | BW7: Dic-31 | BX7: Ene-32 | BY7: Feb-32 | BZ7: Mar-32 | CA7: Abr-32 | CB7: May-32 | CC7: Jun-32 | CD7: Jul-32 | CE7: Ago-32 | CF7: Sep-32 | CG7: Oct-32 | CH7: Nov-32 | CI7: Dic-32
A10: Gastos de Personal & Cargas | B10: EUR | C10: Personal: Link a '7_EQUIPO_RRHH'!Row 108 | D10: ='7_EQUIPO_RRHH'!D108 -> 7794.76 | E10: ='7_EQUIPO_RRHH'!E108 -> 7794.76 | F10: ='7_EQUIPO_RRHH'!F108 -> 7794.76 | G10: ='7_EQUIPO_RRHH'!G108 -> 7794.76 | H10: ='7_EQUIPO_RRHH'!H108 -> 7794.76 | I10: ='7_EQUIPO_RRHH'!I108 -> 7794.76 | J10: ='7_EQUIPO_RRHH'!J108 -> 7794.76 | K10: ='7_EQUIPO_RRHH'!K108 -> 7794.76 | ... CI10: ='7_EQUIPO_RRHH'!CI108 -> 29775.343
A11: Alquiler Coworking Aticco Bogatell | B11: EUR | C11: Fijo: '1_PANEL_CONTROL'!$C$49 | D11: ='1_PANEL_CONTROL'!$C$49 -> 2160 | E11: ='1_PANEL_CONTROL'!$C$49 -> 2160 | F11: ='1_PANEL_CONTROL'!$C$49 -> 2160 | G11: ='1_PANEL_CONTROL'!$C$49 -> 2160 | H11: ='1_PANEL_CONTROL'!$C$49 -> 2160 | I11: ='1_PANEL_CONTROL'!$C$49 -> 2160 | J11: ='1_PANEL_CONTROL'!$C$49 -> 2160 | K11: ='1_PANEL_CONTROL'!$C$49 -> 2160 | ... CI11: ='1_PANEL_CONTROL'!$C$49 -> 2160
A12: Comunicaciones Móviles (Equipo) | B12: EUR | C12: Fijo: '1_PANEL_CONTROL'!$C$50 | D12: ='1_PANEL_CONTROL'!$C$50 -> 100 | E12: ='1_PANEL_CONTROL'!$C$50 -> 100 | F12: ='1_PANEL_CONTROL'!$C$50 -> 100 | G12: ='1_PANEL_CONTROL'!$C$50 -> 100 | H12: ='1_PANEL_CONTROL'!$C$50 -> 100 | I12: ='1_PANEL_CONTROL'!$C$50 -> 100 | J12: ='1_PANEL_CONTROL'!$C$50 -> 100 | K12: ='1_PANEL_CONTROL'!$C$50 -> 100 | ... CI12: ='1_PANEL_CONTROL'!$C$50 -> 100
A13: Licencia ChatGPT Team (IA) | B13: EUR | C13: Fijo: '1_PANEL_CONTROL'!$C$51 | D13: ='1_PANEL_CONTROL'!$C$51 -> 112 | E13: ='1_PANEL_CONTROL'!$C$51 -> 112 | F13: ='1_PANEL_CONTROL'!$C$51 -> 112 | G13: ='1_PANEL_CONTROL'!$C$51 -> 112 | H13: ='1_PANEL_CONTROL'!$C$51 -> 112 | I13: ='1_PANEL_CONTROL'!$C$51 -> 112 | J13: ='1_PANEL_CONTROL'!$C$51 -> 112 | K13: ='1_PANEL_CONTROL'!$C$51 -> 112 | ... CI13: ='1_PANEL_CONTROL'!$C$51 -> 112
A14: Google Workspace | B14: EUR | C14: Fijo: '1_PANEL_CONTROL'!$C$52 | D14: ='1_PANEL_CONTROL'!$C$52 -> 60 | E14: ='1_PANEL_CONTROL'!$C$52 -> 60 | F14: ='1_PANEL_CONTROL'!$C$52 -> 60 | G14: ='1_PANEL_CONTROL'!$C$52 -> 60 | H14: ='1_PANEL_CONTROL'!$C$52 -> 60 | I14: ='1_PANEL_CONTROL'!$C$52 -> 60 | J14: ='1_PANEL_CONTROL'!$C$52 -> 60 | K14: ='1_PANEL_CONTROL'!$C$52 -> 60 | ... CI14: ='1_PANEL_CONTROL'!$C$52 -> 60
A15: HubSpot Sales Hub Professional (CRM) | B15: EUR | C15: Fijo: '1_PANEL_CONTROL'!$C$53 | D15: ='1_PANEL_CONTROL'!$C$53 -> 400 | E15: ='1_PANEL_CONTROL'!$C$53 -> 400 | F15: ='1_PANEL_CONTROL'!$C$53 -> 400 | G15: ='1_PANEL_CONTROL'!$C$53 -> 400 | H15: ='1_PANEL_CONTROL'!$C$53 -> 400 | I15: ='1_PANEL_CONTROL'!$C$53 -> 400 | J15: ='1_PANEL_CONTROL'!$C$53 -> 400 | K15: ='1_PANEL_CONTROL'!$C$53 -> 400 | ... CI15: ='1_PANEL_CONTROL'!$C$53 -> 400
A16: Mixpanel & GA4 Pro | B16: EUR | C16: Fijo: '1_PANEL_CONTROL'!$C$54 | D16: ='1_PANEL_CONTROL'!$C$54 -> 224.4 | E16: ='1_PANEL_CONTROL'!$C$54 -> 224.4 | F16: ='1_PANEL_CONTROL'!$C$54 -> 224.4 | G16: ='1_PANEL_CONTROL'!$C$54 -> 224.4 | H16: ='1_PANEL_CONTROL'!$C$54 -> 224.4 | I16: ='1_PANEL_CONTROL'!$C$54 -> 224.4 | J16: ='1_PANEL_CONTROL'!$C$54 -> 224.4 | K16: ='1_PANEL_CONTROL'!$C$54 -> 224.4 | ... CI16: ='1_PANEL_CONTROL'!$C$54 -> 224.4
A17: n8n Cloud Pro (Automatización) | B17: EUR | C17: Fijo: '1_PANEL_CONTROL'!$C$55 | D17: ='1_PANEL_CONTROL'!$C$55 -> 50 | E17: ='1_PANEL_CONTROL'!$C$55 -> 50 | F17: ='1_PANEL_CONTROL'!$C$55 -> 50 | G17: ='1_PANEL_CONTROL'!$C$55 -> 50 | H17: ='1_PANEL_CONTROL'!$C$55 -> 50 | I17: ='1_PANEL_CONTROL'!$C$55 -> 50 | J17: ='1_PANEL_CONTROL'!$C$55 -> 50 | K17: ='1_PANEL_CONTROL'!$C$55 -> 50 | ... CI17: ='1_PANEL_CONTROL'!$C$55 -> 50
A18: Almacén OhMyBox Poblenou | B18: EUR | C18: Fijo: '1_PANEL_CONTROL'!$C$56 | D18: ='1_PANEL_CONTROL'!$C$56 -> 187 | E18: ='1_PANEL_CONTROL'!$C$56 -> 187 | F18: ='1_PANEL_CONTROL'!$C$56 -> 187 | G18: ='1_PANEL_CONTROL'!$C$56 -> 187 | H18: ='1_PANEL_CONTROL'!$C$56 -> 187 | I18: ='1_PANEL_CONTROL'!$C$56 -> 187 | J18: ='1_PANEL_CONTROL'!$C$56 -> 187 | K18: ='1_PANEL_CONTROL'!$C$56 -> 187 | ... CI18: ='1_PANEL_CONTROL'!$C$56 -> 187
A19: Seguro Stock Póliza OhMyBox | B19: EUR | C19: Fijo: '1_PANEL_CONTROL'!$C$57 | D19: ='1_PANEL_CONTROL'!$C$57 -> 49.5 | E19: ='1_PANEL_CONTROL'!$C$57 -> 49.5 | F19: ='1_PANEL_CONTROL'!$C$57 -> 49.5 | G19: ='1_PANEL_CONTROL'!$C$57 -> 49.5 | H19: ='1_PANEL_CONTROL'!$C$57 -> 49.5 | I19: ='1_PANEL_CONTROL'!$C$57 -> 49.5 | J19: ='1_PANEL_CONTROL'!$C$57 -> 49.5 | K19: ='1_PANEL_CONTROL'!$C$57 -> 49.5 | ... CI19: ='1_PANEL_CONTROL'!$C$57 -> 49.5
A20: Inversión Ads (Meta y TikTok) | B20: EUR | C20: Variable: ='5_DETALLE_INGRESOS'!AdSpend | D20: ='5_DETALLE_INGRESOS'!D13 -> 2955 | E20: ='5_DETALLE_INGRESOS'!E13 -> 2955 | F20: ='5_DETALLE_INGRESOS'!F13 -> 2955 | G20: ='5_DETALLE_INGRESOS'!G13 -> 2955 | H20: ='5_DETALLE_INGRESOS'!H13 -> 2955 | I20: ='5_DETALLE_INGRESOS'!I13 -> 2955 | J20: ='5_DETALLE_INGRESOS'!J13 -> 2955 | K20: ='5_DETALLE_INGRESOS'!K13 -> 2955 | ... CI20: ='5_DETALLE_INGRESOS'!CI13 -> 2955
A21: SEO Frontend Developer (SEO Técnico) | B21: EUR | C21: Fijo: '1_PANEL_CONTROL'!$C$58 | D21: ='1_PANEL_CONTROL'!$C$58 -> 400 | E21: ='1_PANEL_CONTROL'!$C$58 -> 400 | F21: ='1_PANEL_CONTROL'!$C$58 -> 400 | G21: ='1_PANEL_CONTROL'!$C$58 -> 400 | H21: ='1_PANEL_CONTROL'!$C$58 -> 400 | I21: ='1_PANEL_CONTROL'!$C$58 -> 400 | J21: ='1_PANEL_CONTROL'!$C$58 -> 400 | K21: ='1_PANEL_CONTROL'!$C$58 -> 400 | ... CI21: ='1_PANEL_CONTROL'!$C$58 -> 400
A22: Redactor Médico Veterinario (E-E-A-T) | B22: EUR | C22: Fijo: '1_PANEL_CONTROL'!$C$59 | D22: ='1_PANEL_CONTROL'!$C$59 -> 400.05 | E22: ='1_PANEL_CONTROL'!$C$59 -> 400.05 | F22: ='1_PANEL_CONTROL'!$C$59 -> 400.05 | G22: ='1_PANEL_CONTROL'!$C$59 -> 400.05 | H22: ='1_PANEL_CONTROL'!$C$59 -> 400.05 | I22: ='1_PANEL_CONTROL'!$C$59 -> 400.05 | J22: ='1_PANEL_CONTROL'!$C$59 -> 400.05 | K22: ='1_PANEL_CONTROL'!$C$59 -> 400.05 | ... CI22: ='1_PANEL_CONTROL'!$C$59 -> 400.05
A23: Especialista SEO (Linkbuilding) | B23: EUR | C23: Fijo: '1_PANEL_CONTROL'!$C$60 | D23: ='1_PANEL_CONTROL'!$C$60 -> 400.05 | E23: ='1_PANEL_CONTROL'!$C$60 -> 400.05 | F23: ='1_PANEL_CONTROL'!$C$60 -> 400.05 | G23: ='1_PANEL_CONTROL'!$C$60 -> 400.05 | H23: ='1_PANEL_CONTROL'!$C$60 -> 400.05 | I23: ='1_PANEL_CONTROL'!$C$60 -> 400.05 | J23: ='1_PANEL_CONTROL'!$C$60 -> 400.05 | K23: ='1_PANEL_CONTROL'!$C$60 -> 400.05 | ... CI23: ='1_PANEL_CONTROL'!$C$60 -> 400.05
A24: Licencias Herramientas SEO (Semrush) | B24: EUR | C24: Fijo: '1_PANEL_CONTROL'!$C$61 | D24: ='1_PANEL_CONTROL'!$C$61 -> 250 | E24: ='1_PANEL_CONTROL'!$C$61 -> 250 | F24: ='1_PANEL_CONTROL'!$C$61 -> 250 | G24: ='1_PANEL_CONTROL'!$C$61 -> 250 | H24: ='1_PANEL_CONTROL'!$C$61 -> 250 | I24: ='1_PANEL_CONTROL'!$C$61 -> 250 | J24: ='1_PANEL_CONTROL'!$C$61 -> 250 | K24: ='1_PANEL_CONTROL'!$C$61 -> 250 | ... CI24: ='1_PANEL_CONTROL'!$C$61 -> 250
A25: Adquisición de Enlaces y PR (Linkbuilding) | B25: EUR | C25: Variable: '1_PANEL_CONTROL'!$C$62 | D25: ='1_PANEL_CONTROL'!$C$62 -> 550 | E25: ='1_PANEL_CONTROL'!$C$62 -> 550 | F25: ='1_PANEL_CONTROL'!$C$62 -> 550 | G25: ='1_PANEL_CONTROL'!$C$62 -> 550 | H25: ='1_PANEL_CONTROL'!$C$62 -> 550 | I25: ='1_PANEL_CONTROL'!$C$62 -> 550 | J25: ='1_PANEL_CONTROL'!$C$62 -> 550 | K25: ='1_PANEL_CONTROL'!$C$62 -> 550 | ... CI25: ='1_PANEL_CONTROL'!$C$62 -> 550
A26: Dirección de Arte y Creativos Ads | B26: EUR | C26: Fijo: '1_PANEL_CONTROL'!$C$63 | D26: ='1_PANEL_CONTROL'!$C$63 -> 880 | E26: ='1_PANEL_CONTROL'!$C$63 -> 880 | F26: ='1_PANEL_CONTROL'!$C$63 -> 880 | G26: ='1_PANEL_CONTROL'!$C$63 -> 880 | H26: ='1_PANEL_CONTROL'!$C$63 -> 880 | I26: ='1_PANEL_CONTROL'!$C$63 -> 880 | J26: ='1_PANEL_CONTROL'!$C$63 -> 880 | K26: ='1_PANEL_CONTROL'!$C$63 -> 880 | ... CI26: ='1_PANEL_CONTROL'!$C$63 -> 880
A27: Comisiones Influencers (CPA) | B27: EUR | C27: Variable: '1_PANEL_CONTROL'!$C$64 | D27: ='1_PANEL_CONTROL'!$C$64 -> 500 | E27: ='1_PANEL_CONTROL'!$C$64 -> 500 | F27: ='1_PANEL_CONTROL'!$C$64 -> 500 | G27: ='1_PANEL_CONTROL'!$C$64 -> 500 | H27: ='1_PANEL_CONTROL'!$C$64 -> 500 | I27: ='1_PANEL_CONTROL'!$C$64 -> 500 | J27: ='1_PANEL_CONTROL'!$C$64 -> 500 | K27: ='1_PANEL_CONTROL'!$C$64 -> 500 | ... CI27: ='1_PANEL_CONTROL'!$C$64 -> 500
A28: Gestión de Embajadores y RR.PP. | B28: EUR | C28: Fijo: '1_PANEL_CONTROL'!$C$65 | D28: ='1_PANEL_CONTROL'!$C$65 -> 0 | E28: ='1_PANEL_CONTROL'!$C$65 -> 0 | F28: ='1_PANEL_CONTROL'!$C$65 -> 0 | G28: ='1_PANEL_CONTROL'!$C$65 -> 0 | H28: ='1_PANEL_CONTROL'!$C$65 -> 0 | I28: ='1_PANEL_CONTROL'!$C$65 -> 0 | J28: ='1_PANEL_CONTROL'!$C$65 -> 0 | K28: ='1_PANEL_CONTROL'!$C$65 -> 0 | ... CI28: ='1_PANEL_CONTROL'!$C$65 -> 0
A29: Performance Marketing / Trafficker | B29: EUR | C29: Fijo: '1_PANEL_CONTROL'!$C$66 | D29: ='1_PANEL_CONTROL'!$C$66 -> 400 | E29: ='1_PANEL_CONTROL'!$C$66 -> 400 | F29: ='1_PANEL_CONTROL'!$C$66 -> 400 | G29: ='1_PANEL_CONTROL'!$C$66 -> 400 | H29: ='1_PANEL_CONTROL'!$C$66 -> 400 | I29: ='1_PANEL_CONTROL'!$C$66 -> 400 | J29: ='1_PANEL_CONTROL'!$C$66 -> 400 | K29: ='1_PANEL_CONTROL'!$C$66 -> 400 | ... CI29: ='1_PANEL_CONTROL'!$C$66 -> 400
A30: SaaS Vet Dashboard (Interoperabilidad) | B30: EUR | C30: Fijo: '1_PANEL_CONTROL'!$C$67 | D30: ='1_PANEL_CONTROL'!$C$67 -> 50 | E30: ='1_PANEL_CONTROL'!$C$67 -> 50 | F30: ='1_PANEL_CONTROL'!$C$67 -> 50 | G30: ='1_PANEL_CONTROL'!$C$67 -> 50 | H30: ='1_PANEL_CONTROL'!$C$67 -> 50 | I30: ='1_PANEL_CONTROL'!$C$67 -> 50 | J30: ='1_PANEL_CONTROL'!$C$67 -> 50 | K30: ='1_PANEL_CONTROL'!$C$67 -> 50 | ... CI30: ='1_PANEL_CONTROL'!$C$67 -> 50
A31: Remarketing Ads Spend | B31: EUR | C31: Variable: '1_PANEL_CONTROL'!$C$68 | D31: ='1_PANEL_CONTROL'!$C$68 -> 300 | E31: ='1_PANEL_CONTROL'!$C$68 -> 300 | F31: ='1_PANEL_CONTROL'!$C$68 -> 300 | G31: ='1_PANEL_CONTROL'!$C$68 -> 300 | H31: ='1_PANEL_CONTROL'!$C$68 -> 300 | I31: ='1_PANEL_CONTROL'!$C$68 -> 300 | J31: ='1_PANEL_CONTROL'!$C$68 -> 300 | K31: ='1_PANEL_CONTROL'!$C$68 -> 300 | ... CI31: ='1_PANEL_CONTROL'!$C$68 -> 300
A32: Subvención Co-financiada Póliza B2B | B32: EUR | C32: Variable: '1_PANEL_CONTROL'!$C$69 | D32: ='1_PANEL_CONTROL'!$C$69 -> 655 | E32: ='1_PANEL_CONTROL'!$C$69 -> 655 | F32: ='1_PANEL_CONTROL'!$C$69 -> 655 | G32: ='1_PANEL_CONTROL'!$C$69 -> 655 | H32: ='1_PANEL_CONTROL'!$C$69 -> 655 | I32: ='1_PANEL_CONTROL'!$C$69 -> 655 | J32: ='1_PANEL_CONTROL'!$C$69 -> 655 | K32: ='1_PANEL_CONTROL'!$C$69 -> 655 | ... CI32: ='1_PANEL_CONTROL'!$C$69 -> 655
A33: CS B2B Director | B33: EUR | C33: Fijo: '1_PANEL_CONTROL'!$C$70 | D33: ='1_PANEL_CONTROL'!$C$70 -> 400.05 | E33: ='1_PANEL_CONTROL'!$C$70 -> 400.05 | F33: ='1_PANEL_CONTROL'!$C$70 -> 400.05 | G33: ='1_PANEL_CONTROL'!$C$70 -> 400.05 | H33: ='1_PANEL_CONTROL'!$C$70 -> 400.05 | I33: ='1_PANEL_CONTROL'!$C$70 -> 400.05 | J33: ='1_PANEL_CONTROL'!$C$70 -> 400.05 | K33: ='1_PANEL_CONTROL'!$C$70 -> 400.05 | ... CI33: ='1_PANEL_CONTROL'!$C$70 -> 400.05
A34: Especialista Automatización CRM | B34: EUR | C34: Fijo: '1_PANEL_CONTROL'!$C$71 | D34: ='1_PANEL_CONTROL'!$C$71 -> 1028 | E34: ='1_PANEL_CONTROL'!$C$71 -> 1028 | F34: ='1_PANEL_CONTROL'!$C$71 -> 1028 | G34: ='1_PANEL_CONTROL'!$C$71 -> 1028 | H34: ='1_PANEL_CONTROL'!$C$71 -> 1028 | I34: ='1_PANEL_CONTROL'!$C$71 -> 1028 | J34: ='1_PANEL_CONTROL'!$C$71 -> 1028 | K34: ='1_PANEL_CONTROL'!$C$71 -> 1028 | ... CI34: ='1_PANEL_CONTROL'!$C$71 -> 1028
A35: LinkedIn Sales Navigator Advanced | B35: EUR | C35: Fijo: '1_PANEL_CONTROL'!$C$72 | D35: ='1_PANEL_CONTROL'!$C$72 -> 539.96 | E35: ='1_PANEL_CONTROL'!$C$72 -> 539.96 | F35: ='1_PANEL_CONTROL'!$C$72 -> 539.96 | G35: ='1_PANEL_CONTROL'!$C$72 -> 539.96 | H35: ='1_PANEL_CONTROL'!$C$72 -> 539.96 | I35: ='1_PANEL_CONTROL'!$C$72 -> 539.96 | J35: ='1_PANEL_CONTROL'!$C$72 -> 539.96 | K35: ='1_PANEL_CONTROL'!$C$72 -> 539.96 | ... CI35: ='1_PANEL_CONTROL'!$C$72 -> 539.96
A36: Asesoría Fiscal / Contable | B36: EUR | C36: Fijo: '1_PANEL_CONTROL'!$C$73 | D36: ='1_PANEL_CONTROL'!$C$73 -> 150 | E36: ='1_PANEL_CONTROL'!$C$73 -> 150 | F36: ='1_PANEL_CONTROL'!$C$73 -> 150 | G36: ='1_PANEL_CONTROL'!$C$73 -> 150 | H36: ='1_PANEL_CONTROL'!$C$73 -> 150 | I36: ='1_PANEL_CONTROL'!$C$73 -> 150 | J36: ='1_PANEL_CONTROL'!$C$73 -> 150 | K36: ='1_PANEL_CONTROL'!$C$73 -> 150 | ... CI36: ='1_PANEL_CONTROL'!$C$73 -> 150
A37: Asesoría Legal / Protección Datos | B37: EUR | C37: Fijo: '1_PANEL_CONTROL'!$C$74 | D37: ='1_PANEL_CONTROL'!$C$74 -> 200 | E37: ='1_PANEL_CONTROL'!$C$74 -> 200 | F37: ='1_PANEL_CONTROL'!$C$74 -> 200 | G37: ='1_PANEL_CONTROL'!$C$74 -> 200 | H37: ='1_PANEL_CONTROL'!$C$74 -> 200 | I37: ='1_PANEL_CONTROL'!$C$74 -> 200 | J37: ='1_PANEL_CONTROL'!$C$74 -> 200 | K37: ='1_PANEL_CONTROL'!$C$74 -> 200 | ... CI37: ='1_PANEL_CONTROL'!$C$74 -> 200
A38: Gastos de Banca y Comisiones | B38: EUR | C38: Fijo: '1_PANEL_CONTROL'!$C$75 | D38: ='1_PANEL_CONTROL'!$C$75 -> 50 | E38: ='1_PANEL_CONTROL'!$C$75 -> 50 | F38: ='1_PANEL_CONTROL'!$C$75 -> 50 | G38: ='1_PANEL_CONTROL'!$C$75 -> 50 | H38: ='1_PANEL_CONTROL'!$C$75 -> 50 | I38: ='1_PANEL_CONTROL'!$C$75 -> 50 | J38: ='1_PANEL_CONTROL'!$C$75 -> 50 | K38: ='1_PANEL_CONTROL'!$C$75 -> 50 | ... CI38: ='1_PANEL_CONTROL'!$C$75 -> 50
A39: Viajes y Gastos de Representación | B39: EUR | C39: Fijo: '1_PANEL_CONTROL'!$C$76 | D39: ='1_PANEL_CONTROL'!$C$76 -> 100 | E39: ='1_PANEL_CONTROL'!$C$76 -> 100 | F39: ='1_PANEL_CONTROL'!$C$76 -> 100 | G39: ='1_PANEL_CONTROL'!$C$76 -> 100 | H39: ='1_PANEL_CONTROL'!$C$76 -> 100 | I39: ='1_PANEL_CONTROL'!$C$76 -> 100 | J39: ='1_PANEL_CONTROL'!$C$76 -> 100 | K39: ='1_PANEL_CONTROL'!$C$76 -> 100 | ... CI39: ='1_PANEL_CONTROL'!$C$76 -> 100
A40: Seguros Operativos (RC + Ciber) | B40: EUR | C40: Fijo: '1_PANEL_CONTROL'!$C$77 | D40: ='1_PANEL_CONTROL'!$C$77 -> 46.67 | E40: ='1_PANEL_CONTROL'!$C$77 -> 46.67 | F40: ='1_PANEL_CONTROL'!$C$77 -> 46.67 | G40: ='1_PANEL_CONTROL'!$C$77 -> 46.67 | H40: ='1_PANEL_CONTROL'!$C$77 -> 46.67 | I40: ='1_PANEL_CONTROL'!$C$77 -> 46.67 | J40: ='1_PANEL_CONTROL'!$C$77 -> 46.67 | K40: ='1_PANEL_CONTROL'!$C$77 -> 46.67 | ... CI40: ='1_PANEL_CONTROL'!$C$77 -> 46.67
A41: I+D, Optimización de IA y Contingencia IT | B41: EUR | C41: Variable: C78 + 3.00€/cli | D41: ='1_PANEL_CONTROL'!$C$78 + '5_DETALLE_INGRESOS'!D18 * 3 -> 357.14 | E41: ='1_PANEL_CONTROL'!$C$78 + '5_DETALLE_INGRESOS'!E18 * 3 -> 498.14 | F41: ='1_PANEL_CONTROL'!$C$78 + '5_DETALLE_INGRESOS'!F18 * 3 -> 642.14 | G41: ='1_PANEL_CONTROL'!$C$78 + '5_DETALLE_INGRESOS'!G18 * 3 -> 789.14 | H41: ='1_PANEL_CONTROL'!$C$78 + '5_DETALLE_INGRESOS'!H18 * 3 -> 942.14 | I41: ='1_PANEL_CONTROL'!$C$78 + '5_DETALLE_INGRESOS'!I18 * 3 -> 1101.14 | J41: ='1_PANEL_CONTROL'!$C$78 + '5_DETALLE_INGRESOS'!J18 * 3 -> 1266.14 | K41: ='1_PANEL_CONTROL'!$C$78 + '5_DETALLE_INGRESOS'!K18 * 3 -> 1437.14 | ... CI41: ='1_PANEL_CONTROL'!$C$78 + '5_DETALLE_INGRESOS'!CI18 * 3 -> 610599.14
A42: Fondo de Cobertura de Devoluciones (5%) | B42: EUR | C42: Fijo: '1_PANEL_CONTROL'!$C$79 | D42: ='1_PANEL_CONTROL'!$C$79 -> 50 | E42: ='1_PANEL_CONTROL'!$C$79 -> 50 | F42: ='1_PANEL_CONTROL'!$C$79 -> 50 | G42: ='1_PANEL_CONTROL'!$C$79 -> 50 | H42: ='1_PANEL_CONTROL'!$C$79 -> 50 | I42: ='1_PANEL_CONTROL'!$C$79 -> 50 | J42: ='1_PANEL_CONTROL'!$C$79 -> 50 | K42: ='1_PANEL_CONTROL'!$C$79 -> 50 | ... CI42: ='1_PANEL_CONTROL'!$C$79 -> 50
A43: Material Promocional - Welcome Packs | B43: EUR | C43: Variable: '1_PANEL_CONTROL'!$C$81 en M2 | D43: =IF('7_EQUIPO_RRHH'!D$8=2, '1_PANEL_CONTROL'!$C$81, 0) -> 0 | E43: =IF('7_EQUIPO_RRHH'!E$8=2, '1_PANEL_CONTROL'!$C$81, 0) -> 3865 | F43: =IF('7_EQUIPO_RRHH'!F$8=2, '1_PANEL_CONTROL'!$C$81, 0) -> 0 | G43: =IF('7_EQUIPO_RRHH'!G$8=2, '1_PANEL_CONTROL'!$C$81, 0) -> 0 | H43: =IF('7_EQUIPO_RRHH'!H$8=2, '1_PANEL_CONTROL'!$C$81, 0) -> 0 | I43: =IF('7_EQUIPO_RRHH'!I$8=2, '1_PANEL_CONTROL'!$C$81, 0) -> 0 | J43: =IF('7_EQUIPO_RRHH'!J$8=2, '1_PANEL_CONTROL'!$C$81, 0) -> 0 | K43: =IF('7_EQUIPO_RRHH'!K$8=2, '1_PANEL_CONTROL'!$C$81, 0) -> 0 | ... CI43: =IF('7_EQUIPO_RRHH'!CI$8=2, '1_PANEL_CONTROL'!$C$81, 0) -> 0
A44: Stand Modular Iberzoo+Propet (IFEMA) | B44: EUR | C44: Variable: '1_PANEL_CONTROL'!$C$82 en M3 | D44: =IF('7_EQUIPO_RRHH'!D$8=3, '1_PANEL_CONTROL'!$C$82, 0) -> 0 | E44: =IF('7_EQUIPO_RRHH'!E$8=3, '1_PANEL_CONTROL'!$C$82, 0) -> 0 | F44: =IF('7_EQUIPO_RRHH'!F$8=3, '1_PANEL_CONTROL'!$C$82, 0) -> 3146.85 | G44: =IF('7_EQUIPO_RRHH'!G$8=3, '1_PANEL_CONTROL'!$C$82, 0) -> 0 | H44: =IF('7_EQUIPO_RRHH'!H$8=3, '1_PANEL_CONTROL'!$C$82, 0) -> 0 | I44: =IF('7_EQUIPO_RRHH'!I$8=3, '1_PANEL_CONTROL'!$C$82, 0) -> 0 | J44: =IF('7_EQUIPO_RRHH'!J$8=3, '1_PANEL_CONTROL'!$C$82, 0) -> 0 | K44: =IF('7_EQUIPO_RRHH'!K$8=3, '1_PANEL_CONTROL'!$C$82, 0) -> 0 | ... CI44: =IF('7_EQUIPO_RRHH'!CI$8=3, '1_PANEL_CONTROL'!$C$82, 0) -> 0
A45: Stand Modular Congreso AVEPA-SEVC (CCIB) | B45: EUR | C45: Variable: '1_PANEL_CONTROL'!$C$83 en M10 | D45: =IF('7_EQUIPO_RRHH'!D$8=10, '1_PANEL_CONTROL'!$C$83, 0) -> 0 | E45: =IF('7_EQUIPO_RRHH'!E$8=10, '1_PANEL_CONTROL'!$C$83, 0) -> 0 | F45: =IF('7_EQUIPO_RRHH'!F$8=10, '1_PANEL_CONTROL'!$C$83, 0) -> 0 | G45: =IF('7_EQUIPO_RRHH'!G$8=10, '1_PANEL_CONTROL'!$C$83, 0) -> 0 | H45: =IF('7_EQUIPO_RRHH'!H$8=10, '1_PANEL_CONTROL'!$C$83, 0) -> 0 | I45: =IF('7_EQUIPO_RRHH'!I$8=10, '1_PANEL_CONTROL'!$C$83, 0) -> 0 | J45: =IF('7_EQUIPO_RRHH'!J$8=10, '1_PANEL_CONTROL'!$C$83, 0) -> 0 | K45: =IF('7_EQUIPO_RRHH'!K$8=10, '1_PANEL_CONTROL'!$C$83, 0) -> 0 | ... CI45: =IF('7_EQUIPO_RRHH'!CI$8=10, '1_PANEL_CONTROL'!$C$83, 0) -> 0
A46: Amortización de Inmovilizado (CAPEX) | B46: EUR | C46: Amortización: Link a CAPEX_CAJA | D46: ='9_FLUJO_CAJA'!D22 -> 0 | E46: ='9_FLUJO_CAJA'!E22 -> 0 | F46: ='9_FLUJO_CAJA'!F22 -> 0 | G46: ='9_FLUJO_CAJA'!G22 -> 0 | H46: ='9_FLUJO_CAJA'!H22 -> 0 | I46: ='9_FLUJO_CAJA'!I22 -> 0 | J46: ='9_FLUJO_CAJA'!J22 -> 0 | K46: ='9_FLUJO_CAJA'!K22 -> 0 | ... CI46: ='9_FLUJO_CAJA'!CI22 -> 0
A47: TOTAL GASTOS OPEX RECURRENTES | B47: EUR | C47: Total: =SUM(Líneas) | D47: =SUM(D10:D45) -> 21799.58 | E47: =SUM(E10:E45) -> 25805.58 | F47: =SUM(F10:F45) -> 25231.43 | G47: =SUM(G10:G45) -> 22231.58 | H47: =SUM(H10:H45) -> 22384.58 | I47: =SUM(I10:I45) -> 22543.58 | J47: =SUM(J10:J45) -> 22708.58 | K47: =SUM(K10:K45) -> 22879.58 | ... CI47: =SUM(CI10:CI45) -> 654022.16
B49: GUÍA DE GASTOS DE EXPLOTACIÓN FIJOS (OPEX)
B50: 1. DETALLE DE GASTOS DE ESTRUCTURA Y SOFTWARE SaaS: - Coworking: 2.160 €/mes en Aticco Bogatell para albergar de forma flexible al equipo en Barcelona (6 puestos). - Marketing Digital (Ads): Inversión recurrente en pauta publicitaria para mantener el flujo constante de leads. - Software SaaS: Licencias reales de HubSpot CRM (400 €/mes) y Semrush Pro (250 €/mes) para la estrategia SEO. 2. SERVICIOS PROFESIONALES Y LEGALES: - Asesoría fiscal (150 €/mes) y DPO externo para RGPD y privacidad de datos de mascotas (200 €/mes) incluidos.

Sheet 9_FLUJO_CAJA
A4: PLAN DE INVERSIONES (CAPEX) Y ESTADO DE FLUJOS DE CAJA
A5: Escenario Activo: | B5: =CHOOSE('1_PANEL_CONTROL'!$C$4, "🔴 1: NEGATIVO", "🟡 2: EQUILIBRIO", "🟢 3: POSITIVO") -> 🟡 2: EQUILIBRIO | D5: =CHOOSE('1_PANEL_CONTROL'!$C$4, "[NEGATIVO] PLAN DE CAJA Y FLUJO NETO. El burn rate mensual drena la liquidez, cerrando el mes 12 con una caja final acumulada de " & TEXT('9_FLUJO_CAJA'!O37, "#.##0 €") & ", requiriendo aportes adicionales.", "[EQUILIBRIO] PLAN DE CAJA Y FLUJO NETO. Solvencia con caja inicial de " & TEXT('9_FLUJO_CAJA'!D25, "#.##0 €") & " y ENISA en mes 1, cerrando el mes 12 con una caja positiva acumulada de " & TEXT('9_FLUJO_CAJA'!O37, "#.##0 €") & ".", "[POSITIVO] PLAN DE CAJA Y FLUJO NETO. Sólida posición de caja de " & TEXT('9_FLUJO_CAJA'!O37, "#.##0 €") & " a final de Año 1, impulsada por aportes de Venture Capital de " & TEXT('13_CAP_TABLE_FINANCIACION'!E9, "#.##0 €") & ".") -> [EQUILIBRIO] PLAN DE CAJA Y FLUJO NETO. Solvencia con caja inicial de 0 € y ENISA en mes 1, cerrando el mes 12 con una caja positiva acumulada de 185.648 €.
A7: Partida CAPEX / Flujo | B7: Unidad | C7: Regla de Cálculo | D7: Ene-26 | E7: Feb-26 | F7: Mar-26 | G7: Abr-26 | H7: May-26 | I7: Jun-26 | J7: Jul-26 | K7: Ago-26 | L7: Sep-26 | M7: Oct-26 | N7: Nov-26 | O7: Dic-26 | P7: Ene-27 | Q7: Feb-27 | R7: Mar-27 | S7: Abr-27 | T7: May-27 | U7: Jun-27 | V7: Jul-27 | W7: Ago-27 | X7: Sep-27 | Y7: Oct-27 | Z7: Nov-27 | AA7: Dic-27 | AB7: Ene-28 | AC7: Feb-28 | AD7: Mar-28 | AE7: Abr-28 | AF7: May-28 | AG7: Jun-28 | AH7: Jul-28 | AI7: Ago-28 | AJ7: Sep-28 | AK7: Oct-28 | AL7: Nov-28 | AM7: Dic-28 | AN7: Ene-29 | AO7: Feb-29 | AP7: Mar-29 | AQ7: Abr-29 | AR7: May-29 | AS7: Jun-29 | AT7: Jul-29 | AU7: Ago-29 | AV7: Sep-29 | AW7: Oct-29 | AX7: Nov-29 | AY7: Dic-29 | AZ7: Ene-30 | BA7: Feb-30 | BB7: Mar-30 | BC7: Abr-30 | BD7: May-30 | BE7: Jun-30 | BF7: Jul-30 | BG7: Ago-30 | BH7: Sep-30 | BI7: Oct-30 | BJ7: Nov-30 | BK7: Dic-30 | BL7: Ene-31 | BM7: Feb-31 | BN7: Mar-31 | BO7: Abr-31 | BP7: May-31 | BQ7: Jun-31 | BR7: Jul-31 | BS7: Ago-31 | BT7: Sep-31 | BU7: Oct-31 | BV7: Nov-31 | BW7: Dic-31 | BX7: Ene-32 | BY7: Feb-32 | BZ7: Mar-32 | CA7: Abr-32 | CB7: May-32 | CC7: Jun-32 | CD7: Jul-32 | CE7: Ago-32 | CF7: Sep-32 | CG7: Oct-32 | CH7: Nov-32 | CI7: Dic-32
A10: Equipos Informáticos / Hardware | B10: EUR | C10: '1_PANEL_CONTROL'!C86 en M1 | D10: =IF('7_EQUIPO_RRHH'!D$8=1, '1_PANEL_CONTROL'!$C$86, 0) -> 10196 | E10: =IF('7_EQUIPO_RRHH'!E$8=1, '1_PANEL_CONTROL'!$C$86, 0) -> 0 | F10: =IF('7_EQUIPO_RRHH'!F$8=1, '1_PANEL_CONTROL'!$C$86, 0) -> 0 | G10: =IF('7_EQUIPO_RRHH'!G$8=1, '1_PANEL_CONTROL'!$C$86, 0) -> 0 | H10: =IF('7_EQUIPO_RRHH'!H$8=1, '1_PANEL_CONTROL'!$C$86, 0) -> 0 | I10: =IF('7_EQUIPO_RRHH'!I$8=1, '1_PANEL_CONTROL'!$C$86, 0) -> 0 | J10: =IF('7_EQUIPO_RRHH'!J$8=1, '1_PANEL_CONTROL'!$C$86, 0) -> 0 | K10: =IF('7_EQUIPO_RRHH'!K$8=1, '1_PANEL_CONTROL'!$C$86, 0) -> 0 | ... CI10: =IF('7_EQUIPO_RRHH'!CI$8=1, '1_PANEL_CONTROL'!$C$86, 0) -> 0
A11: Desarrollo de la Plataforma | B11: EUR | C11: '1_PANEL_CONTROL'!C87 en M1 | D11: =IF('7_EQUIPO_RRHH'!D$8=1, '1_PANEL_CONTROL'!$C$87, 0) -> 17150 | E11: =IF('7_EQUIPO_RRHH'!E$8=1, '1_PANEL_CONTROL'!$C$87, 0) -> 0 | F11: =IF('7_EQUIPO_RRHH'!F$8=1, '1_PANEL_CONTROL'!$C$87, 0) -> 0 | G11: =IF('7_EQUIPO_RRHH'!G$8=1, '1_PANEL_CONTROL'!$C$87, 0) -> 0 | H11: =IF('7_EQUIPO_RRHH'!H$8=1, '1_PANEL_CONTROL'!$C$87, 0) -> 0 | I11: =IF('7_EQUIPO_RRHH'!I$8=1, '1_PANEL_CONTROL'!$C$87, 0) -> 0 | J11: =IF('7_EQUIPO_RRHH'!J$8=1, '1_PANEL_CONTROL'!$C$87, 0) -> 0 | K11: =IF('7_EQUIPO_RRHH'!K$8=1, '1_PANEL_CONTROL'!$C$87, 0) -> 0 | ... CI11: =IF('7_EQUIPO_RRHH'!CI$8=1, '1_PANEL_CONTROL'!$C$87, 0) -> 0
A12: Licencias y Setup Inicial | B12: EUR | C12: '1_PANEL_CONTROL'!C88 en M1 | D12: =IF('7_EQUIPO_RRHH'!D$8=1, '1_PANEL_CONTROL'!$C$88, 0) -> 1500 | E12: =IF('7_EQUIPO_RRHH'!E$8=1, '1_PANEL_CONTROL'!$C$88, 0) -> 0 | F12: =IF('7_EQUIPO_RRHH'!F$8=1, '1_PANEL_CONTROL'!$C$88, 0) -> 0 | G12: =IF('7_EQUIPO_RRHH'!G$8=1, '1_PANEL_CONTROL'!$C$88, 0) -> 0 | H12: =IF('7_EQUIPO_RRHH'!H$8=1, '1_PANEL_CONTROL'!$C$88, 0) -> 0 | I12: =IF('7_EQUIPO_RRHH'!I$8=1, '1_PANEL_CONTROL'!$C$88, 0) -> 0 | J12: =IF('7_EQUIPO_RRHH'!J$8=1, '1_PANEL_CONTROL'!$C$88, 0) -> 0 | K12: =IF('7_EQUIPO_RRHH'!K$8=1, '1_PANEL_CONTROL'!$C$88, 0) -> 0 | ... CI12: =IF('7_EQUIPO_RRHH'!CI$8=1, '1_PANEL_CONTROL'!$C$88, 0) -> 0
A13: Registro de Propiedad Industrial | B13: EUR | C13: '1_PANEL_CONTROL'!C89 en M1 | D13: =IF('7_EQUIPO_RRHH'!D$8=1, '1_PANEL_CONTROL'!$C$89, 0) -> 0 | E13: =IF('7_EQUIPO_RRHH'!E$8=1, '1_PANEL_CONTROL'!$C$89, 0) -> 0 | F13: =IF('7_EQUIPO_RRHH'!F$8=1, '1_PANEL_CONTROL'!$C$89, 0) -> 0 | G13: =IF('7_EQUIPO_RRHH'!G$8=1, '1_PANEL_CONTROL'!$C$89, 0) -> 0 | H13: =IF('7_EQUIPO_RRHH'!H$8=1, '1_PANEL_CONTROL'!$C$89, 0) -> 0 | I13: =IF('7_EQUIPO_RRHH'!I$8=1, '1_PANEL_CONTROL'!$C$89, 0) -> 0 | J13: =IF('7_EQUIPO_RRHH'!J$8=1, '1_PANEL_CONTROL'!$C$89, 0) -> 0 | K13: =IF('7_EQUIPO_RRHH'!K$8=1, '1_PANEL_CONTROL'!$C$89, 0) -> 0 | ... CI13: =IF('7_EQUIPO_RRHH'!CI$8=1, '1_PANEL_CONTROL'!$C$89, 0) -> 0
A14: Cumplimiento de Privacidad y RGPD | B14: EUR | C14: '1_PANEL_CONTROL'!C90 en M1 | D14: =IF('7_EQUIPO_RRHH'!D$8=1, '1_PANEL_CONTROL'!$C$90, 0) -> 15000 | E14: =IF('7_EQUIPO_RRHH'!E$8=1, '1_PANEL_CONTROL'!$C$90, 0) -> 0 | F14: =IF('7_EQUIPO_RRHH'!F$8=1, '1_PANEL_CONTROL'!$C$90, 0) -> 0 | G14: =IF('7_EQUIPO_RRHH'!G$8=1, '1_PANEL_CONTROL'!$C$90, 0) -> 0 | H14: =IF('7_EQUIPO_RRHH'!H$8=1, '1_PANEL_CONTROL'!$C$90, 0) -> 0 | I14: =IF('7_EQUIPO_RRHH'!I$8=1, '1_PANEL_CONTROL'!$C$90, 0) -> 0 | J14: =IF('7_EQUIPO_RRHH'!J$8=1, '1_PANEL_CONTROL'!$C$90, 0) -> 0 | K14: =IF('7_EQUIPO_RRHH'!K$8=1, '1_PANEL_CONTROL'!$C$90, 0) -> 0 | ... CI14: =IF('7_EQUIPO_RRHH'!CI$8=1, '1_PANEL_CONTROL'!$C$90, 0) -> 0
A15: Homologación y Certificación HW | B15: EUR | C15: '1_PANEL_CONTROL'!C91 en M1 | D15: =IF('7_EQUIPO_RRHH'!D$8=1, '1_PANEL_CONTROL'!$C$91, 0) -> 0 | E15: =IF('7_EQUIPO_RRHH'!E$8=1, '1_PANEL_CONTROL'!$C$91, 0) -> 0 | F15: =IF('7_EQUIPO_RRHH'!F$8=1, '1_PANEL_CONTROL'!$C$91, 0) -> 0 | G15: =IF('7_EQUIPO_RRHH'!G$8=1, '1_PANEL_CONTROL'!$C$91, 0) -> 0 | H15: =IF('7_EQUIPO_RRHH'!H$8=1, '1_PANEL_CONTROL'!$C$91, 0) -> 0 | I15: =IF('7_EQUIPO_RRHH'!I$8=1, '1_PANEL_CONTROL'!$C$91, 0) -> 0 | J15: =IF('7_EQUIPO_RRHH'!J$8=1, '1_PANEL_CONTROL'!$C$91, 0) -> 0 | K15: =IF('7_EQUIPO_RRHH'!K$8=1, '1_PANEL_CONTROL'!$C$91, 0) -> 0 | ... CI15: =IF('7_EQUIPO_RRHH'!CI$8=1, '1_PANEL_CONTROL'!$C$91, 0) -> 0
A16: TOTAL INVERSIONES DEL PERIODO (CAPEX) | B16: EUR | C16: SUMA(Líneas) | D16: =SUM(D10:D15) -> 43846 | E16: =SUM(E10:E15) -> 0 | F16: =SUM(F10:F15) -> 0 | G16: =SUM(G10:G15) -> 0 | H16: =SUM(H10:H15) -> 0 | I16: =SUM(I10:I15) -> 0 | J16: =SUM(J10:J15) -> 0 | K16: =SUM(K10:K15) -> 0 | ... CI16: =SUM(CI10:CI15) -> 0
A17: Amort. Equipos Informáticos | B17: EUR | C17: CAPEX/Periodo | D17: =IF(SUM($D$10:$CI$10)>0, SUM($D$10:$CI$10)/('1_PANEL_CONTROL'!$C$10), 0) -> 169.93333 | E17: =IF(SUM($D$10:$CI$10)>0, SUM($D$10:$CI$10)/('1_PANEL_CONTROL'!$C$10), 0) -> 169.93333 | F17: =IF(SUM($D$10:$CI$10)>0, SUM($D$10:$CI$10)/('1_PANEL_CONTROL'!$C$10), 0) -> 169.93333 | G17: =IF(SUM($D$10:$CI$10)>0, SUM($D$10:$CI$10)/('1_PANEL_CONTROL'!$C$10), 0) -> 169.93333 | H17: =IF(SUM($D$10:$CI$10)>0, SUM($D$10:$CI$10)/('1_PANEL_CONTROL'!$C$10), 0) -> 169.93333 | I17: =IF(SUM($D$10:$CI$10)>0, SUM($D$10:$CI$10)/('1_PANEL_CONTROL'!$C$10), 0) -> 169.93333 | J17: =IF(SUM($D$10:$CI$10)>0, SUM($D$10:$CI$10)/('1_PANEL_CONTROL'!$C$10), 0) -> 169.93333 | K17: =IF(SUM($D$10:$CI$10)>0, SUM($D$10:$CI$10)/('1_PANEL_CONTROL'!$C$10), 0) -> 169.93333 | ... CI17: =IF(SUM($D$10:$CI$10)>0, SUM($D$10:$CI$10)/('1_PANEL_CONTROL'!$C$10), 0) -> 169.93333
A18: Amort. Desarrollo Plataforma | B18: EUR | C18: CAPEX/Periodo | D18: =IF(SUM($D$11:$CI$11)>0, SUM($D$11:$CI$11)/('1_PANEL_CONTROL'!$C$10), 0) -> 285.83333 | E18: =IF(SUM($D$11:$CI$11)>0, SUM($D$11:$CI$11)/('1_PANEL_CONTROL'!$C$10), 0) -> 285.83333 | F18: =IF(SUM($D$11:$CI$11)>0, SUM($D$11:$CI$11)/('1_PANEL_CONTROL'!$C$10), 0) -> 285.83333 | G18: =IF(SUM($D$11:$CI$11)>0, SUM($D$11:$CI$11)/('1_PANEL_CONTROL'!$C$10), 0) -> 285.83333 | H18: =IF(SUM($D$11:$CI$11)>0, SUM($D$11:$CI$11)/('1_PANEL_CONTROL'!$C$10), 0) -> 285.83333 | I18: =IF(SUM($D$11:$CI$11)>0, SUM($D$11:$CI$11)/('1_PANEL_CONTROL'!$C$10), 0) -> 285.83333 | J18: =IF(SUM($D$11:$CI$11)>0, SUM($D$11:$CI$11)/('1_PANEL_CONTROL'!$C$10), 0) -> 285.83333 | K18: =IF(SUM($D$11:$CI$11)>0, SUM($D$11:$CI$11)/('1_PANEL_CONTROL'!$C$10), 0) -> 285.83333 | ... CI18: =IF(SUM($D$11:$CI$11)>0, SUM($D$11:$CI$11)/('1_PANEL_CONTROL'!$C$10), 0) -> 285.83333
A19: Amort. Licencias y Setup | B19: EUR | C19: CAPEX/Periodo | D19: =IF(SUM($D$12:$CI$12)>0, SUM($D$12:$CI$12)/('1_PANEL_CONTROL'!$C$10), 0) -> 25 | E19: =IF(SUM($D$12:$CI$12)>0, SUM($D$12:$CI$12)/('1_PANEL_CONTROL'!$C$10), 0) -> 25 | F19: =IF(SUM($D$12:$CI$12)>0, SUM($D$12:$CI$12)/('1_PANEL_CONTROL'!$C$10), 0) -> 25 | G19: =IF(SUM($D$12:$CI$12)>0, SUM($D$12:$CI$12)/('1_PANEL_CONTROL'!$C$10), 0) -> 25 | H19: =IF(SUM($D$12:$CI$12)>0, SUM($D$12:$CI$12)/('1_PANEL_CONTROL'!$C$10), 0) -> 25 | I19: =IF(SUM($D$12:$CI$12)>0, SUM($D$12:$CI$12)/('1_PANEL_CONTROL'!$C$10), 0) -> 25 | J19: =IF(SUM($D$12:$CI$12)>0, SUM($D$12:$CI$12)/('1_PANEL_CONTROL'!$C$10), 0) -> 25 | K19: =IF(SUM($D$12:$CI$12)>0, SUM($D$12:$CI$12)/('1_PANEL_CONTROL'!$C$10), 0) -> 25 | ... CI19: =IF(SUM($D$12:$CI$12)>0, SUM($D$12:$CI$12)/('1_PANEL_CONTROL'!$C$10), 0) -> 25
A20: Amort. Propiedad Industrial | B20: EUR | C20: CAPEX/Periodo | D20: =IF(SUM($D$13:$CI$13)>0, SUM($D$13:$CI$13)/('1_PANEL_CONTROL'!$C$10), 0) -> 0 | E20: =IF(SUM($D$13:$CI$13)>0, SUM($D$13:$CI$13)/('1_PANEL_CONTROL'!$C$10), 0) -> 0 | F20: =IF(SUM($D$13:$CI$13)>0, SUM($D$13:$CI$13)/('1_PANEL_CONTROL'!$C$10), 0) -> 0 | G20: =IF(SUM($D$13:$CI$13)>0, SUM($D$13:$CI$13)/('1_PANEL_CONTROL'!$C$10), 0) -> 0 | H20: =IF(SUM($D$13:$CI$13)>0, SUM($D$13:$CI$13)/('1_PANEL_CONTROL'!$C$10), 0) -> 0 | I20: =IF(SUM($D$13:$CI$13)>0, SUM($D$13:$CI$13)/('1_PANEL_CONTROL'!$C$10), 0) -> 0 | J20: =IF(SUM($D$13:$CI$13)>0, SUM($D$13:$CI$13)/('1_PANEL_CONTROL'!$C$10), 0) -> 0 | K20: =IF(SUM($D$13:$CI$13)>0, SUM($D$13:$CI$13)/('1_PANEL_CONTROL'!$C$10), 0) -> 0 | ... CI20: =IF(SUM($D$13:$CI$13)>0, SUM($D$13:$CI$13)/('1_PANEL_CONTROL'!$C$10), 0) -> 0
A21: Amort. Privacidad y RGPD | B21: EUR | C21: CAPEX/Periodo | D21: =IF(SUM($D$14:$CI$14)>0, SUM($D$14:$CI$14)/('1_PANEL_CONTROL'!$C$10), 0) -> 250 | E21: =IF(SUM($D$14:$CI$14)>0, SUM($D$14:$CI$14)/('1_PANEL_CONTROL'!$C$10), 0) -> 250 | F21: =IF(SUM($D$14:$CI$14)>0, SUM($D$14:$CI$14)/('1_PANEL_CONTROL'!$C$10), 0) -> 250 | G21: =IF(SUM($D$14:$CI$14)>0, SUM($D$14:$CI$14)/('1_PANEL_CONTROL'!$C$10), 0) -> 250 | H21: =IF(SUM($D$14:$CI$14)>0, SUM($D$14:$CI$14)/('1_PANEL_CONTROL'!$C$10), 0) -> 250 | I21: =IF(SUM($D$14:$CI$14)>0, SUM($D$14:$CI$14)/('1_PANEL_CONTROL'!$C$10), 0) -> 250 | J21: =IF(SUM($D$14:$CI$14)>0, SUM($D$14:$CI$14)/('1_PANEL_CONTROL'!$C$10), 0) -> 250 | K21: =IF(SUM($D$14:$CI$14)>0, SUM($D$14:$CI$14)/('1_PANEL_CONTROL'!$C$10), 0) -> 250 | ... CI21: =IF(SUM($D$14:$CI$14)>0, SUM($D$14:$CI$14)/('1_PANEL_CONTROL'!$C$10), 0) -> 250
A22: Amort. Homologación y Certificación | B22: EUR | C22: CAPEX/Periodo | D22: =IF(SUM($D$15:$CI$15)>0, SUM($D$15:$CI$15)/('1_PANEL_CONTROL'!$C$10), 0) -> 0 | E22: =IF(SUM($D$15:$CI$15)>0, SUM($D$15:$CI$15)/('1_PANEL_CONTROL'!$C$10), 0) -> 0 | F22: =IF(SUM($D$15:$CI$15)>0, SUM($D$15:$CI$15)/('1_PANEL_CONTROL'!$C$10), 0) -> 0 | G22: =IF(SUM($D$15:$CI$15)>0, SUM($D$15:$CI$15)/('1_PANEL_CONTROL'!$C$10), 0) -> 0 | H22: =IF(SUM($D$15:$CI$15)>0, SUM($D$15:$CI$15)/('1_PANEL_CONTROL'!$C$10), 0) -> 0 | I22: =IF(SUM($D$15:$CI$15)>0, SUM($D$15:$CI$15)/('1_PANEL_CONTROL'!$C$10), 0) -> 0 | J22: =IF(SUM($D$15:$CI$15)>0, SUM($D$15:$CI$15)/('1_PANEL_CONTROL'!$C$10), 0) -> 0 | K22: =IF(SUM($D$15:$CI$15)>0, SUM($D$15:$CI$15)/('1_PANEL_CONTROL'!$C$10), 0) -> 0 | ... CI22: =IF(SUM($D$15:$CI$15)>0, SUM($D$15:$CI$15)/('1_PANEL_CONTROL'!$C$10), 0) -> 0
A23: TOTAL AMORTIZACIÓN MENSUAL (OPEX) | B23: EUR | C23: SUMA(Líneas) | D23: =SUM(D17:D22) -> 730.76667 | E23: =SUM(E17:E22) -> 730.76667 | F23: =SUM(F17:F22) -> 730.76667 | G23: =SUM(G17:G22) -> 730.76667 | H23: =SUM(H17:H22) -> 730.76667 | I23: =SUM(I17:I22) -> 730.76667 | J23: =SUM(J17:J22) -> 730.76667 | K23: =SUM(K17:K22) -> 730.76667 | ... CI23: =SUM(CI17:CI22) -> 730.76667
A24: Flujo de Caja - Estado Mensual
A25: Caja Inicial | B25: EUR | C25: Saldo al inicio del mes | D25: 0 | E25: =D37 -> 160450.5 | F25: =E37 -> 149647.02 | G25: =F37 -> 141181.73 | H25: =G37 -> 137729.82 | I25: =H37 -> 136145.73 | J25: =I37 -> 136580.66 | K25: =J37 -> 139002.5 | L25: =K37 -> 143637.25 | ... CI25: =CH37 -> 99530021
